Workbook

Sheet README
A1: Chamberlain Apartments — Live TIF / Tax Appeal Model
A3: Built by KA Asset Management — May 2026
A4: Methodology source: Ehlers tax appeal analysis (published in Chamberlain TIF Update, 11/8/25)
A5: Contractual source: Recorded Minimum Assessment Agreement (Hennepin County T05543322, 6/18/2018)
A7: PURPOSE
A8: Live version of the TIF/tax appeal economics in the November 2025 Chamberlain Investment Overview (pp.13–14). User inputs a taxable market value (TMV) for each pay year 2026–2044 in the Inputs_TMV tab. The model recalculates Net Tax Capacity, Total Tax Increment Available, net TIF Note payment after Admin (10%) and OSA (0.36%) holdbacks, full TIF Note amortization at 4.60% interest against $7,142,377 principal, and gross property tax liability. Scenario_Compare runs three appeal targets side-by-side over the full 19-year TIF life — the correct horizon, vs. the 10-year truncation in the IDP/Shaver April 2026 model.
A10: CONVENTIONS
A11: • BLUE font on YELLOW fill = user input (change these freely)
A12: • BLACK font = formula (do not edit)
A13: • GREEN font = cross-sheet link
A15: TABS
A16: 1. README — this page
... A34: MAA Floor = $43,835,000 (legally enforceable assessed-value floor through TIF maturity)

Sheet Assumptions
A1: Assumptions & Constants
A3: TIF MECHANICS
A4: Class Rate (apartments) | B4: 0.0125 | C4: MN 273.13 — apartments above first $100K at 1.25%
A5: Tax Capacity Rate (composite local) | B5: 1.27866 | C5: Composite city + county + school + special, ties to Ehlers: 176,312 ÷ 137,888 = 1.2787 ≈ 1.28 (rounding to 1.2787 produces exact Ehlers match)
A6: Developer Share of Increment | B6: 1 | C6: TIF Plan §IV — Developer receives 90% of captured tax increment
A7: Admin Holdback % | B7: 0.1 | C7: Ehlers: "After admin (10%): Net annual developer reduction = –$158,681"
A8: OSA TIF Fee % | B8: 0.0036 | C8: State Auditor TIF fee; applied to TIF before developer share per Ehlers methodology
A9: Original Frozen Net Tax Capacity (Base) | B9: 37179 | C9: TIF "Original Tax Capacity" was frozen at project inception (pre-construction, very low); set to 0 for Ehlers-consistent simplification (marginal calc unaffected). Adjust if exact figure needed.
A11: TIF NOTE
A12: TIF Note Original Principal | B12: 7142377 | C12: TIF Note face; constant across scenarios per Investment Overview pg 14
A13: TIF Note Interest Rate | B13: 0.046 | C13: Per executed TIF Note; matches IDP model B15
A14: TIF Note Contractual Maturity | B14: 2/1/2046 | C14: Recorded TIF Note maturity (TIF terminates upon Note retirement OR maturity)
A15: Beginning Balance (Pay-2026 Start) | B15: 7269118.6 | C15: Per Shaver Inputs!B5 1/1/2026 starting balance (matches IDP model exactly so direct comparison is apples-to-apples)
A17: VALUATION INPUTS
A18: MAA Floor (recorded) | B18: 43835000 | C18: MAA §4: "shall not be less than $43,835,000 as of January 2, 2021... and each January 2 thereafter until termination" (Hennepin Co. T05543322)
A19: Pay 2025 TMV (1H) | B19: 54866000 | C19: 1H-2025 actual
A20: Pay 2025 TMV (2H) | B20: 52150000 | C20: 2H-2025 actual — County has already reduced
A21: Pay 2026 TMV (County preliminary) | B21: 52151000 | C21: Per Shaver MV History attachment row "2026: 52,151,000" — this is the 2026 starting point, NOT $54.866M
A23: EHLERS PUBLISHED RESULTS (anchors for reconciliation)
A24: Ehlers TMV reduction modeled | B24: 11031000 | C24: $54.866M baseline minus $43.835M MAA floor (full reduction to floor)
A25: Ehlers NTC reduction (annual) | B25: 137888 | C25: $11,031,000 × 1.25%
A26: Ehlers gross TIF reduction (annual) | B26: 176312 | C26: 137,888 NTC × 1.28
A27: Ehlers net TIF reduction after Admin | B27: 158681 | C27: $176,312 × 90% (developer share applied to admin haircut per Ehlers)
A28: Ehlers 18-yr cumulative tax savings | B28: 2856258 | C28: $158,681 × 18 yrs (approx) per Chamberlain TIF Update PDF p.1
A29: Ehlers lifetime TIF principal reduction | B29: -180329 | C29: Slower amortization impact
A30: Ehlers net nominal benefit | B30: 2675929 | C30: $2,856,258 minus $180,329 ≈ $2.68M
A31: Ehlers NPV @ 5% | B31: 1100000 | C31: Approximate, per Ehlers
A33: DISCOUNT RATE FOR NPV
A34: Discount Rate | B34: 0.05 | C34: Match Ehlers @ 5%. The IDP/Shaver model uses 8%, which understates TIF NPV by discounting at a higher rate than the TIF Note actually carries (4.60%).

Sheet Inputs_TMV
A1: Taxable Market Value Inputs by Scenario
A2: Edit YELLOW cells to change the TMV assumption for any year. Default values reflect: Current = $54.866M held flat (KA Nov-2025 baseline); Mid = $52.15M held flat (the IDP-claimed appeal target — note: County has already set 2026 at $52.151M); Aggressive = $50.0M held flat (KA Investment Overview pg 14 appeal scenario); plus a fourth column showing the Ehlers MAA-floor stress test at $43.835M.
A4: Pay Year | B4: Scenario 1: Current ($54.866M flat) | C4: Scenario 2: Mid Appeal ($52.15M flat) | D4: Scenario 3: Aggressive Appeal ($50.0M flat) | E4: Scenario 4: MAA Floor (Ehlers) ($43.835M flat)
A5: 2026 | B5: 54866000 | C5: 52150000 | D5: 50000000 | E5: 43835000
A6: 2027 | B6: 54866000 | C6: 52150000 | D6: 50000000 | E6: 43835000
A7: 2028 | B7: 54866000 | C7: 52150000 | D7: 50000000 | E7: 43835000
A8: 2029 | B8: 54866000 | C8: 52150000 | D8: 50000000 | E8: 43835000
A9: 2030 | B9: 54866000 | C9: 52150000 | D9: 50000000 | E9: 43835000
A10: 2031 | B10: 54866000 | C10: 52150000 | D10: 50000000 | E10: 43835000
A11: 2032 | B11: 54866000 | C11: 52150000 | D11: 50000000 | E11: 43835000
A12: 2033 | B12: 54866000 | C12: 52150000 | D12: 50000000 | E12: 43835000
A13: 2034 | B13: 54866000 | C13: 52150000 | D13: 50000000 | E13: 43835000
A14: 2035 | B14: 54866000 | C14: 52150000 | D14: 50000000 | E14: 43835000
A15: 2036 | B15: 54866000 | C15: 52150000 | D15: 50000000 | E15: 43835000
A16: 2037 | B16: 54866000 | C16: 52150000 | D16: 50000000 | E16: 43835000
... A23: 2044 | B23: 54866000 | C23: 52150000 | D23: 50000000 | E23: 43835000
A24: QUICK TESTS:
A25: • To replicate Shaver's stated scenario exactly (Mid Appeal): set ALL Mid Appeal cells (C5:C23) to $52,150,000. Engine_Mid_Appeal then shows the truth: even at flat $52.15M, net benefit vs. Current is $159K nominal / $101K NPV (positive, not negative).
A26: • To replicate KA Nov-2025 'Aggressive Appeal $50M' scenario: set ALL Aggressive cells (D5:D23) to $50,000,000. Engine_Agg_Appeal shows TIF payoff in 2042 (matches KA Nov-2025: 2/1/2044 within rounding) and net benefit of $285K nominal / $182K NPV.
A27: • To replicate Ehlers MAA-Floor stress test: set ALL MAA cells (E5:E23) to $43,835,000. Engine_MAA_Floor reproduces Ehlers' $158,681/yr net TIF reduction exactly (see Ehlers_Recon tab).
A28: • To test market growth: enter increasing TMVs by year (e.g., 2026=$50M, 2027=$51M, 2028=$52M, etc.). The model accepts any TMV schedule.
A29: • To test partial appeals (only some years successful): set Mid Appeal years 2026-2028 to $52.15M and 2029-2044 back to $54.866M. Model accounts for partial-period appeals.

Sheet Attorney_Fees
A1: Attorney Fees — Per Scenario
A2: IDP/Shaver applies a 25% fee to EVERY year of tax savings (overstates ~19x). MN contingency norm: 25% of FIRST-YEAR savings per successful petition. Set Pay Year for each appeal below — fees auto-compute per scenario based on each scenario's TMV reduction. To disable an appeal, clear its Pay Year cell.
A4: GLOBAL FEE PARAMETERS
A5: Contingency Fee % (of tax savings) | B5: 0.25
A6: Years of Savings per Appeal | B6: 1
A8: SCENARIO REFERENCE (TMVs from Inputs_TMV row 5)
A9: Scenario | B9: Reference TMV | C9: Annual Tax Savings vs. Current | D9: Fee per Appeal
A10: Current ($54.866M baseline) | B10: =Inputs_TMV!B5 -> 54866000 | C10: 0 | D10: 0
A11: Mid Appeal ($52.15M) | B11: =Inputs_TMV!C5 -> 52150000 | C11: =(B10-B11)*Assumptions!$B$4*Assumptions!$B$5 -> 43410.507 | D11: =C11*Attorney_Fees!$B$6*Attorney_Fees!$B$5 -> 10852.627
A12: Aggressive Appeal ($50.0M) | B12: =Inputs_TMV!D5 -> 50000000 | C12: =(B10-B12)*Assumptions!$B$4*Assumptions!$B$5 -> 77774.495 | D12: =C12*Attorney_Fees!$B$6*Attorney_Fees!$B$5 -> 19443.624
A13: MAA Floor ($43.835M) | B13: =Inputs_TMV!E5 -> 43835000 | C13: =(B10-B13)*Assumptions!$B$4*Assumptions!$B$5 -> 176311.23 | D13: =C13*Attorney_Fees!$B$6*Attorney_Fees!$B$5 -> 44077.808
A15: APPEAL EVENT SCHEDULE
A16: Appeal Event | B16: Pay Year | C16: Fee — Mid | D16: Fee — Agg | E16: Fee — MAA | F16: Disc Factor | G16: Notes
A17: Current Appeal | B17: 2026 | C17: =IF(AND(ISNUMBER(B17),B17>=2026,B17<=2044),Attorney_Fees!$D$11,0) -> 10852.627 | D17: =IF(AND(ISNUMBER(B17),B17>=2026,B17<=2044),Attorney_Fees!$D$12,0) -> 19443.624 | E17: =IF(AND(ISNUMBER(B17),B17>=2026,B17<=2044),Attorney_Fees!$D$13,0) -> 44077.808 | F17: =IF(ISNUMBER(B17),1/(1+Assumptions!$B$34)^(B17-2026),0) -> 1 | G17: In-flight 2025-pay-2026 petition
A18: 2nd Appeal | B18: 2030 | C18: =IF(AND(ISNUMBER(B18),B18>=2026,B18<=2044),Attorney_Fees!$D$11,0) -> 10852.627 | D18: =IF(AND(ISNUMBER(B18),B18>=2026,B18<=2044),Attorney_Fees!$D$12,0) -> 19443.624 | E18: =IF(AND(ISNUMBER(B18),B18>=2026,B18<=2044),Attorney_Fees!$D$13,0) -> 44077.808 | F18: =IF(ISNUMBER(B18),1/(1+Assumptions!$B$34)^(B18-2026),0) -> 0.82270247 | G18: Mid-hold reassessment
A19: 3rd Appeal | B19: 2036 | C19: =IF(AND(ISNUMBER(B19),B19>=2026,B19<=2044),Attorney_Fees!$D$11,0) -> 10852.627 | D19: =IF(AND(ISNUMBER(B19),B19>=2026,B19<=2044),Attorney_Fees!$D$12,0) -> 19443.624 | E19: =IF(AND(ISNUMBER(B19),B19>=2026,B19<=2044),Attorney_Fees!$D$13,0) -> 44077.808 | F19: =IF(ISNUMBER(B19),1/(1+Assumptions!$B$34)^(B19-2026),0) -> 0.61391325 | G19: Late-hold reassessment
A20: (custom) | C20: =IF(AND(ISNUMBER(B20),B20>=2026,B20<=2044),Attorney_Fees!$D$11,0) -> 0 | D20: =IF(AND(ISNUMBER(B20),B20>=2026,B20<=2044),Attorney_Fees!$D$12,0) -> 0 | E20: =IF(AND(ISNUMBER(B20),B20>=2026,B20<=2044),Attorney_Fees!$D$13,0) -> 0 | F20: =IF(ISNUMBER(B20),1/(1+Assumptions!$B$34)^(B20-2026),0) -> 0 | G20: Add events as needed
A21: (custom) | C21: =IF(AND(ISNUMBER(B21),B21>=2026,B21<=2044),Attorney_Fees!$D$11,0) -> 0 | D21: =IF(AND(ISNUMBER(B21),B21>=2026,B21<=2044),Attorney_Fees!$D$12,0) -> 0 | E21: =IF(AND(ISNUMBER(B21),B21>=2026,B21<=2044),Attorney_Fees!$D$13,0) -> 0 | F21: =IF(ISNUMBER(B21),1/(1+Assumptions!$B$34)^(B21-2026),0) -> 0
A23: TOTAL FEES BY SCENARIO
B24: Current | C24: Mid | D24: Agg | E24: MAA
A25: Total Fees — Nominal | B25: 0 | C25: =SUM(C17:C21) -> 32557.88 | D25: =SUM(D17:D21) -> 58330.871 | E25: =SUM(E17:E21) -> 132233.42
A26: Total Fees — NPV @ DiscRate | B26: 0 | C26: =SUMPRODUCT(C17:C21,F17:F21) -> 26443.681 | D26: =SUMPRODUCT(D17:D21,F17:F21) -> 47376.639 | E26: =SUMPRODUCT(E17:E21,F17:F21) -> 107400.68
A28: COMPARISON TO IDP/SHAVER FEE TREATMENT
A29: Shaver Cash Savings total fees (10-yr) | B29: 373694 | C29: Shaver Investor_Summary B12 — applied EVERY year of his 10-yr horizon
A30: This model — Agg, 3 appeals (default) | B30: =Attorney_Fees!$D$25 -> 58330.871 | C30: 3 events × 25% × first-year savings — only in appeal years
A31: Shaver overstates fees by | B31: =Attorney_Fees!$B$29-Attorney_Fees!$D$25 -> 315363.13 | C31: =Attorney_Fees!$B$29/Attorney_Fees!$D$25 -> 6.4064533 | D31: ← multiple
A33: KEY TAKEAWAY: Even applying the correct industry-standard fee structure (25% × first-year savings × 3 appeal events over 19 years), every appeal scenario remains net-positive on Scenario_Compare. Shaver's $373K fee is structurally wrong — it treats fees as recurring annual costs, not contingency events.

Sheet Engine_Current
A1: Engine — Scenario 1: Current ($54.866M flat)
A2: All TMV figures linked from Inputs_TMV tab. All constants linked from Assumptions tab. Methodology: Ehlers (Chamberlain TIF Update, 11/8/25).
A4: Pay Year | B4: TMV | C4: NTC | D4: Captured NTC | E4: Total Tax Increment | F4: Less OSA | G4: Less Admin | H4: Developer Share | I4: Net TIF to Developer | J4: Note Beg Bal | K4: Note Interest | L4: Note Principal Pmt | M4: Note End Bal | N4: Total Property Tax
B5: (input) | C5: TMV × ClassRate | D5: NTC − BaseNTC | E5: Captured × TaxCapRate | F5: × 0.36% | G5: × 10% | H5: × 90% | I5: TI × (1−OSA) × (1−Admin) × DevShare | K5: BegBal × 4.60% | L5: MIN(TIF − Int, Bal) | M5: Beg + Int − TIF (floored at 0) | N5: NTC × TaxCapRate (full burden)
A6: =Inputs_TMV!$A$5 -> 2026 | B6: =Inputs_TMV!$B$5 -> 54866000 | C6: =B6*Assumptions!$B$4 -> 685825 | D6: =MAX(C6-Assumptions!$B$9,0) -> 648646 | E6: =D6*Assumptions!$B$5 -> 829397.69 | F6: =E6*Assumptions!$B$8 -> 2985.8317 | G6: =(E6-F6)*Assumptions!$B$7 -> 82641.186 | H6: =(E6-F6-G6)*(1-Assumptions!$B$6) -> 0 | I6: =(E6-F6-G6)*Assumptions!$B$6 -> 743770.68 | J6: =Assumptions!$B$15 -> 7269118.6 | K6: =J6*Assumptions!$B$13 -> 334379.45 | L6: =MAX(0,MIN(I6-K6,J6)) -> 409391.22 | M6: =MAX(0,J6+K6-I6) -> 6859727.3 | N6: =C6*Assumptions!$B$5 -> 876936.99
A7: =Inputs_TMV!$A$6 -> 2027 | B7: =Inputs_TMV!$B$6 -> 54866000 | C7: =B7*Assumptions!$B$4 -> 685825 | D7: =MAX(C7-Assumptions!$B$9,0) -> 648646 | E7: =D7*Assumptions!$B$5 -> 829397.69 | F7: =E7*Assumptions!$B$8 -> 2985.8317 | G7: =(E7-F7)*Assumptions!$B$7 -> 82641.186 | H7: =(E7-F7-G7)*(1-Assumptions!$B$6) -> 0 | I7: =(E7-F7-G7)*Assumptions!$B$6 -> 743770.68 | J7: =M6 -> 6859727.3 | K7: =J7*Assumptions!$B$13 -> 315547.46 | L7: =MAX(0,MIN(I7-K7,J7)) -> 428223.22 | M7: =MAX(0,J7+K7-I7) -> 6431504.1 | N7: =C7*Assumptions!$B$5 -> 876936.99
A8: =Inputs_TMV!$A$7 -> 2028 | B8: =Inputs_TMV!$B$7 -> 54866000 | C8: =B8*Assumptions!$B$4 -> 685825 | D8: =MAX(C8-Assumptions!$B$9,0) -> 648646 | E8: =D8*Assumptions!$B$5 -> 829397.69 | F8: =E8*Assumptions!$B$8 -> 2985.8317 | G8: =(E8-F8)*Assumptions!$B$7 -> 82641.186 | H8: =(E8-F8-G8)*(1-Assumptions!$B$6) -> 0 | I8: =(E8-F8-G8)*Assumptions!$B$6 -> 743770.68 | J8: =M7 -> 6431504.1 | K8: =J8*Assumptions!$B$13 -> 295849.19 | L8: =MAX(0,MIN(I8-K8,J8)) -> 447921.49 | M8: =MAX(0,J8+K8-I8) -> 5983582.6 | N8: =C8*Assumptions!$B$5 -> 876936.99
A9: =Inputs_TMV!$A$8 -> 2029 | B9: =Inputs_TMV!$B$8 -> 54866000 | C9: =B9*Assumptions!$B$4 -> 685825 | D9: =MAX(C9-Assumptions!$B$9,0) -> 648646 | E9: =D9*Assumptions!$B$5 -> 829397.69 | F9: =E9*Assumptions!$B$8 -> 2985.8317 | G9: =(E9-F9)*Assumptions!$B$7 -> 82641.186 | H9: =(E9-F9-G9)*(1-Assumptions!$B$6) -> 0 | I9: =(E9-F9-G9)*Assumptions!$B$6 -> 743770.68 | J9: =M8 -> 5983582.6 | K9: =J9*Assumptions!$B$13 -> 275244.8 | L9: =MAX(0,MIN(I9-K9,J9)) -> 468525.87 | M9: =MAX(0,J9+K9-I9) -> 5515056.8 | N9: =C9*Assumptions!$B$5 -> 876936.99
A10: =Inputs_TMV!$A$9 -> 2030 | B10: =Inputs_TMV!$B$9 -> 54866000 | C10: =B10*Assumptions!$B$4 -> 685825 | D10: =MAX(C10-Assumptions!$B$9,0) -> 648646 | E10: =D10*Assumptions!$B$5 -> 829397.69 | F10: =E10*Assumptions!$B$8 -> 2985.8317 | G10: =(E10-F10)*Assumptions!$B$7 -> 82641.186 | H10: =(E10-F10-G10)*(1-Assumptions!$B$6) -> 0 | I10: =(E10-F10-G10)*Assumptions!$B$6 -> 743770.68 | J10: =M9 -> 5515056.8 | K10: =J10*Assumptions!$B$13 -> 253692.61 | L10: =MAX(0,MIN(I10-K10,J10)) -> 490078.07 | M10: =MAX(0,J10+K10-I10) -> 5024978.7 | N10: =C10*Assumptions!$B$5 -> 876936.99
A11: =Inputs_TMV!$A$10 -> 2031 | B11: =Inputs_TMV!$B$10 -> 54866000 | C11: =B11*Assumptions!$B$4 -> 685825 | D11: =MAX(C11-Assumptions!$B$9,0) -> 648646 | E11: =D11*Assumptions!$B$5 -> 829397.69 | F11: =E11*Assumptions!$B$8 -> 2985.8317 | G11: =(E11-F11)*Assumptions!$B$7 -> 82641.186 | H11: =(E11-F11-G11)*(1-Assumptions!$B$6) -> 0 | I11: =(E11-F11-G11)*Assumptions!$B$6 -> 743770.68 | J11: =M10 -> 5024978.7 | K11: =J11*Assumptions!$B$13 -> 231149.02 | L11: =MAX(0,MIN(I11-K11,J11)) -> 512621.66 | M11: =MAX(0,J11+K11-I11) -> 4512357 | N11: =C11*Assumptions!$B$5 -> 876936.99
A12: =Inputs_TMV!$A$11 -> 2032 | B12: =Inputs_TMV!$B$11 -> 54866000 | C12: =B12*Assumptions!$B$4 -> 685825 | D12: =MAX(C12-Assumptions!$B$9,0) -> 648646 | E12: =D12*Assumptions!$B$5 -> 829397.69 | F12: =E12*Assumptions!$B$8 -> 2985.8317 | G12: =(E12-F12)*Assumptions!$B$7 -> 82641.186 | H12: =(E12-F12-G12)*(1-Assumptions!$B$6) -> 0 | I12: =(E12-F12-G12)*Assumptions!$B$6 -> 743770.68 | J12: =M11 -> 4512357 | K12: =J12*Assumptions!$B$13 -> 207568.42 | L12: =MAX(0,MIN(I12-K12,J12)) -> 536202.25 | M12: =MAX(0,J12+K12-I12) -> 3976154.8 | N12: =C12*Assumptions!$B$5 -> 876936.99
A13: =Inputs_TMV!$A$12 -> 2033 | B13: =Inputs_TMV!$B$12 -> 54866000 | C13: =B13*Assumptions!$B$4 -> 685825 | D13: =MAX(C13-Assumptions!$B$9,0) -> 648646 | E13: =D13*Assumptions!$B$5 -> 829397.69 | F13: =E13*Assumptions!$B$8 -> 2985.8317 | G13: =(E13-F13)*Assumptions!$B$7 -> 82641.186 | H13: =(E13-F13-G13)*(1-Assumptions!$B$6) -> 0 | I13: =(E13-F13-G13)*Assumptions!$B$6 -> 743770.68 | J13: =M12 -> 3976154.8 | K13: =J13*Assumptions!$B$13 -> 182903.12 | L13: =MAX(0,MIN(I13-K13,J13)) -> 560867.56 | M13: =MAX(0,J13+K13-I13) -> 3415287.2 | N13: =C13*Assumptions!$B$5 -> 876936.99
A14: =Inputs_TMV!$A$13 -> 2034 | B14: =Inputs_TMV!$B$13 -> 54866000 | C14: =B14*Assumptions!$B$4 -> 685825 | D14: =MAX(C14-Assumptions!$B$9,0) -> 648646 | E14: =D14*Assumptions!$B$5 -> 829397.69 | F14: =E14*Assumptions!$B$8 -> 2985.8317 | G14: =(E14-F14)*Assumptions!$B$7 -> 82641.186 | H14: =(E14-F14-G14)*(1-Assumptions!$B$6) -> 0 | I14: =(E14-F14-G14)*Assumptions!$B$6 -> 743770.68 | J14: =M13 -> 3415287.2 | K14: =J14*Assumptions!$B$13 -> 157103.21 | L14: =MAX(0,MIN(I14-K14,J14)) -> 586667.46 | M14: =MAX(0,J14+K14-I14) -> 2828619.8 | N14: =C14*Assumptions!$B$5 -> 876936.99
A15: =Inputs_TMV!$A$14 -> 2035 | B15: =Inputs_TMV!$B$14 -> 54866000 | C15: =B15*Assumptions!$B$4 -> 685825 | D15: =MAX(C15-Assumptions!$B$9,0) -> 648646 | E15: =D15*Assumptions!$B$5 -> 829397.69 | F15: =E15*Assumptions!$B$8 -> 2985.8317 | G15: =(E15-F15)*Assumptions!$B$7 -> 82641.186 | H15: =(E15-F15-G15)*(1-Assumptions!$B$6) -> 0 | I15: =(E15-F15-G15)*Assumptions!$B$6 -> 743770.68 | J15: =M14 -> 2828619.8 | K15: =J15*Assumptions!$B$13 -> 130116.51 | L15: =MAX(0,MIN(I15-K15,J15)) -> 613654.17 | M15: =MAX(0,J15+K15-I15) -> 2214965.6 | N15: =C15*Assumptions!$B$5 -> 876936.99
A16: =Inputs_TMV!$A$15 -> 2036 | B16: =Inputs_TMV!$B$15 -> 54866000 | C16: =B16*Assumptions!$B$4 -> 685825 | D16: =MAX(C16-Assumptions!$B$9,0) -> 648646 | E16: =D16*Assumptions!$B$5 -> 829397.69 | F16: =E16*Assumptions!$B$8 -> 2985.8317 | G16: =(E16-F16)*Assumptions!$B$7 -> 82641.186 | H16: =(E16-F16-G16)*(1-Assumptions!$B$6) -> 0 | I16: =(E16-F16-G16)*Assumptions!$B$6 -> 743770.68 | J16: =M15 -> 2214965.6 | K16: =J16*Assumptions!$B$13 -> 101888.42 | L16: =MAX(0,MIN(I16-K16,J16)) -> 641882.26 | M16: =MAX(0,J16+K16-I16) -> 1573083.4 | N16: =C16*Assumptions!$B$5 -> 876936.99
A17: =Inputs_TMV!$A$16 -> 2037 | B17: =Inputs_TMV!$B$16 -> 54866000 | C17: =B17*Assumptions!$B$4 -> 685825 | D17: =MAX(C17-Assumptions!$B$9,0) -> 648646 | E17: =D17*Assumptions!$B$5 -> 829397.69 | F17: =E17*Assumptions!$B$8 -> 2985.8317 | G17: =(E17-F17)*Assumptions!$B$7 -> 82641.186 | H17: =(E17-F17-G17)*(1-Assumptions!$B$6) -> 0 | I17: =(E17-F17-G17)*Assumptions!$B$6 -> 743770.68 | J17: =M16 -> 1573083.4 | K17: =J17*Assumptions!$B$13 -> 72361.834 | L17: =MAX(0,MIN(I17-K17,J17)) -> 671408.84 | M17: =MAX(0,J17+K17-I17) -> 901674.51 | N17: =C17*Assumptions!$B$5 -> 876936.99
A18: =Inputs_TMV!$A$17 -> 2038 | B18: =Inputs_TMV!$B$17 -> 54866000 | C18: =B18*Assumptions!$B$4 -> 685825 | D18: =MAX(C18-Assumptions!$B$9,0) -> 648646 | E18: =D18*Assumptions!$B$5 -> 829397.69 | F18: =E18*Assumptions!$B$8 -> 2985.8317 | G18: =(E18-F18)*Assumptions!$B$7 -> 82641.186 | H18: =(E18-F18-G18)*(1-Assumptions!$B$6) -> 0 | I18: =(E18-F18-G18)*Assumptions!$B$6 -> 743770.68 | J18: =M17 -> 901674.51 | K18: =J18*Assumptions!$B$13 -> 41477.027 | L18: =MAX(0,MIN(I18-K18,J18)) -> 702293.65 | M18: =MAX(0,J18+K18-I18) -> 199380.86 | N18: =C18*Assumptions!$B$5 -> 876936.99
A19: =Inputs_TMV!$A$18 -> 2039 | B19: =Inputs_TMV!$B$18 -> 54866000 | C19: =B19*Assumptions!$B$4 -> 685825 | D19: =MAX(C19-Assumptions!$B$9,0) -> 648646 | E19: =D19*Assumptions!$B$5 -> 829397.69 | F19: =E19*Assumptions!$B$8 -> 2985.8317 | G19: =(E19-F19)*Assumptions!$B$7 -> 82641.186 | H19: =(E19-F19-G19)*(1-Assumptions!$B$6) -> 0 | I19: =(E19-F19-G19)*Assumptions!$B$6 -> 743770.68 | J19: =M18 -> 199380.86 | K19: =J19*Assumptions!$B$13 -> 9171.5195 | L19: =MAX(0,MIN(I19-K19,J19)) -> 199380.86 | M19: =MAX(0,J19+K19-I19) -> 0 | N19: =C19*Assumptions!$B$5 -> 876936.99
A20: =Inputs_TMV!$A$19 -> 2040 | B20: =Inputs_TMV!$B$19 -> 54866000 | C20: =B20*Assumptions!$B$4 -> 685825 | D20: =MAX(C20-Assumptions!$B$9,0) -> 648646 | E20: =D20*Assumptions!$B$5 -> 829397.69 | F20: =E20*Assumptions!$B$8 -> 2985.8317 | G20: =(E20-F20)*Assumptions!$B$7 -> 82641.186 | H20: =(E20-F20-G20)*(1-Assumptions!$B$6) -> 0 | I20: =(E20-F20-G20)*Assumptions!$B$6 -> 743770.68 | J20: =M19 -> 0 | K20: =J20*Assumptions!$B$13 -> 0 | L20: =MAX(0,MIN(I20-K20,J20)) -> 0 | M20: =MAX(0,J20+K20-I20) -> 0 | N20: =C20*Assumptions!$B$5 -> 876936.99
A21: =Inputs_TMV!$A$20 -> 2041 | B21: =Inputs_TMV!$B$20 -> 54866000 | C21: =B21*Assumptions!$B$4 -> 685825 | D21: =MAX(C21-Assumptions!$B$9,0) -> 648646 | E21: =D21*Assumptions!$B$5 -> 829397.69 | F21: =E21*Assumptions!$B$8 -> 2985.8317 | G21: =(E21-F21)*Assumptions!$B$7 -> 82641.186 | H21: =(E21-F21-G21)*(1-Assumptions!$B$6) -> 0 | I21: =(E21-F21-G21)*Assumptions!$B$6 -> 743770.68 | J21: =M20 -> 0 | K21: =J21*Assumptions!$B$13 -> 0 | L21: =MAX(0,MIN(I21-K21,J21)) -> 0 | M21: =MAX(0,J21+K21-I21) -> 0 | N21: =C21*Assumptions!$B$5 -> 876936.99
A22: =Inputs_TMV!$A$21 -> 2042 | B22: =Inputs_TMV!$B$21 -> 54866000 | C22: =B22*Assumptions!$B$4 -> 685825 | D22: =MAX(C22-Assumptions!$B$9,0) -> 648646 | E22: =D22*Assumptions!$B$5 -> 829397.69 | F22: =E22*Assumptions!$B$8 -> 2985.8317 | G22: =(E22-F22)*Assumptions!$B$7 -> 82641.186 | H22: =(E22-F22-G22)*(1-Assumptions!$B$6) -> 0 | I22: =(E22-F22-G22)*Assumptions!$B$6 -> 743770.68 | J22: =M21 -> 0 | K22: =J22*Assumptions!$B$13 -> 0 | L22: =MAX(0,MIN(I22-K22,J22)) -> 0 | M22: =MAX(0,J22+K22-I22) -> 0 | N22: =C22*Assumptions!$B$5 -> 876936.99
A23: =Inputs_TMV!$A$22 -> 2043 | B23: =Inputs_TMV!$B$22 -> 54866000 | C23: =B23*Assumptions!$B$4 -> 685825 | D23: =MAX(C23-Assumptions!$B$9,0) -> 648646 | E23: =D23*Assumptions!$B$5 -> 829397.69 | F23: =E23*Assumptions!$B$8 -> 2985.8317 | G23: =(E23-F23)*Assumptions!$B$7 -> 82641.186 | H23: =(E23-F23-G23)*(1-Assumptions!$B$6) -> 0 | I23: =(E23-F23-G23)*Assumptions!$B$6 -> 743770.68 | J23: =M22 -> 0 | K23: =J23*Assumptions!$B$13 -> 0 | L23: =MAX(0,MIN(I23-K23,J23)) -> 0 | M23: =MAX(0,J23+K23-I23) -> 0 | N23: =C23*Assumptions!$B$5 -> 876936.99
A24: =Inputs_TMV!$A$23 -> 2044 | B24: =Inputs_TMV!$B$23 -> 54866000 | C24: =B24*Assumptions!$B$4 -> 685825 | D24: =MAX(C24-Assumptions!$B$9,0) -> 648646 | E24: =D24*Assumptions!$B$5 -> 829397.69 | F24: =E24*Assumptions!$B$8 -> 2985.8317 | G24: =(E24-F24)*Assumptions!$B$7 -> 82641.186 | H24: =(E24-F24-G24)*(1-Assumptions!$B$6) -> 0 | I24: =(E24-F24-G24)*Assumptions!$B$6 -> 743770.68 | J24: =M23 -> 0 | K24: =J24*Assumptions!$B$13 -> 0 | L24: =MAX(0,MIN(I24-K24,J24)) -> 0 | M24: =MAX(0,J24+K24-I24) -> 0 | N24: =C24*Assumptions!$B$5 -> 876936.99
A25: Totals | C25: =SUM(C6:C24) -> 13030675 | D25: =SUM(D6:D24) -> 12324274 | E25: =SUM(E6:E24) -> 15758556 | F25: =SUM(F6:F24) -> 56730.802 | G25: =SUM(G6:G24) -> 1570182.5 | H25: =SUM(H6:H24) -> 0 | I25: =SUM(I6:I24) -> 14131643 | K25: =SUM(K6:K24) -> 2608452.6 | L25: =SUM(L6:L24) -> 7269118.6 | N25: =SUM(N6:N24) -> 16661803
A27: TIF Note Payoff Year: | B27: =IFERROR(INDEX(A6:A24,MATCH(TRUE(),M6:M24=0,0)),"Not paid off in horizon") -> 2039
A28: NPV @ DiscRate: | H28: NPV Net TIF: | I28: =NPV(Assumptions!$B$34,I6:I24) -> 8988707.3 | M28: NPV Prop Tax: | N28: =NPV(Assumptions!$B$34,N6:N24) -> 10598065

Sheet Engine_Mid_Appeal
A1: Engine — Scenario 2: Mid Appeal ($52.15M flat)
A2: All TMV figures linked from Inputs_TMV tab. All constants linked from Assumptions tab. Methodology: Ehlers (Chamberlain TIF Update, 11/8/25).
A4: Pay Year | B4: TMV | C4: NTC | D4: Captured NTC | E4: Total Tax Increment | F4: Less OSA | G4: Less Admin | H4: Developer Share | I4: Net TIF to Developer | J4: Note Beg Bal | K4: Note Interest | L4: Note Principal Pmt | M4: Note End Bal | N4: Total Property Tax
B5: (input) | C5: TMV × ClassRate | D5: NTC − BaseNTC | E5: Captured × TaxCapRate | F5: × 0.36% | G5: × 10% | H5: × 90% | I5: TI × (1−OSA) × (1−Admin) × DevShare | K5: BegBal × 4.60% | L5: MIN(TIF − Int, Bal) | M5: Beg + Int − TIF (floored at 0) | N5: NTC × TaxCapRate (full burden)
A6: =Inputs_TMV!$A$5 -> 2026 | B6: =Inputs_TMV!$C$5 -> 52150000 | C6: =B6*Assumptions!$B$4 -> 651875 | D6: =MAX(C6-Assumptions!$B$9,0) -> 614696 | E6: =D6*Assumptions!$B$5 -> 785987.19 | F6: =E6*Assumptions!$B$8 -> 2829.5539 | G6: =(E6-F6)*Assumptions!$B$7 -> 78315.763 | H6: =(E6-F6-G6)*(1-Assumptions!$B$6) -> 0 | I6: =(E6-F6-G6)*Assumptions!$B$6 -> 704841.87 | J6: =Assumptions!$B$15 -> 7269118.6 | K6: =J6*Assumptions!$B$13 -> 334379.45 | L6: =MAX(0,MIN(I6-K6,J6)) -> 370462.42 | M6: =MAX(0,J6+K6-I6) -> 6898656.2 | N6: =C6*Assumptions!$B$5 -> 833526.49
A7: =Inputs_TMV!$A$6 -> 2027 | B7: =Inputs_TMV!$C$6 -> 52150000 | C7: =B7*Assumptions!$B$4 -> 651875 | D7: =MAX(C7-Assumptions!$B$9,0) -> 614696 | E7: =D7*Assumptions!$B$5 -> 785987.19 | F7: =E7*Assumptions!$B$8 -> 2829.5539 | G7: =(E7-F7)*Assumptions!$B$7 -> 78315.763 | H7: =(E7-F7-G7)*(1-Assumptions!$B$6) -> 0 | I7: =(E7-F7-G7)*Assumptions!$B$6 -> 704841.87 | J7: =M6 -> 6898656.2 | K7: =J7*Assumptions!$B$13 -> 317338.18 | L7: =MAX(0,MIN(I7-K7,J7)) -> 387503.69 | M7: =MAX(0,J7+K7-I7) -> 6511152.5 | N7: =C7*Assumptions!$B$5 -> 833526.49
A8: =Inputs_TMV!$A$7 -> 2028 | B8: =Inputs_TMV!$C$7 -> 52150000 | C8: =B8*Assumptions!$B$4 -> 651875 | D8: =MAX(C8-Assumptions!$B$9,0) -> 614696 | E8: =D8*Assumptions!$B$5 -> 785987.19 | F8: =E8*Assumptions!$B$8 -> 2829.5539 | G8: =(E8-F8)*Assumptions!$B$7 -> 78315.763 | H8: =(E8-F8-G8)*(1-Assumptions!$B$6) -> 0 | I8: =(E8-F8-G8)*Assumptions!$B$6 -> 704841.87 | J8: =M7 -> 6511152.5 | K8: =J8*Assumptions!$B$13 -> 299513.01 | L8: =MAX(0,MIN(I8-K8,J8)) -> 405328.86 | M8: =MAX(0,J8+K8-I8) -> 6105823.6 | N8: =C8*Assumptions!$B$5 -> 833526.49
A9: =Inputs_TMV!$A$8 -> 2029 | B9: =Inputs_TMV!$C$8 -> 52150000 | C9: =B9*Assumptions!$B$4 -> 651875 | D9: =MAX(C9-Assumptions!$B$9,0) -> 614696 | E9: =D9*Assumptions!$B$5 -> 785987.19 | F9: =E9*Assumptions!$B$8 -> 2829.5539 | G9: =(E9-F9)*Assumptions!$B$7 -> 78315.763 | H9: =(E9-F9-G9)*(1-Assumptions!$B$6) -> 0 | I9: =(E9-F9-G9)*Assumptions!$B$6 -> 704841.87 | J9: =M8 -> 6105823.6 | K9: =J9*Assumptions!$B$13 -> 280867.89 | L9: =MAX(0,MIN(I9-K9,J9)) -> 423973.98 | M9: =MAX(0,J9+K9-I9) -> 5681849.6 | N9: =C9*Assumptions!$B$5 -> 833526.49
A10: =Inputs_TMV!$A$9 -> 2030 | B10: =Inputs_TMV!$C$9 -> 52150000 | C10: =B10*Assumptions!$B$4 -> 651875 | D10: =MAX(C10-Assumptions!$B$9,0) -> 614696 | E10: =D10*Assumptions!$B$5 -> 785987.19 | F10: =E10*Assumptions!$B$8 -> 2829.5539 | G10: =(E10-F10)*Assumptions!$B$7 -> 78315.763 | H10: =(E10-F10-G10)*(1-Assumptions!$B$6) -> 0 | I10: =(E10-F10-G10)*Assumptions!$B$6 -> 704841.87 | J10: =M9 -> 5681849.6 | K10: =J10*Assumptions!$B$13 -> 261365.08 | L10: =MAX(0,MIN(I10-K10,J10)) -> 443476.79 | M10: =MAX(0,J10+K10-I10) -> 5238372.8 | N10: =C10*Assumptions!$B$5 -> 833526.49
A11: =Inputs_TMV!$A$10 -> 2031 | B11: =Inputs_TMV!$C$10 -> 52150000 | C11: =B11*Assumptions!$B$4 -> 651875 | D11: =MAX(C11-Assumptions!$B$9,0) -> 614696 | E11: =D11*Assumptions!$B$5 -> 785987.19 | F11: =E11*Assumptions!$B$8 -> 2829.5539 | G11: =(E11-F11)*Assumptions!$B$7 -> 78315.763 | H11: =(E11-F11-G11)*(1-Assumptions!$B$6) -> 0 | I11: =(E11-F11-G11)*Assumptions!$B$6 -> 704841.87 | J11: =M10 -> 5238372.8 | K11: =J11*Assumptions!$B$13 -> 240965.15 | L11: =MAX(0,MIN(I11-K11,J11)) -> 463876.72 | M11: =MAX(0,J11+K11-I11) -> 4774496.1 | N11: =C11*Assumptions!$B$5 -> 833526.49
A12: =Inputs_TMV!$A$11 -> 2032 | B12: =Inputs_TMV!$C$11 -> 52150000 | C12: =B12*Assumptions!$B$4 -> 651875 | D12: =MAX(C12-Assumptions!$B$9,0) -> 614696 | E12: =D12*Assumptions!$B$5 -> 785987.19 | F12: =E12*Assumptions!$B$8 -> 2829.5539 | G12: =(E12-F12)*Assumptions!$B$7 -> 78315.763 | H12: =(E12-F12-G12)*(1-Assumptions!$B$6) -> 0 | I12: =(E12-F12-G12)*Assumptions!$B$6 -> 704841.87 | J12: =M11 -> 4774496.1 | K12: =J12*Assumptions!$B$13 -> 219626.82 | L12: =MAX(0,MIN(I12-K12,J12)) -> 485215.05 | M12: =MAX(0,J12+K12-I12) -> 4289281.1 | N12: =C12*Assumptions!$B$5 -> 833526.49
A13: =Inputs_TMV!$A$12 -> 2033 | B13: =Inputs_TMV!$C$12 -> 52150000 | C13: =B13*Assumptions!$B$4 -> 651875 | D13: =MAX(C13-Assumptions!$B$9,0) -> 614696 | E13: =D13*Assumptions!$B$5 -> 785987.19 | F13: =E13*Assumptions!$B$8 -> 2829.5539 | G13: =(E13-F13)*Assumptions!$B$7 -> 78315.763 | H13: =(E13-F13-G13)*(1-Assumptions!$B$6) -> 0 | I13: =(E13-F13-G13)*Assumptions!$B$6 -> 704841.87 | J13: =M12 -> 4289281.1 | K13: =J13*Assumptions!$B$13 -> 197306.93 | L13: =MAX(0,MIN(I13-K13,J13)) -> 507534.94 | M13: =MAX(0,J13+K13-I13) -> 3781746.1 | N13: =C13*Assumptions!$B$5 -> 833526.49
A14: =Inputs_TMV!$A$13 -> 2034 | B14: =Inputs_TMV!$C$13 -> 52150000 | C14: =B14*Assumptions!$B$4 -> 651875 | D14: =MAX(C14-Assumptions!$B$9,0) -> 614696 | E14: =D14*Assumptions!$B$5 -> 785987.19 | F14: =E14*Assumptions!$B$8 -> 2829.5539 | G14: =(E14-F14)*Assumptions!$B$7 -> 78315.763 | H14: =(E14-F14-G14)*(1-Assumptions!$B$6) -> 0 | I14: =(E14-F14-G14)*Assumptions!$B$6 -> 704841.87 | J14: =M13 -> 3781746.1 | K14: =J14*Assumptions!$B$13 -> 173960.32 | L14: =MAX(0,MIN(I14-K14,J14)) -> 530881.55 | M14: =MAX(0,J14+K14-I14) -> 3250864.6 | N14: =C14*Assumptions!$B$5 -> 833526.49
A15: =Inputs_TMV!$A$14 -> 2035 | B15: =Inputs_TMV!$C$14 -> 52150000 | C15: =B15*Assumptions!$B$4 -> 651875 | D15: =MAX(C15-Assumptions!$B$9,0) -> 614696 | E15: =D15*Assumptions!$B$5 -> 785987.19 | F15: =E15*Assumptions!$B$8 -> 2829.5539 | G15: =(E15-F15)*Assumptions!$B$7 -> 78315.763 | H15: =(E15-F15-G15)*(1-Assumptions!$B$6) -> 0 | I15: =(E15-F15-G15)*Assumptions!$B$6 -> 704841.87 | J15: =M14 -> 3250864.6 | K15: =J15*Assumptions!$B$13 -> 149539.77 | L15: =MAX(0,MIN(I15-K15,J15)) -> 555302.1 | M15: =MAX(0,J15+K15-I15) -> 2695562.5 | N15: =C15*Assumptions!$B$5 -> 833526.49
A16: =Inputs_TMV!$A$15 -> 2036 | B16: =Inputs_TMV!$C$15 -> 52150000 | C16: =B16*Assumptions!$B$4 -> 651875 | D16: =MAX(C16-Assumptions!$B$9,0) -> 614696 | E16: =D16*Assumptions!$B$5 -> 785987.19 | F16: =E16*Assumptions!$B$8 -> 2829.5539 | G16: =(E16-F16)*Assumptions!$B$7 -> 78315.763 | H16: =(E16-F16-G16)*(1-Assumptions!$B$6) -> 0 | I16: =(E16-F16-G16)*Assumptions!$B$6 -> 704841.87 | J16: =M15 -> 2695562.5 | K16: =J16*Assumptions!$B$13 -> 123995.87 | L16: =MAX(0,MIN(I16-K16,J16)) -> 580846 | M16: =MAX(0,J16+K16-I16) -> 2114716.5 | N16: =C16*Assumptions!$B$5 -> 833526.49
A17: =Inputs_TMV!$A$16 -> 2037 | B17: =Inputs_TMV!$C$16 -> 52150000 | C17: =B17*Assumptions!$B$4 -> 651875 | D17: =MAX(C17-Assumptions!$B$9,0) -> 614696 | E17: =D17*Assumptions!$B$5 -> 785987.19 | F17: =E17*Assumptions!$B$8 -> 2829.5539 | G17: =(E17-F17)*Assumptions!$B$7 -> 78315.763 | H17: =(E17-F17-G17)*(1-Assumptions!$B$6) -> 0 | I17: =(E17-F17-G17)*Assumptions!$B$6 -> 704841.87 | J17: =M16 -> 2114716.5 | K17: =J17*Assumptions!$B$13 -> 97276.958 | L17: =MAX(0,MIN(I17-K17,J17)) -> 607564.91 | M17: =MAX(0,J17+K17-I17) -> 1507151.6 | N17: =C17*Assumptions!$B$5 -> 833526.49
A18: =Inputs_TMV!$A$17 -> 2038 | B18: =Inputs_TMV!$C$17 -> 52150000 | C18: =B18*Assumptions!$B$4 -> 651875 | D18: =MAX(C18-Assumptions!$B$9,0) -> 614696 | E18: =D18*Assumptions!$B$5 -> 785987.19 | F18: =E18*Assumptions!$B$8 -> 2829.5539 | G18: =(E18-F18)*Assumptions!$B$7 -> 78315.763 | H18: =(E18-F18-G18)*(1-Assumptions!$B$6) -> 0 | I18: =(E18-F18-G18)*Assumptions!$B$6 -> 704841.87 | J18: =M17 -> 1507151.6 | K18: =J18*Assumptions!$B$13 -> 69328.972 | L18: =MAX(0,MIN(I18-K18,J18)) -> 635512.9 | M18: =MAX(0,J18+K18-I18) -> 871638.68 | N18: =C18*Assumptions!$B$5 -> 833526.49
A19: =Inputs_TMV!$A$18 -> 2039 | B19: =Inputs_TMV!$C$18 -> 52150000 | C19: =B19*Assumptions!$B$4 -> 651875 | D19: =MAX(C19-Assumptions!$B$9,0) -> 614696 | E19: =D19*Assumptions!$B$5 -> 785987.19 | F19: =E19*Assumptions!$B$8 -> 2829.5539 | G19: =(E19-F19)*Assumptions!$B$7 -> 78315.763 | H19: =(E19-F19-G19)*(1-Assumptions!$B$6) -> 0 | I19: =(E19-F19-G19)*Assumptions!$B$6 -> 704841.87 | J19: =M18 -> 871638.68 | K19: =J19*Assumptions!$B$13 -> 40095.379 | L19: =MAX(0,MIN(I19-K19,J19)) -> 664746.49 | M19: =MAX(0,J19+K19-I19) -> 206892.19 | N19: =C19*Assumptions!$B$5 -> 833526.49
A20: =Inputs_TMV!$A$19 -> 2040 | B20: =Inputs_TMV!$C$19 -> 52150000 | C20: =B20*Assumptions!$B$4 -> 651875 | D20: =MAX(C20-Assumptions!$B$9,0) -> 614696 | E20: =D20*Assumptions!$B$5 -> 785987.19 | F20: =E20*Assumptions!$B$8 -> 2829.5539 | G20: =(E20-F20)*Assumptions!$B$7 -> 78315.763 | H20: =(E20-F20-G20)*(1-Assumptions!$B$6) -> 0 | I20: =(E20-F20-G20)*Assumptions!$B$6 -> 704841.87 | J20: =M19 -> 206892.19 | K20: =J20*Assumptions!$B$13 -> 9517.0406 | L20: =MAX(0,MIN(I20-K20,J20)) -> 206892.19 | M20: =MAX(0,J20+K20-I20) -> 0 | N20: =C20*Assumptions!$B$5 -> 833526.49
A21: =Inputs_TMV!$A$20 -> 2041 | B21: =Inputs_TMV!$C$20 -> 52150000 | C21: =B21*Assumptions!$B$4 -> 651875 | D21: =MAX(C21-Assumptions!$B$9,0) -> 614696 | E21: =D21*Assumptions!$B$5 -> 785987.19 | F21: =E21*Assumptions!$B$8 -> 2829.5539 | G21: =(E21-F21)*Assumptions!$B$7 -> 78315.763 | H21: =(E21-F21-G21)*(1-Assumptions!$B$6) -> 0 | I21: =(E21-F21-G21)*Assumptions!$B$6 -> 704841.87 | J21: =M20 -> 0 | K21: =J21*Assumptions!$B$13 -> 0 | L21: =MAX(0,MIN(I21-K21,J21)) -> 0 | M21: =MAX(0,J21+K21-I21) -> 0 | N21: =C21*Assumptions!$B$5 -> 833526.49
A22: =Inputs_TMV!$A$21 -> 2042 | B22: =Inputs_TMV!$C$21 -> 52150000 | C22: =B22*Assumptions!$B$4 -> 651875 | D22: =MAX(C22-Assumptions!$B$9,0) -> 614696 | E22: =D22*Assumptions!$B$5 -> 785987.19 | F22: =E22*Assumptions!$B$8 -> 2829.5539 | G22: =(E22-F22)*Assumptions!$B$7 -> 78315.763 | H22: =(E22-F22-G22)*(1-Assumptions!$B$6) -> 0 | I22: =(E22-F22-G22)*Assumptions!$B$6 -> 704841.87 | J22: =M21 -> 0 | K22: =J22*Assumptions!$B$13 -> 0 | L22: =MAX(0,MIN(I22-K22,J22)) -> 0 | M22: =MAX(0,J22+K22-I22) -> 0 | N22: =C22*Assumptions!$B$5 -> 833526.49
A23: =Inputs_TMV!$A$22 -> 2043 | B23: =Inputs_TMV!$C$22 -> 52150000 | C23: =B23*Assumptions!$B$4 -> 651875 | D23: =MAX(C23-Assumptions!$B$9,0) -> 614696 | E23: =D23*Assumptions!$B$5 -> 785987.19 | F23: =E23*Assumptions!$B$8 -> 2829.5539 | G23: =(E23-F23)*Assumptions!$B$7 -> 78315.763 | H23: =(E23-F23-G23)*(1-Assumptions!$B$6) -> 0 | I23: =(E23-F23-G23)*Assumptions!$B$6 -> 704841.87 | J23: =M22 -> 0 | K23: =J23*Assumptions!$B$13 -> 0 | L23: =MAX(0,MIN(I23-K23,J23)) -> 0 | M23: =MAX(0,J23+K23-I23) -> 0 | N23: =C23*Assumptions!$B$5 -> 833526.49
A24: =Inputs_TMV!$A$23 -> 2044 | B24: =Inputs_TMV!$C$23 -> 52150000 | C24: =B24*Assumptions!$B$4 -> 651875 | D24: =MAX(C24-Assumptions!$B$9,0) -> 614696 | E24: =D24*Assumptions!$B$5 -> 785987.19 | F24: =E24*Assumptions!$B$8 -> 2829.5539 | G24: =(E24-F24)*Assumptions!$B$7 -> 78315.763 | H24: =(E24-F24-G24)*(1-Assumptions!$B$6) -> 0 | I24: =(E24-F24-G24)*Assumptions!$B$6 -> 704841.87 | J24: =M23 -> 0 | K24: =J24*Assumptions!$B$13 -> 0 | L24: =MAX(0,MIN(I24-K24,J24)) -> 0 | M24: =MAX(0,J24+K24-I24) -> 0 | N24: =C24*Assumptions!$B$5 -> 833526.49
A25: Totals | C25: =SUM(C6:C24) -> 12385625 | D25: =SUM(D6:D24) -> 11679224 | E25: =SUM(E6:E24) -> 14933757 | F25: =SUM(F6:F24) -> 53761.524 | G25: =SUM(G6:G24) -> 1487999.5 | H25: =SUM(H6:H24) -> 0 | I25: =SUM(I6:I24) -> 13391996 | K25: =SUM(K6:K24) -> 2815076.8 | L25: =SUM(L6:L24) -> 7269118.6 | N25: =SUM(N6:N24) -> 15837003
A27: TIF Note Payoff Year: | B27: =IFERROR(INDEX(A6:A24,MATCH(TRUE(),M6:M24=0,0)),"Not paid off in horizon") -> 2040
A28: NPV @ DiscRate: | H28: NPV Net TIF: | I28: =NPV(Assumptions!$B$34,I6:I24) -> 8518240.2 | M28: NPV Prop Tax: | N28: =NPV(Assumptions!$B$34,N6:N24) -> 10073435

Sheet Engine_Agg_Appeal
A1: Engine — Scenario 3: Aggressive Appeal ($50.0M flat)
A2: All TMV figures linked from Inputs_TMV tab. All constants linked from Assumptions tab. Methodology: Ehlers (Chamberlain TIF Update, 11/8/25).
A4: Pay Year | B4: TMV | C4: NTC | D4: Captured NTC | E4: Total Tax Increment | F4: Less OSA | G4: Less Admin | H4: Developer Share | I4: Net TIF to Developer | J4: Note Beg Bal | K4: Note Interest | L4: Note Principal Pmt | M4: Note End Bal | N4: Total Property Tax
B5: (input) | C5: TMV × ClassRate | D5: NTC − BaseNTC | E5: Captured × TaxCapRate | F5: × 0.36% | G5: × 10% | H5: × 90% | I5: TI × (1−OSA) × (1−Admin) × DevShare | K5: BegBal × 4.60% | L5: MIN(TIF − Int, Bal) | M5: Beg + Int − TIF (floored at 0) | N5: NTC × TaxCapRate (full burden)
A6: =Inputs_TMV!$A$5 -> 2026 | B6: =Inputs_TMV!$D$5 -> 50000000 | C6: =B6*Assumptions!$B$4 -> 625000 | D6: =MAX(C6-Assumptions!$B$9,0) -> 587821 | E6: =D6*Assumptions!$B$5 -> 751623.2 | F6: =E6*Assumptions!$B$8 -> 2705.8435 | G6: =(E6-F6)*Assumptions!$B$7 -> 74891.736 | H6: =(E6-F6-G6)*(1-Assumptions!$B$6) -> 0 | I6: =(E6-F6-G6)*Assumptions!$B$6 -> 674025.62 | J6: =Assumptions!$B$15 -> 7269118.6 | K6: =J6*Assumptions!$B$13 -> 334379.45 | L6: =MAX(0,MIN(I6-K6,J6)) -> 339646.17 | M6: =MAX(0,J6+K6-I6) -> 6929472.4 | N6: =C6*Assumptions!$B$5 -> 799162.5
A7: =Inputs_TMV!$A$6 -> 2027 | B7: =Inputs_TMV!$D$6 -> 50000000 | C7: =B7*Assumptions!$B$4 -> 625000 | D7: =MAX(C7-Assumptions!$B$9,0) -> 587821 | E7: =D7*Assumptions!$B$5 -> 751623.2 | F7: =E7*Assumptions!$B$8 -> 2705.8435 | G7: =(E7-F7)*Assumptions!$B$7 -> 74891.736 | H7: =(E7-F7-G7)*(1-Assumptions!$B$6) -> 0 | I7: =(E7-F7-G7)*Assumptions!$B$6 -> 674025.62 | J7: =M6 -> 6929472.4 | K7: =J7*Assumptions!$B$13 -> 318755.73 | L7: =MAX(0,MIN(I7-K7,J7)) -> 355269.89 | M7: =MAX(0,J7+K7-I7) -> 6574202.5 | N7: =C7*Assumptions!$B$5 -> 799162.5
A8: =Inputs_TMV!$A$7 -> 2028 | B8: =Inputs_TMV!$D$7 -> 50000000 | C8: =B8*Assumptions!$B$4 -> 625000 | D8: =MAX(C8-Assumptions!$B$9,0) -> 587821 | E8: =D8*Assumptions!$B$5 -> 751623.2 | F8: =E8*Assumptions!$B$8 -> 2705.8435 | G8: =(E8-F8)*Assumptions!$B$7 -> 74891.736 | H8: =(E8-F8-G8)*(1-Assumptions!$B$6) -> 0 | I8: =(E8-F8-G8)*Assumptions!$B$6 -> 674025.62 | J8: =M7 -> 6574202.5 | K8: =J8*Assumptions!$B$13 -> 302413.32 | L8: =MAX(0,MIN(I8-K8,J8)) -> 371612.31 | M8: =MAX(0,J8+K8-I8) -> 6202590.2 | N8: =C8*Assumptions!$B$5 -> 799162.5
A9: =Inputs_TMV!$A$8 -> 2029 | B9: =Inputs_TMV!$D$8 -> 50000000 | C9: =B9*Assumptions!$B$4 -> 625000 | D9: =MAX(C9-Assumptions!$B$9,0) -> 587821 | E9: =D9*Assumptions!$B$5 -> 751623.2 | F9: =E9*Assumptions!$B$8 -> 2705.8435 | G9: =(E9-F9)*Assumptions!$B$7 -> 74891.736 | H9: =(E9-F9-G9)*(1-Assumptions!$B$6) -> 0 | I9: =(E9-F9-G9)*Assumptions!$B$6 -> 674025.62 | J9: =M8 -> 6202590.2 | K9: =J9*Assumptions!$B$13 -> 285319.15 | L9: =MAX(0,MIN(I9-K9,J9)) -> 388706.47 | M9: =MAX(0,J9+K9-I9) -> 5813883.7 | N9: =C9*Assumptions!$B$5 -> 799162.5
A10: =Inputs_TMV!$A$9 -> 2030 | B10: =Inputs_TMV!$D$9 -> 50000000 | C10: =B10*Assumptions!$B$4 -> 625000 | D10: =MAX(C10-Assumptions!$B$9,0) -> 587821 | E10: =D10*Assumptions!$B$5 -> 751623.2 | F10: =E10*Assumptions!$B$8 -> 2705.8435 | G10: =(E10-F10)*Assumptions!$B$7 -> 74891.736 | H10: =(E10-F10-G10)*(1-Assumptions!$B$6) -> 0 | I10: =(E10-F10-G10)*Assumptions!$B$6 -> 674025.62 | J10: =M9 -> 5813883.7 | K10: =J10*Assumptions!$B$13 -> 267438.65 | L10: =MAX(0,MIN(I10-K10,J10)) -> 406586.97 | M10: =MAX(0,J10+K10-I10) -> 5407296.8 | N10: =C10*Assumptions!$B$5 -> 799162.5
A11: =Inputs_TMV!$A$10 -> 2031 | B11: =Inputs_TMV!$D$10 -> 50000000 | C11: =B11*Assumptions!$B$4 -> 625000 | D11: =MAX(C11-Assumptions!$B$9,0) -> 587821 | E11: =D11*Assumptions!$B$5 -> 751623.2 | F11: =E11*Assumptions!$B$8 -> 2705.8435 | G11: =(E11-F11)*Assumptions!$B$7 -> 74891.736 | H11: =(E11-F11-G11)*(1-Assumptions!$B$6) -> 0 | I11: =(E11-F11-G11)*Assumptions!$B$6 -> 674025.62 | J11: =M10 -> 5407296.8 | K11: =J11*Assumptions!$B$13 -> 248735.65 | L11: =MAX(0,MIN(I11-K11,J11)) -> 425289.97 | M11: =MAX(0,J11+K11-I11) -> 4982006.8 | N11: =C11*Assumptions!$B$5 -> 799162.5
A12: =Inputs_TMV!$A$11 -> 2032 | B12: =Inputs_TMV!$D$11 -> 50000000 | C12: =B12*Assumptions!$B$4 -> 625000 | D12: =MAX(C12-Assumptions!$B$9,0) -> 587821 | E12: =D12*Assumptions!$B$5 -> 751623.2 | F12: =E12*Assumptions!$B$8 -> 2705.8435 | G12: =(E12-F12)*Assumptions!$B$7 -> 74891.736 | H12: =(E12-F12-G12)*(1-Assumptions!$B$6) -> 0 | I12: =(E12-F12-G12)*Assumptions!$B$6 -> 674025.62 | J12: =M11 -> 4982006.8 | K12: =J12*Assumptions!$B$13 -> 229172.31 | L12: =MAX(0,MIN(I12-K12,J12)) -> 444853.31 | M12: =MAX(0,J12+K12-I12) -> 4537153.5 | N12: =C12*Assumptions!$B$5 -> 799162.5
A13: =Inputs_TMV!$A$12 -> 2033 | B13: =Inputs_TMV!$D$12 -> 50000000 | C13: =B13*Assumptions!$B$4 -> 625000 | D13: =MAX(C13-Assumptions!$B$9,0) -> 587821 | E13: =D13*Assumptions!$B$5 -> 751623.2 | F13: =E13*Assumptions!$B$8 -> 2705.8435 | G13: =(E13-F13)*Assumptions!$B$7 -> 74891.736 | H13: =(E13-F13-G13)*(1-Assumptions!$B$6) -> 0 | I13: =(E13-F13-G13)*Assumptions!$B$6 -> 674025.62 | J13: =M12 -> 4537153.5 | K13: =J13*Assumptions!$B$13 -> 208709.06 | L13: =MAX(0,MIN(I13-K13,J13)) -> 465316.56 | M13: =MAX(0,J13+K13-I13) -> 4071836.9 | N13: =C13*Assumptions!$B$5 -> 799162.5
A14: =Inputs_TMV!$A$13 -> 2034 | B14: =Inputs_TMV!$D$13 -> 50000000 | C14: =B14*Assumptions!$B$4 -> 625000 | D14: =MAX(C14-Assumptions!$B$9,0) -> 587821 | E14: =D14*Assumptions!$B$5 -> 751623.2 | F14: =E14*Assumptions!$B$8 -> 2705.8435 | G14: =(E14-F14)*Assumptions!$B$7 -> 74891.736 | H14: =(E14-F14-G14)*(1-Assumptions!$B$6) -> 0 | I14: =(E14-F14-G14)*Assumptions!$B$6 -> 674025.62 | J14: =M13 -> 4071836.9 | K14: =J14*Assumptions!$B$13 -> 187304.5 | L14: =MAX(0,MIN(I14-K14,J14)) -> 486721.12 | M14: =MAX(0,J14+K14-I14) -> 3585115.8 | N14: =C14*Assumptions!$B$5 -> 799162.5
A15: =Inputs_TMV!$A$14 -> 2035 | B15: =Inputs_TMV!$D$14 -> 50000000 | C15: =B15*Assumptions!$B$4 -> 625000 | D15: =MAX(C15-Assumptions!$B$9,0) -> 587821 | E15: =D15*Assumptions!$B$5 -> 751623.2 | F15: =E15*Assumptions!$B$8 -> 2705.8435 | G15: =(E15-F15)*Assumptions!$B$7 -> 74891.736 | H15: =(E15-F15-G15)*(1-Assumptions!$B$6) -> 0 | I15: =(E15-F15-G15)*Assumptions!$B$6 -> 674025.62 | J15: =M14 -> 3585115.8 | K15: =J15*Assumptions!$B$13 -> 164915.33 | L15: =MAX(0,MIN(I15-K15,J15)) -> 509110.29 | M15: =MAX(0,J15+K15-I15) -> 3076005.5 | N15: =C15*Assumptions!$B$5 -> 799162.5
A16: =Inputs_TMV!$A$15 -> 2036 | B16: =Inputs_TMV!$D$15 -> 50000000 | C16: =B16*Assumptions!$B$4 -> 625000 | D16: =MAX(C16-Assumptions!$B$9,0) -> 587821 | E16: =D16*Assumptions!$B$5 -> 751623.2 | F16: =E16*Assumptions!$B$8 -> 2705.8435 | G16: =(E16-F16)*Assumptions!$B$7 -> 74891.736 | H16: =(E16-F16-G16)*(1-Assumptions!$B$6) -> 0 | I16: =(E16-F16-G16)*Assumptions!$B$6 -> 674025.62 | J16: =M15 -> 3076005.5 | K16: =J16*Assumptions!$B$13 -> 141496.25 | L16: =MAX(0,MIN(I16-K16,J16)) -> 532529.37 | M16: =MAX(0,J16+K16-I16) -> 2543476.1 | N16: =C16*Assumptions!$B$5 -> 799162.5
A17: =Inputs_TMV!$A$16 -> 2037 | B17: =Inputs_TMV!$D$16 -> 50000000 | C17: =B17*Assumptions!$B$4 -> 625000 | D17: =MAX(C17-Assumptions!$B$9,0) -> 587821 | E17: =D17*Assumptions!$B$5 -> 751623.2 | F17: =E17*Assumptions!$B$8 -> 2705.8435 | G17: =(E17-F17)*Assumptions!$B$7 -> 74891.736 | H17: =(E17-F17-G17)*(1-Assumptions!$B$6) -> 0 | I17: =(E17-F17-G17)*Assumptions!$B$6 -> 674025.62 | J17: =M16 -> 2543476.1 | K17: =J17*Assumptions!$B$13 -> 116999.9 | L17: =MAX(0,MIN(I17-K17,J17)) -> 557025.72 | M17: =MAX(0,J17+K17-I17) -> 1986450.4 | N17: =C17*Assumptions!$B$5 -> 799162.5
A18: =Inputs_TMV!$A$17 -> 2038 | B18: =Inputs_TMV!$D$17 -> 50000000 | C18: =B18*Assumptions!$B$4 -> 625000 | D18: =MAX(C18-Assumptions!$B$9,0) -> 587821 | E18: =D18*Assumptions!$B$5 -> 751623.2 | F18: =E18*Assumptions!$B$8 -> 2705.8435 | G18: =(E18-F18)*Assumptions!$B$7 -> 74891.736 | H18: =(E18-F18-G18)*(1-Assumptions!$B$6) -> 0 | I18: =(E18-F18-G18)*Assumptions!$B$6 -> 674025.62 | J18: =M17 -> 1986450.4 | K18: =J18*Assumptions!$B$13 -> 91376.72 | L18: =MAX(0,MIN(I18-K18,J18)) -> 582648.9 | M18: =MAX(0,J18+K18-I18) -> 1403801.5 | N18: =C18*Assumptions!$B$5 -> 799162.5
A19: =Inputs_TMV!$A$18 -> 2039 | B19: =Inputs_TMV!$D$18 -> 50000000 | C19: =B19*Assumptions!$B$4 -> 625000 | D19: =MAX(C19-Assumptions!$B$9,0) -> 587821 | E19: =D19*Assumptions!$B$5 -> 751623.2 | F19: =E19*Assumptions!$B$8 -> 2705.8435 | G19: =(E19-F19)*Assumptions!$B$7 -> 74891.736 | H19: =(E19-F19-G19)*(1-Assumptions!$B$6) -> 0 | I19: =(E19-F19-G19)*Assumptions!$B$6 -> 674025.62 | J19: =M18 -> 1403801.5 | K19: =J19*Assumptions!$B$13 -> 64574.87 | L19: =MAX(0,MIN(I19-K19,J19)) -> 609450.75 | M19: =MAX(0,J19+K19-I19) -> 794350.78 | N19: =C19*Assumptions!$B$5 -> 799162.5
A20: =Inputs_TMV!$A$19 -> 2040 | B20: =Inputs_TMV!$D$19 -> 50000000 | C20: =B20*Assumptions!$B$4 -> 625000 | D20: =MAX(C20-Assumptions!$B$9,0) -> 587821 | E20: =D20*Assumptions!$B$5 -> 751623.2 | F20: =E20*Assumptions!$B$8 -> 2705.8435 | G20: =(E20-F20)*Assumptions!$B$7 -> 74891.736 | H20: =(E20-F20-G20)*(1-Assumptions!$B$6) -> 0 | I20: =(E20-F20-G20)*Assumptions!$B$6 -> 674025.62 | J20: =M19 -> 794350.78 | K20: =J20*Assumptions!$B$13 -> 36540.136 | L20: =MAX(0,MIN(I20-K20,J20)) -> 637485.48 | M20: =MAX(0,J20+K20-I20) -> 156865.29 | N20: =C20*Assumptions!$B$5 -> 799162.5
A21: =Inputs_TMV!$A$20 -> 2041 | B21: =Inputs_TMV!$D$20 -> 50000000 | C21: =B21*Assumptions!$B$4 -> 625000 | D21: =MAX(C21-Assumptions!$B$9,0) -> 587821 | E21: =D21*Assumptions!$B$5 -> 751623.2 | F21: =E21*Assumptions!$B$8 -> 2705.8435 | G21: =(E21-F21)*Assumptions!$B$7 -> 74891.736 | H21: =(E21-F21-G21)*(1-Assumptions!$B$6) -> 0 | I21: =(E21-F21-G21)*Assumptions!$B$6 -> 674025.62 | J21: =M20 -> 156865.29 | K21: =J21*Assumptions!$B$13 -> 7215.8036 | L21: =MAX(0,MIN(I21-K21,J21)) -> 156865.29 | M21: =MAX(0,J21+K21-I21) -> 0 | N21: =C21*Assumptions!$B$5 -> 799162.5
A22: =Inputs_TMV!$A$21 -> 2042 | B22: =Inputs_TMV!$D$21 -> 50000000 | C22: =B22*Assumptions!$B$4 -> 625000 | D22: =MAX(C22-Assumptions!$B$9,0) -> 587821 | E22: =D22*Assumptions!$B$5 -> 751623.2 | F22: =E22*Assumptions!$B$8 -> 2705.8435 | G22: =(E22-F22)*Assumptions!$B$7 -> 74891.736 | H22: =(E22-F22-G22)*(1-Assumptions!$B$6) -> 0 | I22: =(E22-F22-G22)*Assumptions!$B$6 -> 674025.62 | J22: =M21 -> 0 | K22: =J22*Assumptions!$B$13 -> 0 | L22: =MAX(0,MIN(I22-K22,J22)) -> 0 | M22: =MAX(0,J22+K22-I22) -> 0 | N22: =C22*Assumptions!$B$5 -> 799162.5
A23: =Inputs_TMV!$A$22 -> 2043 | B23: =Inputs_TMV!$D$22 -> 50000000 | C23: =B23*Assumptions!$B$4 -> 625000 | D23: =MAX(C23-Assumptions!$B$9,0) -> 587821 | E23: =D23*Assumptions!$B$5 -> 751623.2 | F23: =E23*Assumptions!$B$8 -> 2705.8435 | G23: =(E23-F23)*Assumptions!$B$7 -> 74891.736 | H23: =(E23-F23-G23)*(1-Assumptions!$B$6) -> 0 | I23: =(E23-F23-G23)*Assumptions!$B$6 -> 674025.62 | J23: =M22 -> 0 | K23: =J23*Assumptions!$B$13 -> 0 | L23: =MAX(0,MIN(I23-K23,J23)) -> 0 | M23: =MAX(0,J23+K23-I23) -> 0 | N23: =C23*Assumptions!$B$5 -> 799162.5
A24: =Inputs_TMV!$A$23 -> 2044 | B24: =Inputs_TMV!$D$23 -> 50000000 | C24: =B24*Assumptions!$B$4 -> 625000 | D24: =MAX(C24-Assumptions!$B$9,0) -> 587821 | E24: =D24*Assumptions!$B$5 -> 751623.2 | F24: =E24*Assumptions!$B$8 -> 2705.8435 | G24: =(E24-F24)*Assumptions!$B$7 -> 74891.736 | H24: =(E24-F24-G24)*(1-Assumptions!$B$6) -> 0 | I24: =(E24-F24-G24)*Assumptions!$B$6 -> 674025.62 | J24: =M23 -> 0 | K24: =J24*Assumptions!$B$13 -> 0 | L24: =MAX(0,MIN(I24-K24,J24)) -> 0 | M24: =MAX(0,J24+K24-I24) -> 0 | N24: =C24*Assumptions!$B$5 -> 799162.5
A25: Totals | C25: =SUM(C6:C24) -> 11875000 | D25: =SUM(D6:D24) -> 11168599 | E25: =SUM(E6:E24) -> 14280841 | F25: =SUM(F6:F24) -> 51411.027 | G25: =SUM(G6:G24) -> 1422943 | H25: =SUM(H6:H24) -> 0 | I25: =SUM(I6:I24) -> 12806487 | K25: =SUM(K6:K24) -> 3005346.8 | L25: =SUM(L6:L24) -> 7269118.6 | N25: =SUM(N6:N24) -> 15184088
A27: TIF Note Payoff Year: | B27: =IFERROR(INDEX(A6:A24,MATCH(TRUE(),M6:M24=0,0)),"Not paid off in horizon") -> 2041
A28: NPV @ DiscRate: | H28: NPV Net TIF: | I28: =NPV(Assumptions!$B$34,I6:I24) -> 8145815.9 | M28: NPV Prop Tax: | N28: =NPV(Assumptions!$B$34,N6:N24) -> 9658135.2

Sheet Engine_MAA_Floor
A1: Engine — Scenario 4: MAA Floor / Ehlers Stress ($43.835M flat)
A2: All TMV figures linked from Inputs_TMV tab. All constants linked from Assumptions tab. Methodology: Ehlers (Chamberlain TIF Update, 11/8/25).
A4: Pay Year | B4: TMV | C4: NTC | D4: Captured NTC | E4: Total Tax Increment | F4: Less OSA | G4: Less Admin | H4: Developer Share | I4: Net TIF to Developer | J4: Note Beg Bal | K4: Note Interest | L4: Note Principal Pmt | M4: Note End Bal | N4: Total Property Tax
B5: (input) | C5: TMV × ClassRate | D5: NTC − BaseNTC | E5: Captured × TaxCapRate | F5: × 0.36% | G5: × 10% | H5: × 90% | I5: TI × (1−OSA) × (1−Admin) × DevShare | K5: BegBal × 4.60% | L5: MIN(TIF − Int, Bal) | M5: Beg + Int − TIF (floored at 0) | N5: NTC × TaxCapRate (full burden)
A6: =Inputs_TMV!$A$5 -> 2026 | B6: =Inputs_TMV!$E$5 -> 43835000 | C6: =B6*Assumptions!$B$4 -> 547937.5 | D6: =MAX(C6-Assumptions!$B$9,0) -> 510758.5 | E6: =D6*Assumptions!$B$5 -> 653086.46 | F6: =E6*Assumptions!$B$8 -> 2351.1113 | G6: =(E6-F6)*Assumptions!$B$7 -> 65073.535 | H6: =(E6-F6-G6)*(1-Assumptions!$B$6) -> 0 | I6: =(E6-F6-G6)*Assumptions!$B$6 -> 585661.82 | J6: =Assumptions!$B$15 -> 7269118.6 | K6: =J6*Assumptions!$B$13 -> 334379.45 | L6: =MAX(0,MIN(I6-K6,J6)) -> 251282.36 | M6: =MAX(0,J6+K6-I6) -> 7017836.2 | N6: =C6*Assumptions!$B$5 -> 700625.76
A7: =Inputs_TMV!$A$6 -> 2027 | B7: =Inputs_TMV!$E$6 -> 43835000 | C7: =B7*Assumptions!$B$4 -> 547937.5 | D7: =MAX(C7-Assumptions!$B$9,0) -> 510758.5 | E7: =D7*Assumptions!$B$5 -> 653086.46 | F7: =E7*Assumptions!$B$8 -> 2351.1113 | G7: =(E7-F7)*Assumptions!$B$7 -> 65073.535 | H7: =(E7-F7-G7)*(1-Assumptions!$B$6) -> 0 | I7: =(E7-F7-G7)*Assumptions!$B$6 -> 585661.82 | J7: =M6 -> 7017836.2 | K7: =J7*Assumptions!$B$13 -> 322820.47 | L7: =MAX(0,MIN(I7-K7,J7)) -> 262841.35 | M7: =MAX(0,J7+K7-I7) -> 6754994.9 | N7: =C7*Assumptions!$B$5 -> 700625.76
A8: =Inputs_TMV!$A$7 -> 2028 | B8: =Inputs_TMV!$E$7 -> 43835000 | C8: =B8*Assumptions!$B$4 -> 547937.5 | D8: =MAX(C8-Assumptions!$B$9,0) -> 510758.5 | E8: =D8*Assumptions!$B$5 -> 653086.46 | F8: =E8*Assumptions!$B$8 -> 2351.1113 | G8: =(E8-F8)*Assumptions!$B$7 -> 65073.535 | H8: =(E8-F8-G8)*(1-Assumptions!$B$6) -> 0 | I8: =(E8-F8-G8)*Assumptions!$B$6 -> 585661.82 | J8: =M7 -> 6754994.9 | K8: =J8*Assumptions!$B$13 -> 310729.76 | L8: =MAX(0,MIN(I8-K8,J8)) -> 274932.05 | M8: =MAX(0,J8+K8-I8) -> 6480062.8 | N8: =C8*Assumptions!$B$5 -> 700625.76
A9: =Inputs_TMV!$A$8 -> 2029 | B9: =Inputs_TMV!$E$8 -> 43835000 | C9: =B9*Assumptions!$B$4 -> 547937.5 | D9: =MAX(C9-Assumptions!$B$9,0) -> 510758.5 | E9: =D9*Assumptions!$B$5 -> 653086.46 | F9: =E9*Assumptions!$B$8 -> 2351.1113 | G9: =(E9-F9)*Assumptions!$B$7 -> 65073.535 | H9: =(E9-F9-G9)*(1-Assumptions!$B$6) -> 0 | I9: =(E9-F9-G9)*Assumptions!$B$6 -> 585661.82 | J9: =M8 -> 6480062.8 | K9: =J9*Assumptions!$B$13 -> 298082.89 | L9: =MAX(0,MIN(I9-K9,J9)) -> 287578.93 | M9: =MAX(0,J9+K9-I9) -> 6192483.9 | N9: =C9*Assumptions!$B$5 -> 700625.76
A10: =Inputs_TMV!$A$9 -> 2030 | B10: =Inputs_TMV!$E$9 -> 43835000 | C10: =B10*Assumptions!$B$4 -> 547937.5 | D10: =MAX(C10-Assumptions!$B$9,0) -> 510758.5 | E10: =D10*Assumptions!$B$5 -> 653086.46 | F10: =E10*Assumptions!$B$8 -> 2351.1113 | G10: =(E10-F10)*Assumptions!$B$7 -> 65073.535 | H10: =(E10-F10-G10)*(1-Assumptions!$B$6) -> 0 | I10: =(E10-F10-G10)*Assumptions!$B$6 -> 585661.82 | J10: =M9 -> 6192483.9 | K10: =J10*Assumptions!$B$13 -> 284854.26 | L10: =MAX(0,MIN(I10-K10,J10)) -> 300807.56 | M10: =MAX(0,J10+K10-I10) -> 5891676.3 | N10: =C10*Assumptions!$B$5 -> 700625.76
A11: =Inputs_TMV!$A$10 -> 2031 | B11: =Inputs_TMV!$E$10 -> 43835000 | C11: =B11*Assumptions!$B$4 -> 547937.5 | D11: =MAX(C11-Assumptions!$B$9,0) -> 510758.5 | E11: =D11*Assumptions!$B$5 -> 653086.46 | F11: =E11*Assumptions!$B$8 -> 2351.1113 | G11: =(E11-F11)*Assumptions!$B$7 -> 65073.535 | H11: =(E11-F11-G11)*(1-Assumptions!$B$6) -> 0 | I11: =(E11-F11-G11)*Assumptions!$B$6 -> 585661.82 | J11: =M10 -> 5891676.3 | K11: =J11*Assumptions!$B$13 -> 271017.11 | L11: =MAX(0,MIN(I11-K11,J11)) -> 314644.71 | M11: =MAX(0,J11+K11-I11) -> 5577031.6 | N11: =C11*Assumptions!$B$5 -> 700625.76
A12: =Inputs_TMV!$A$11 -> 2032 | B12: =Inputs_TMV!$E$11 -> 43835000 | C12: =B12*Assumptions!$B$4 -> 547937.5 | D12: =MAX(C12-Assumptions!$B$9,0) -> 510758.5 | E12: =D12*Assumptions!$B$5 -> 653086.46 | F12: =E12*Assumptions!$B$8 -> 2351.1113 | G12: =(E12-F12)*Assumptions!$B$7 -> 65073.535 | H12: =(E12-F12-G12)*(1-Assumptions!$B$6) -> 0 | I12: =(E12-F12-G12)*Assumptions!$B$6 -> 585661.82 | J12: =M11 -> 5577031.6 | K12: =J12*Assumptions!$B$13 -> 256543.45 | L12: =MAX(0,MIN(I12-K12,J12)) -> 329118.36 | M12: =MAX(0,J12+K12-I12) -> 5247913.2 | N12: =C12*Assumptions!$B$5 -> 700625.76
A13: =Inputs_TMV!$A$12 -> 2033 | B13: =Inputs_TMV!$E$12 -> 43835000 | C13: =B13*Assumptions!$B$4 -> 547937.5 | D13: =MAX(C13-Assumptions!$B$9,0) -> 510758.5 | E13: =D13*Assumptions!$B$5 -> 653086.46 | F13: =E13*Assumptions!$B$8 -> 2351.1113 | G13: =(E13-F13)*Assumptions!$B$7 -> 65073.535 | H13: =(E13-F13-G13)*(1-Assumptions!$B$6) -> 0 | I13: =(E13-F13-G13)*Assumptions!$B$6 -> 585661.82 | J13: =M12 -> 5247913.2 | K13: =J13*Assumptions!$B$13 -> 241404.01 | L13: =MAX(0,MIN(I13-K13,J13)) -> 344257.81 | M13: =MAX(0,J13+K13-I13) -> 4903655.4 | N13: =C13*Assumptions!$B$5 -> 700625.76
A14: =Inputs_TMV!$A$13 -> 2034 | B14: =Inputs_TMV!$E$13 -> 43835000 | C14: =B14*Assumptions!$B$4 -> 547937.5 | D14: =MAX(C14-Assumptions!$B$9,0) -> 510758.5 | E14: =D14*Assumptions!$B$5 -> 653086.46 | F14: =E14*Assumptions!$B$8 -> 2351.1113 | G14: =(E14-F14)*Assumptions!$B$7 -> 65073.535 | H14: =(E14-F14-G14)*(1-Assumptions!$B$6) -> 0 | I14: =(E14-F14-G14)*Assumptions!$B$6 -> 585661.82 | J14: =M13 -> 4903655.4 | K14: =J14*Assumptions!$B$13 -> 225568.15 | L14: =MAX(0,MIN(I14-K14,J14)) -> 360093.67 | M14: =MAX(0,J14+K14-I14) -> 4543561.8 | N14: =C14*Assumptions!$B$5 -> 700625.76
A15: =Inputs_TMV!$A$14 -> 2035 | B15: =Inputs_TMV!$E$14 -> 43835000 | C15: =B15*Assumptions!$B$4 -> 547937.5 | D15: =MAX(C15-Assumptions!$B$9,0) -> 510758.5 | E15: =D15*Assumptions!$B$5 -> 653086.46 | F15: =E15*Assumptions!$B$8 -> 2351.1113 | G15: =(E15-F15)*Assumptions!$B$7 -> 65073.535 | H15: =(E15-F15-G15)*(1-Assumptions!$B$6) -> 0 | I15: =(E15-F15-G15)*Assumptions!$B$6 -> 585661.82 | J15: =M14 -> 4543561.8 | K15: =J15*Assumptions!$B$13 -> 209003.84 | L15: =MAX(0,MIN(I15-K15,J15)) -> 376657.98 | M15: =MAX(0,J15+K15-I15) -> 4166903.8 | N15: =C15*Assumptions!$B$5 -> 700625.76
A16: =Inputs_TMV!$A$15 -> 2036 | B16: =Inputs_TMV!$E$15 -> 43835000 | C16: =B16*Assumptions!$B$4 -> 547937.5 | D16: =MAX(C16-Assumptions!$B$9,0) -> 510758.5 | E16: =D16*Assumptions!$B$5 -> 653086.46 | F16: =E16*Assumptions!$B$8 -> 2351.1113 | G16: =(E16-F16)*Assumptions!$B$7 -> 65073.535 | H16: =(E16-F16-G16)*(1-Assumptions!$B$6) -> 0 | I16: =(E16-F16-G16)*Assumptions!$B$6 -> 585661.82 | J16: =M15 -> 4166903.8 | K16: =J16*Assumptions!$B$13 -> 191677.57 | L16: =MAX(0,MIN(I16-K16,J16)) -> 393984.24 | M16: =MAX(0,J16+K16-I16) -> 3772919.6 | N16: =C16*Assumptions!$B$5 -> 700625.76
A17: =Inputs_TMV!$A$16 -> 2037 | B17: =Inputs_TMV!$E$16 -> 43835000 | C17: =B17*Assumptions!$B$4 -> 547937.5 | D17: =MAX(C17-Assumptions!$B$9,0) -> 510758.5 | E17: =D17*Assumptions!$B$5 -> 653086.46 | F17: =E17*Assumptions!$B$8 -> 2351.1113 | G17: =(E17-F17)*Assumptions!$B$7 -> 65073.535 | H17: =(E17-F17-G17)*(1-Assumptions!$B$6) -> 0 | I17: =(E17-F17-G17)*Assumptions!$B$6 -> 585661.82 | J17: =M16 -> 3772919.6 | K17: =J17*Assumptions!$B$13 -> 173554.3 | L17: =MAX(0,MIN(I17-K17,J17)) -> 412107.52 | M17: =MAX(0,J17+K17-I17) -> 3360812 | N17: =C17*Assumptions!$B$5 -> 700625.76
A18: =Inputs_TMV!$A$17 -> 2038 | B18: =Inputs_TMV!$E$17 -> 43835000 | C18: =B18*Assumptions!$B$4 -> 547937.5 | D18: =MAX(C18-Assumptions!$B$9,0) -> 510758.5 | E18: =D18*Assumptions!$B$5 -> 653086.46 | F18: =E18*Assumptions!$B$8 -> 2351.1113 | G18: =(E18-F18)*Assumptions!$B$7 -> 65073.535 | H18: =(E18-F18-G18)*(1-Assumptions!$B$6) -> 0 | I18: =(E18-F18-G18)*Assumptions!$B$6 -> 585661.82 | J18: =M17 -> 3360812 | K18: =J18*Assumptions!$B$13 -> 154597.35 | L18: =MAX(0,MIN(I18-K18,J18)) -> 431064.46 | M18: =MAX(0,J18+K18-I18) -> 2929747.6 | N18: =C18*Assumptions!$B$5 -> 700625.76
A19: =Inputs_TMV!$A$18 -> 2039 | B19: =Inputs_TMV!$E$18 -> 43835000 | C19: =B19*Assumptions!$B$4 -> 547937.5 | D19: =MAX(C19-Assumptions!$B$9,0) -> 510758.5 | E19: =D19*Assumptions!$B$5 -> 653086.46 | F19: =E19*Assumptions!$B$8 -> 2351.1113 | G19: =(E19-F19)*Assumptions!$B$7 -> 65073.535 | H19: =(E19-F19-G19)*(1-Assumptions!$B$6) -> 0 | I19: =(E19-F19-G19)*Assumptions!$B$6 -> 585661.82 | J19: =M18 -> 2929747.6 | K19: =J19*Assumptions!$B$13 -> 134768.39 | L19: =MAX(0,MIN(I19-K19,J19)) -> 450893.43 | M19: =MAX(0,J19+K19-I19) -> 2478854.1 | N19: =C19*Assumptions!$B$5 -> 700625.76
A20: =Inputs_TMV!$A$19 -> 2040 | B20: =Inputs_TMV!$E$19 -> 43835000 | C20: =B20*Assumptions!$B$4 -> 547937.5 | D20: =MAX(C20-Assumptions!$B$9,0) -> 510758.5 | E20: =D20*Assumptions!$B$5 -> 653086.46 | F20: =E20*Assumptions!$B$8 -> 2351.1113 | G20: =(E20-F20)*Assumptions!$B$7 -> 65073.535 | H20: =(E20-F20-G20)*(1-Assumptions!$B$6) -> 0 | I20: =(E20-F20-G20)*Assumptions!$B$6 -> 585661.82 | J20: =M19 -> 2478854.1 | K20: =J20*Assumptions!$B$13 -> 114027.29 | L20: =MAX(0,MIN(I20-K20,J20)) -> 471634.53 | M20: =MAX(0,J20+K20-I20) -> 2007219.6 | N20: =C20*Assumptions!$B$5 -> 700625.76
A21: =Inputs_TMV!$A$20 -> 2041 | B21: =Inputs_TMV!$E$20 -> 43835000 | C21: =B21*Assumptions!$B$4 -> 547937.5 | D21: =MAX(C21-Assumptions!$B$9,0) -> 510758.5 | E21: =D21*Assumptions!$B$5 -> 653086.46 | F21: =E21*Assumptions!$B$8 -> 2351.1113 | G21: =(E21-F21)*Assumptions!$B$7 -> 65073.535 | H21: =(E21-F21-G21)*(1-Assumptions!$B$6) -> 0 | I21: =(E21-F21-G21)*Assumptions!$B$6 -> 585661.82 | J21: =M20 -> 2007219.6 | K21: =J21*Assumptions!$B$13 -> 92332.102 | L21: =MAX(0,MIN(I21-K21,J21)) -> 493329.71 | M21: =MAX(0,J21+K21-I21) -> 1513889.9 | N21: =C21*Assumptions!$B$5 -> 700625.76
A22: =Inputs_TMV!$A$21 -> 2042 | B22: =Inputs_TMV!$E$21 -> 43835000 | C22: =B22*Assumptions!$B$4 -> 547937.5 | D22: =MAX(C22-Assumptions!$B$9,0) -> 510758.5 | E22: =D22*Assumptions!$B$5 -> 653086.46 | F22: =E22*Assumptions!$B$8 -> 2351.1113 | G22: =(E22-F22)*Assumptions!$B$7 -> 65073.535 | H22: =(E22-F22-G22)*(1-Assumptions!$B$6) -> 0 | I22: =(E22-F22-G22)*Assumptions!$B$6 -> 585661.82 | J22: =M21 -> 1513889.9 | K22: =J22*Assumptions!$B$13 -> 69638.935 | L22: =MAX(0,MIN(I22-K22,J22)) -> 516022.88 | M22: =MAX(0,J22+K22-I22) -> 997867.02 | N22: =C22*Assumptions!$B$5 -> 700625.76
A23: =Inputs_TMV!$A$22 -> 2043 | B23: =Inputs_TMV!$E$22 -> 43835000 | C23: =B23*Assumptions!$B$4 -> 547937.5 | D23: =MAX(C23-Assumptions!$B$9,0) -> 510758.5 | E23: =D23*Assumptions!$B$5 -> 653086.46 | F23: =E23*Assumptions!$B$8 -> 2351.1113 | G23: =(E23-F23)*Assumptions!$B$7 -> 65073.535 | H23: =(E23-F23-G23)*(1-Assumptions!$B$6) -> 0 | I23: =(E23-F23-G23)*Assumptions!$B$6 -> 585661.82 | J23: =M22 -> 997867.02 | K23: =J23*Assumptions!$B$13 -> 45901.883 | L23: =MAX(0,MIN(I23-K23,J23)) -> 539759.93 | M23: =MAX(0,J23+K23-I23) -> 458107.08 | N23: =C23*Assumptions!$B$5 -> 700625.76
A24: =Inputs_TMV!$A$23 -> 2044 | B24: =Inputs_TMV!$E$23 -> 43835000 | C24: =B24*Assumptions!$B$4 -> 547937.5 | D24: =MAX(C24-Assumptions!$B$9,0) -> 510758.5 | E24: =D24*Assumptions!$B$5 -> 653086.46 | F24: =E24*Assumptions!$B$8 -> 2351.1113 | G24: =(E24-F24)*Assumptions!$B$7 -> 65073.535 | H24: =(E24-F24-G24)*(1-Assumptions!$B$6) -> 0 | I24: =(E24-F24-G24)*Assumptions!$B$6 -> 585661.82 | J24: =M23 -> 458107.08 | K24: =J24*Assumptions!$B$13 -> 21072.926 | L24: =MAX(0,MIN(I24-K24,J24)) -> 458107.08 | M24: =MAX(0,J24+K24-I24) -> 0 | N24: =C24*Assumptions!$B$5 -> 700625.76
A25: Totals | C25: =SUM(C6:C24) -> 10410812 | D25: =SUM(D6:D24) -> 9704411.5 | E25: =SUM(E6:E24) -> 12408643 | F25: =SUM(F6:F24) -> 44671.114 | G25: =SUM(G6:G24) -> 1236397.2 | H25: =SUM(H6:H24) -> 0 | I25: =SUM(I6:I24) -> 11127575 | K25: =SUM(K6:K24) -> 3751974.1 | L25: =SUM(L6:L24) -> 7269118.6 | N25: =SUM(N6:N24) -> 13311890
A27: TIF Note Payoff Year: | B27: =IFERROR(INDEX(A6:A24,MATCH(TRUE(),M6:M24=0,0)),"Not paid off in horizon") -> 2044
A28: NPV @ DiscRate: | H28: NPV Net TIF: | I28: =NPV(Assumptions!$B$34,I6:I24) -> 7077911 | M28: NPV Prop Tax: | N28: =NPV(Assumptions!$B$34,N6:N24) -> 8467287.2

Sheet Scenario_Compare
A1: Scenario Comparison — The Answer Page
A2: Full 19-year horizon (Pay 2026–2044). All numbers derived from Engine_* tabs, which pull live from Inputs_TMV. Change TMVs in Inputs_TMV and watch this page recalc.
A4: Metric | B4: Current ($54.866M flat) | C4: Mid Appeal ($52.15M flat) | D4: Aggressive Appeal ($50.0M flat) | E4: MAA Floor ($43.835M)
A5: TIF NOTE — over full 19-year horizon
A6: TIF Note Payoff Year | B6: =Engine_Current!B27 -> 2039 | C6: =Engine_Mid_Appeal!B27 -> 2040 | D6: =Engine_Agg_Appeal!B27 -> 2041 | E6: =Engine_MAA_Floor!B27 -> 2044
A7: Total Net TIF Received by Developer | B7: =Engine_Current!I25 -> 14131643 | C7: =Engine_Mid_Appeal!I25 -> 13391996 | D7: =Engine_Agg_Appeal!I25 -> 12806487 | E7: =Engine_MAA_Floor!I25 -> 11127575
A8: Total Note Interest Paid | B8: =Engine_Current!K25 -> 2608452.6 | C8: =Engine_Mid_Appeal!K25 -> 2815076.8 | D8: =Engine_Agg_Appeal!K25 -> 3005346.8 | E8: =Engine_MAA_Floor!K25 -> 3751974.1
A9: Total Note Principal Paid | B9: =Engine_Current!L25 -> 7269118.6 | C9: =Engine_Mid_Appeal!L25 -> 7269118.6 | D9: =Engine_Agg_Appeal!L25 -> 7269118.6 | E9: =Engine_MAA_Floor!L25 -> 7269118.6
A10: NPV Net TIF (@ DiscRate) | B10: =Engine_Current!I28 -> 8988707.3 | C10: =Engine_Mid_Appeal!I28 -> 8518240.2 | D10: =Engine_Agg_Appeal!I28 -> 8145815.9 | E10: =Engine_MAA_Floor!I28 -> 7077911
A11: PROPERTY TAX — full burden over 19 years
A12: Total Property Tax Paid (2026–2044) | B12: =Engine_Current!N25 -> 16661803 | C12: =Engine_Mid_Appeal!N25 -> 15837003 | D12: =Engine_Agg_Appeal!N25 -> 15184088 | E12: =Engine_MAA_Floor!N25 -> 13311890
A13: NPV Property Tax (@ DiscRate) | B13: =Engine_Current!N28 -> 10598065 | C13: =Engine_Mid_Appeal!N28 -> 10073435 | D13: =Engine_Agg_Appeal!N28 -> 9658135.2 | E13: =Engine_MAA_Floor!N28 -> 8467287.2
A14: VS. CURRENT — Tax Savings & TIF Reduction
A15: Tax Savings vs. Current (Nominal) | B15: =0 -> 0 | C15: =Engine_Current!N25-Engine_Mid_Appeal!N25 -> 824799.63 | D15: =Engine_Current!N25-Engine_Agg_Appeal!N25 -> 1477715.4 | E15: =Engine_Current!N25-Engine_MAA_Floor!N25 -> 3349913.4
A16: Tax Savings vs. Current (NPV @ DiscRate) | B16: =0 -> 0 | C16: =Engine_Current!N28-Engine_Mid_Appeal!N28 -> 524629.91 | D16: =Engine_Current!N28-Engine_Agg_Appeal!N28 -> 939929.72 | E16: =Engine_Current!N28-Engine_MAA_Floor!N28 -> 2130777.8
A17: TIF Reduction vs. Current (Nominal) | B17: =0 -> 0 | C17: =Engine_Current!I25-Engine_Mid_Appeal!I25 -> 739647.32 | D17: =Engine_Current!I25-Engine_Agg_Appeal!I25 -> 1325156.1 | E17: =Engine_Current!I25-Engine_MAA_Floor!I25 -> 3004068.3
A18: TIF Reduction vs. Current (NPV) | B18: =0 -> 0 | C18: =Engine_Current!I28-Engine_Mid_Appeal!I28 -> 470467.11 | D18: =Engine_Current!I28-Engine_Agg_Appeal!I28 -> 842891.38 | E18: =Engine_Current!I28-Engine_MAA_Floor!I28 -> 1910796.3
A19: NET ECONOMIC BENEFIT — TWO FRAMINGS (compare to Ehlers)
A20: Full Owner Cash Flow — NOMINAL (Tax Savings − TIF Reduction) | B20: =0 -> 0 | C20: =(Engine_Current!N25-Engine_Mid_Appeal!N25)-(Engine_Current!I25-Engine_Mid_Appeal!I25) -> 85152.314 | D20: =(Engine_Current!N25-Engine_Agg_Appeal!N25)-(Engine_Current!I25-Engine_Agg_Appeal!I25) -> 152559.34 | E20: =(Engine_Current!N25-Engine_MAA_Floor!N25)-(Engine_Current!I25-Engine_MAA_Floor!I25) -> 345845.06
A21: Full Owner Cash Flow — NPV @ DiscRate | B21: =0 -> 0 | C21: =(Engine_Current!N28-Engine_Mid_Appeal!N28)-(Engine_Current!I28-Engine_Mid_Appeal!I28) -> 54162.791 | D21: =(Engine_Current!N28-Engine_Agg_Appeal!N28)-(Engine_Current!I28-Engine_Agg_Appeal!I28) -> 97038.344 | E21: =(Engine_Current!N28-Engine_MAA_Floor!N28)-(Engine_Current!I28-Engine_MAA_Floor!I28) -> 219981.5
A22: ── Ehlers-Style Framing (TIF Reduction over Note Life − Slower Amort Cost) ──
A23: Annual TIF Reduction (Year-1 baseline) | B23: 0 | C23: =Engine_Current!I6-Engine_Mid_Appeal!I6 -> 38928.806 | D23: =Engine_Current!I6-Engine_Agg_Appeal!I6 -> 69745.056 | E23: =Engine_Current!I6-Engine_MAA_Floor!I6 -> 158108.86
A24: Years of Note Life (until payoff) | B24: =IFERROR(Engine_Current!B27-2025,0) -> 14 | C24: =IFERROR(Engine_Mid_Appeal!B27-2025,0) -> 15 | D24: =IFERROR(Engine_Agg_Appeal!B27-2025,0) -> 16 | E24: =IFERROR(Engine_MAA_Floor!B27-2025,0) -> 19
A25: Ehlers Cumulative Savings = Annual Red × Years | B25: 0 | C25: =C23*C24 -> 583932.09 | D25: =D23*D24 -> 1115920.9 | E25: =E23*E24 -> 3004068.3
A26: Slower Amortization Cost (extra Note interest) | B26: 0 | C26: =Engine_Mid_Appeal!K25-Engine_Current!K25 -> 206624.24 | D26: =Engine_Agg_Appeal!K25-Engine_Current!K25 -> 396894.24 | E26: =Engine_MAA_Floor!K25-Engine_Current!K25 -> 1143521.5
A27: Ehlers Net Benefit — NOMINAL | B27: 0 | C27: =C25-C26 -> 377307.86 | D27: =D25-D26 -> 719026.65 | E27: =E25-E26 -> 1860546.8
A28: ATTORNEY FEES (from Attorney_Fees tab)
A29: Total Attorney Fees — Nominal | B29: =-Attorney_Fees!$B$25 -> 0 | C29: =-Attorney_Fees!$C$25 -> -32557.88 | D29: =-Attorney_Fees!$D$25 -> -58330.871 | E29: =-Attorney_Fees!$E$25 -> -132233.42
A30: Total Attorney Fees — NPV @ DiscRate | B30: =-Attorney_Fees!$B$26 -> 0 | C30: =-Attorney_Fees!$C$26 -> -26443.681 | D30: =-Attorney_Fees!$D$26 -> -47376.639 | E30: =-Attorney_Fees!$E$26 -> -107400.68
A31: Net Benefit AFTER Attorney Fees — NOMINAL | B31: =B20+B29 -> 0 | C31: =C20+C29 -> 52594.434 | D31: =D20+D29 -> 94228.467 | E31: =E20+E29 -> 213611.63
A32: Net Benefit AFTER Attorney Fees — NPV @ DiscRate | B32: =B21+B30 -> 0 | C32: =C21+C30 -> 27719.11 | D32: =D21+D30 -> 49661.705 | E32: =E21+E30 -> 112580.82
A34: TAKEAWAYS
A35: The "Net Benefit vs. Current" rows above replicate the Ehlers framing — total benefit = (tax savings from lower assessed value) minus (TIF reduction from same).
A36: Note the asymmetry: deeper appeals are MORE valuable, not less. The MAA Floor scenario captures the maximum economic upside.
A37: The TIF Note STILL FULLY AMORTIZES under every scenario including the MAA floor — Note retirement is not at risk. The "Payoff Year" row shows this directly.
A38: The IDP/Shaver model truncates at year 10 (2035). At that point, the TIF Note is NOT YET PAID OFF — meaning year 10 captures all the cost of the slower amortization but NONE of the back-end tax savings that continue through 2044 even after the Note is retired.
A39: NPV uses a 5% discount rate, consistent with KA Nov-2025 analysis and Ehlers. The Shaver 8% rate over-discounts future TIF receipts (the actual TIF Note carries 4.6%).
A40: Attorney fees: this model applies 25% × 1 year of tax savings per appeal event (industry standard), with 3 appeal events over the 19-year hold (Attorney_Fees tab). The IDP/Shaver $373,694 figure applies the fee uniformly across 10 years — which only makes sense if every year is a separately-priced appeal. Even applying his exaggerated fee structure to this model, the Aggressive Appeal still produces a positive net benefit.

Sheet Scenario_Analysis_4Cases
A1: Scenario Analysis — 4 Cases (Component Breakdown by Year)
A2: Four scenarios over 2026-2045. Each scenario block shows year-by-year components and totals/NPV in the right columns (V-Z). ★ The decision-relevant answer is the DELTA between scenarios (rows 49-51) — that's what appealing saves vs. doing nothing. Net Cash Flow absolute totals are NEGATIVE for all scenarios because property tax paid > TIF received over 20 years — that's expected for any real estate (LLC is a net taxpayer). The MAA Floor appeal saves the LLC $11.5M nominal / $5.5M NPV@5% vs. baseline.
A4: Parameters & Inputs (yellow = adjustable)
A5: Attorney Fee % | B5: 0.25 | C5: Baseline TMV Growth | D5: 0.04 | E5: Appeal Target CAGR | F5: 0.025
A6: NPV Discount Rates → | B6: 0.05 | C6: 0.06 | D6: 0.07 | E6: 0.08
A7: Scenario 2026 Starting TMVs → | B7: 54866000 | C7: 50000000 | D7: 47500000 | E7: 43835000
B8: S1: No Appeal | C8: S2: Mid Appeal | D8: S3: Aggressive | E8: S4: MAA Floor
A9: ★ THE ANSWER (delta vs. no-appeal baseline, NPV@5%): Mid Appeal saves $2.54M • Aggressive saves $3.13M • MAA Floor saves $5.50M → Scroll to row 47 for full detail by NPV rate.
A10: SCENARIO 1: BASELINE — No Appeal, $54.866M @ 4%/yr growth
A11: Component | B11: 2026 | C11: 2027 | D11: 2028 | E11: 2029 | F11: 2030 | G11: 2031 | H11: 2032 | I11: 2033 | J11: 2034 | K11: 2035 | L11: 2036 | M11: 2037 | N11: 2038 | O11: 2039 | P11: 2040 | Q11: 2041 | R11: 2042 | S11: 2043 | T11: 2044 | U11: 2045 | V11: Total | W11: NPV 5% | X11: NPV 6% | Y11: NPV 7% | Z11: NPV 8%
A12: Taxable Market Value (TMV) | B12: =Scenario_Analysis_4Cases!$B$7*(1+Scenario_Analysis_4Cases!$D$5)^0 -> 54866000 | C12: =Scenario_Analysis_4Cases!$B$7*(1+Scenario_Analysis_4Cases!$D$5)^1 -> 57060640 | D12: =Scenario_Analysis_4Cases!$B$7*(1+Scenario_Analysis_4Cases!$D$5)^2 -> 59343066 | E12: =Scenario_Analysis_4Cases!$B$7*(1+Scenario_Analysis_4Cases!$D$5)^3 -> 61716788 | F12: =Scenario_Analysis_4Cases!$B$7*(1+Scenario_Analysis_4Cases!$D$5)^4 -> 64185460 | G12: =Scenario_Analysis_4Cases!$B$7*(1+Scenario_Analysis_4Cases!$D$5)^5 -> 66752878 | H12: =Scenario_Analysis_4Cases!$B$7*(1+Scenario_Analysis_4Cases!$D$5)^6 -> 69422993 | I12: =Scenario_Analysis_4Cases!$B$7*(1+Scenario_Analysis_4Cases!$D$5)^7 -> 72199913 | J12: =Scenario_Analysis_4Cases!$B$7*(1+Scenario_Analysis_4Cases!$D$5)^8 -> 75087910 | K12: =Scenario_Analysis_4Cases!$B$7*(1+Scenario_Analysis_4Cases!$D$5)^9 -> 78091426 | L12: =Scenario_Analysis_4Cases!$B$7*(1+Scenario_Analysis_4Cases!$D$5)^10 -> 81215083 | M12: =Scenario_Analysis_4Cases!$B$7*(1+Scenario_Analysis_4Cases!$D$5)^11 -> 84463686 | N12: =Scenario_Analysis_4Cases!$B$7*(1+Scenario_Analysis_4Cases!$D$5)^12 -> 87842234 | O12: =Scenario_Analysis_4Cases!$B$7*(1+Scenario_Analysis_4Cases!$D$5)^13 -> 91355923 | P12: =Scenario_Analysis_4Cases!$B$7*(1+Scenario_Analysis_4Cases!$D$5)^14 -> 95010160 | Q12: =Scenario_Analysis_4Cases!$B$7*(1+Scenario_Analysis_4Cases!$D$5)^15 -> 98810566 | R12: =Scenario_Analysis_4Cases!$B$7*(1+Scenario_Analysis_4Cases!$D$5)^16 -> 1.0276299e+08 | S12: =Scenario_Analysis_4Cases!$B$7*(1+Scenario_Analysis_4Cases!$D$5)^17 -> 1.0687351e+08 | T12: =Scenario_Analysis_4Cases!$B$7*(1+Scenario_Analysis_4Cases!$D$5)^18 -> 1.1114845e+08 | U12: =Scenario_Analysis_4Cases!$B$7*(1+Scenario_Analysis_4Cases!$D$5)^19 -> 1.1559439e+08 | V12: — | W12: — | X12: — | Y12: — | Z12: —
A13: Property Tax Paid (out) | B13: =-B12*Assumptions!$B$4*Assumptions!$B$5 -> -876936.99 | C13: =-C12*Assumptions!$B$4*Assumptions!$B$5 -> -912014.47 | D13: =-D12*Assumptions!$B$4*Assumptions!$B$5 -> -948495.05 | E13: =-E12*Assumptions!$B$4*Assumptions!$B$5 -> -986434.86 | F13: =-F12*Assumptions!$B$4*Assumptions!$B$5 -> -1025892.2 | G13: =-G12*Assumptions!$B$4*Assumptions!$B$5 -> -1066927.9 | H13: =-H12*Assumptions!$B$4*Assumptions!$B$5 -> -1109605.1 | I13: =-I12*Assumptions!$B$4*Assumptions!$B$5 -> -1153989.3 | ... U13: =-U12*Assumptions!$B$4*Assumptions!$B$5 -> -1847574 | V13: =SUM(B13:U13) -> -26113499 | W13: =NPV(Scenario_Analysis_4Cases!$B$6,B13:U13) -> -15275254 | X13: =NPV(Scenario_Analysis_4Cases!$C$6,B13:U13) -> -13890570 | Y13: =NPV(Scenario_Analysis_4Cases!$D$6,B13:U13) -> -12679695 | Z13: =NPV(Scenario_Analysis_4Cases!$E$6,B13:U13) -> -11617189
A14: Net TIF Received (in) | B14: =MIN(MAX(0,B12*Assumptions!$B$4-Assumptions!$B$9)*Assumptions!$B$5*(1-Assumptions!$B$7),(Assumptions!$B$15)*(1+Assumptions!$B$13)) -> 746457.92 | C14: =MIN(MAX(0,C12*Assumptions!$B$4-Assumptions!$B$9)*Assumptions!$B$5*(1-Assumptions!$B$7),(B17)*(1+Assumptions!$B$13)) -> 778027.66 | D14: =MIN(MAX(0,D12*Assumptions!$B$4-Assumptions!$B$9)*Assumptions!$B$5*(1-Assumptions!$B$7),(C17)*(1+Assumptions!$B$13)) -> 810860.18 | E14: =MIN(MAX(0,E12*Assumptions!$B$4-Assumptions!$B$9)*Assumptions!$B$5*(1-Assumptions!$B$7),(D17)*(1+Assumptions!$B$13)) -> 845006 | F14: =MIN(MAX(0,F12*Assumptions!$B$4-Assumptions!$B$9)*Assumptions!$B$5*(1-Assumptions!$B$7),(E17)*(1+Assumptions!$B$13)) -> 880517.65 | G14: =MIN(MAX(0,G12*Assumptions!$B$4-Assumptions!$B$9)*Assumptions!$B$5*(1-Assumptions!$B$7),(F17)*(1+Assumptions!$B$13)) -> 917449.78 | H14: =MIN(MAX(0,H12*Assumptions!$B$4-Assumptions!$B$9)*Assumptions!$B$5*(1-Assumptions!$B$7),(G17)*(1+Assumptions!$B$13)) -> 955859.18 | I14: =MIN(MAX(0,I12*Assumptions!$B$4-Assumptions!$B$9)*Assumptions!$B$5*(1-Assumptions!$B$7),(H17)*(1+Assumptions!$B$13)) -> 995804.96 | J14: =MIN(MAX(0,J12*Assumptions!$B$4-Assumptions!$B$9)*Assumptions!$B$5*(1-Assumptions!$B$7),(I17)*(1+Assumptions!$B$13)) -> 1037348.6 | ... U14: =MIN(MAX(0,U12*Assumptions!$B$4-Assumptions!$B$9)*Assumptions!$B$5*(1-Assumptions!$B$7),(T17)*(1+Assumptions!$B$13)) -> 0 | V14: =SUM(B14:U14) -> 9461953.2 | W14: =NPV(Scenario_Analysis_4Cases!$B$6,B14:U14) -> 7114228.6 | X14: =NPV(Scenario_Analysis_4Cases!$C$6,B14:U14) -> 6747512.6 | Y14: =NPV(Scenario_Analysis_4Cases!$D$6,B14:U14) -> 6407967.4 | Z14: =NPV(Scenario_Analysis_4Cases!$E$6,B14:U14) -> 6093165.7
A15: Attorney Fee Paid (out) | B15: 0 | C15: 0 | D15: 0 | E15: 0 | F15: 0 | G15: 0 | H15: 0 | I15: 0 | J15: 0 | K15: 0 | L15: 0 | M15: 0 | N15: 0 | O15: 0 | P15: 0 | Q15: 0 | R15: 0 | S15: 0 | T15: 0 | U15: 0 | V15: =SUM(B15:U15) -> 0 | W15: =NPV(Scenario_Analysis_4Cases!$B$6,B15:U15) -> 0 | X15: =NPV(Scenario_Analysis_4Cases!$C$6,B15:U15) -> 0 | Y15: =NPV(Scenario_Analysis_4Cases!$D$6,B15:U15) -> 0 | Z15: =NPV(Scenario_Analysis_4Cases!$E$6,B15:U15) -> 0
A16: Net Cash Flow (Tax + TIF + Fee) | B16: =B13+B14+B15 -> -130479.07 | C16: =C13+C14+C15 -> -133986.82 | D16: =D13+D14+D15 -> -137634.88 | E16: =E13+E14+E15 -> -141428.86 | F16: =F13+F14+F15 -> -145374.6 | G16: =G13+G14+G15 -> -149478.16 | H16: =H13+H14+H15 -> -153745.88 | I16: =I13+I14+I15 -> -158184.3 | ... U16: =U13+U14+U15 -> -1847574 | V16: =SUM(B16:U16) -> -16651545 | W16: =NPV(Scenario_Analysis_4Cases!$B$6,B16:U16) -> -8161025.7 | X16: =NPV(Scenario_Analysis_4Cases!$C$6,B16:U16) -> -7143057.4 | Y16: =NPV(Scenario_Analysis_4Cases!$D$6,B16:U16) -> -6271727.2 | Z16: =NPV(Scenario_Analysis_4Cases!$E$6,B16:U16) -> -5524023.3
A17: Note End Balance (info) | B17: =MAX(0,(Assumptions!$B$15)*(1+Assumptions!$B$13)-B14) -> 6857040.1 | C17: =MAX(0,(B17)*(1+Assumptions!$B$13)-C14) -> 6394436.3 | D17: =MAX(0,(C17)*(1+Assumptions!$B$13)-D14) -> 5877720.2 | E17: =MAX(0,(D17)*(1+Assumptions!$B$13)-E14) -> 5303089.3 | F17: =MAX(0,(E17)*(1+Assumptions!$B$13)-F14) -> 4666513.8 | G17: =MAX(0,(F17)*(1+Assumptions!$B$13)-G14) -> 3963723.6 | H17: =MAX(0,(G17)*(1+Assumptions!$B$13)-H14) -> 3190195.7 | I17: =MAX(0,(H17)*(1+Assumptions!$B$13)-I14) -> 2341139.8 | J17: =MAX(0,(I17)*(1+Assumptions!$B$13)-J14) -> 1411483.6 | ... U17: =MAX(0,(T17)*(1+Assumptions!$B$13)-U14) -> 0 | V17: — | W17: — | X17: — | Y17: — | Z17: —
A19: SCENARIO 2: MID APPEAL — $50M start, 4% growth, 5-yr appeals to 2.5% CAGR line
A20: Component | B20: 2026 | C20: 2027 | D20: 2028 | E20: 2029 | F20: 2030 | G20: 2031 | H20: 2032 | I20: 2033 | J20: 2034 | K20: 2035 | L20: 2036 | M20: 2037 | N20: 2038 | O20: 2039 | P20: 2040 | Q20: 2041 | R20: 2042 | S20: 2043 | T20: 2044 | U20: 2045 | V20: Total | W20: NPV 5% | X20: NPV 6% | Y20: NPV 7% | Z20: NPV 8%
A21: Taxable Market Value (TMV) | B21: =Scenario_Analysis_4Cases!$C$7*(1+Scenario_Analysis_4Cases!$F$5)^0 -> 50000000 | C21: =B21*(1+Scenario_Analysis_4Cases!$D$5) -> 52000000 | D21: =C21*(1+Scenario_Analysis_4Cases!$D$5) -> 54080000 | E21: =D21*(1+Scenario_Analysis_4Cases!$D$5) -> 56243200 | F21: =E21*(1+Scenario_Analysis_4Cases!$D$5) -> 58492928 | G21: =Scenario_Analysis_4Cases!$C$7*(1+Scenario_Analysis_4Cases!$F$5)^5 -> 56570411 | H21: =G21*(1+Scenario_Analysis_4Cases!$D$5) -> 58833227 | I21: =H21*(1+Scenario_Analysis_4Cases!$D$5) -> 61186556 | J21: =I21*(1+Scenario_Analysis_4Cases!$D$5) -> 63634018 | K21: =J21*(1+Scenario_Analysis_4Cases!$D$5) -> 66179379 | L21: =Scenario_Analysis_4Cases!$C$7*(1+Scenario_Analysis_4Cases!$F$5)^10 -> 64004227 | M21: =L21*(1+Scenario_Analysis_4Cases!$D$5) -> 66564396 | N21: =M21*(1+Scenario_Analysis_4Cases!$D$5) -> 69226972 | O21: =N21*(1+Scenario_Analysis_4Cases!$D$5) -> 71996051 | P21: =O21*(1+Scenario_Analysis_4Cases!$D$5) -> 74875893 | Q21: =Scenario_Analysis_4Cases!$C$7*(1+Scenario_Analysis_4Cases!$F$5)^15 -> 72414908 | R21: =Q21*(1+Scenario_Analysis_4Cases!$D$5) -> 75311505 | S21: =R21*(1+Scenario_Analysis_4Cases!$D$5) -> 78323965 | T21: =S21*(1+Scenario_Analysis_4Cases!$D$5) -> 81456923 | U21: =T21*(1+Scenario_Analysis_4Cases!$D$5) -> 84715200 | V21: — | W21: — | X21: — | Y21: — | Z21: —
A22: Property Tax Paid (out) | B22: =-B21*Assumptions!$B$4*Assumptions!$B$5 -> -799162.5 | C22: =-C21*Assumptions!$B$4*Assumptions!$B$5 -> -831129 | D22: =-D21*Assumptions!$B$4*Assumptions!$B$5 -> -864374.16 | E22: =-E21*Assumptions!$B$4*Assumptions!$B$5 -> -898949.13 | F22: =-F21*Assumptions!$B$4*Assumptions!$B$5 -> -934907.09 | G22: =-G21*Assumptions!$B$4*Assumptions!$B$5 -> -904179.02 | H22: =-H21*Assumptions!$B$4*Assumptions!$B$5 -> -940346.18 | I22: =-I21*Assumptions!$B$4*Assumptions!$B$5 -> -977960.02 | ... U22: =-U21*Assumptions!$B$4*Assumptions!$B$5 -> -1354024.2 | V22: =SUM(B22:U22) -> -21035711 | W22: =NPV(Scenario_Analysis_4Cases!$B$6,B22:U22) -> -12578977 | X22: =NPV(Scenario_Analysis_4Cases!$C$6,B22:U22) -> -11487527 | Y22: =NPV(Scenario_Analysis_4Cases!$D$6,B22:U22) -> -10530004 | Z22: =NPV(Scenario_Analysis_4Cases!$E$6,B22:U22) -> -9687066.2
A23: Net TIF Received (in) | B23: =MIN(MAX(0,B21*Assumptions!$B$4-Assumptions!$B$9)*Assumptions!$B$5*(1-Assumptions!$B$7),(Assumptions!$B$15)*(1+Assumptions!$B$13)) -> 676460.88 | C23: =MIN(MAX(0,C21*Assumptions!$B$4-Assumptions!$B$9)*Assumptions!$B$5*(1-Assumptions!$B$7),(B26)*(1+Assumptions!$B$13)) -> 705230.73 | D23: =MIN(MAX(0,D21*Assumptions!$B$4-Assumptions!$B$9)*Assumptions!$B$5*(1-Assumptions!$B$7),(C26)*(1+Assumptions!$B$13)) -> 735151.37 | E23: =MIN(MAX(0,E21*Assumptions!$B$4-Assumptions!$B$9)*Assumptions!$B$5*(1-Assumptions!$B$7),(D26)*(1+Assumptions!$B$13)) -> 766268.84 | F23: =MIN(MAX(0,F21*Assumptions!$B$4-Assumptions!$B$9)*Assumptions!$B$5*(1-Assumptions!$B$7),(E26)*(1+Assumptions!$B$13)) -> 798631.01 | G23: =MIN(MAX(0,G21*Assumptions!$B$4-Assumptions!$B$9)*Assumptions!$B$5*(1-Assumptions!$B$7),(F26)*(1+Assumptions!$B$13)) -> 770975.74 | H23: =MIN(MAX(0,H21*Assumptions!$B$4-Assumptions!$B$9)*Assumptions!$B$5*(1-Assumptions!$B$7),(G26)*(1+Assumptions!$B$13)) -> 803526.19 | I23: =MIN(MAX(0,I21*Assumptions!$B$4-Assumptions!$B$9)*Assumptions!$B$5*(1-Assumptions!$B$7),(H26)*(1+Assumptions!$B$13)) -> 837378.65 | J23: =MIN(MAX(0,J21*Assumptions!$B$4-Assumptions!$B$9)*Assumptions!$B$5*(1-Assumptions!$B$7),(I26)*(1+Assumptions!$B$13)) -> 872585.21 | ... U23: =MIN(MAX(0,U21*Assumptions!$B$4-Assumptions!$B$9)*Assumptions!$B$5*(1-Assumptions!$B$7),(T26)*(1+Assumptions!$B$13)) -> 0 | V23: =SUM(B23:U23) -> 9789184.8 | W23: =NPV(Scenario_Analysis_4Cases!$B$6,B23:U23) -> 7095799.5 | X23: =NPV(Scenario_Analysis_4Cases!$C$6,B23:U23) -> 6688123.9 | Y23: =NPV(Scenario_Analysis_4Cases!$D$6,B23:U23) -> 6314098.9 | Z23: =NPV(Scenario_Analysis_4Cases!$E$6,B23:U23) -> 5970391.1
A24: Attorney Fee Paid (out) | B24: =-Scenario_Analysis_4Cases!$B$5*MAX(0,(Scenario_Analysis_4Cases!$B$7*(1+Scenario_Analysis_4Cases!$D$5)^0-B21))*Assumptions!$B$4*Assumptions!$B$5 -> -19443.624 | C24: 0 | D24: 0 | E24: 0 | F24: 0 | G24: =-Scenario_Analysis_4Cases!$B$5*MAX(0,(Scenario_Analysis_4Cases!$B$7*(1+Scenario_Analysis_4Cases!$D$5)^5-G21))*Assumptions!$B$4*Assumptions!$B$5 -> -40687.231 | H24: 0 | I24: 0 | J24: 0 | K24: 0 | L24: =-Scenario_Analysis_4Cases!$B$5*MAX(0,(Scenario_Analysis_4Cases!$B$7*(1+Scenario_Analysis_4Cases!$D$5)^10-L21))*Assumptions!$B$4*Assumptions!$B$5 -> -68771.352 | M24: 0 | N24: 0 | O24: 0 | P24: 0 | Q24: =-Scenario_Analysis_4Cases!$B$5*MAX(0,(Scenario_Analysis_4Cases!$B$7*(1+Scenario_Analysis_4Cases!$D$5)^15-Q21))*Assumptions!$B$4*Assumptions!$B$5 -> -105472.1 | R24: 0 | S24: 0 | T24: 0 | U24: 0 | V24: =SUM(B24:U24) -> -234374.31 | W24: =NPV(Scenario_Analysis_4Cases!$B$6,B24:U24) -> -137406.34 | X24: =NPV(Scenario_Analysis_4Cases!$C$6,B24:U24) -> -124772.52 | Y24: =NPV(Scenario_Analysis_4Cases!$D$6,B24:U24) -> -113683.05 | Z24: =NPV(Scenario_Analysis_4Cases!$E$6,B24:U24) -> -103924.37
A25: Net Cash Flow (Tax + TIF + Fee) | B25: =B22+B23+B24 -> -142145.24 | C25: =C22+C23+C24 -> -125898.27 | D25: =D22+D23+D24 -> -129222.79 | E25: =E22+E23+E24 -> -132680.28 | F25: =F22+F23+F24 -> -136276.08 | G25: =G22+G23+G24 -> -173890.5 | H25: =H22+H23+H24 -> -136819.99 | I25: =I22+I23+I24 -> -140581.37 | ... U25: =U22+U23+U24 -> -1354024.2 | V25: =SUM(B25:U25) -> -11480901 | W25: =NPV(Scenario_Analysis_4Cases!$B$6,B25:U25) -> -5620583.3 | X25: =NPV(Scenario_Analysis_4Cases!$C$6,B25:U25) -> -4924176.1 | Y25: =NPV(Scenario_Analysis_4Cases!$D$6,B25:U25) -> -4329587.9 | Z25: =NPV(Scenario_Analysis_4Cases!$E$6,B25:U25) -> -3820599.5
A26: Note End Balance (info) | B26: =MAX(0,(Assumptions!$B$15)*(1+Assumptions!$B$13)-B23) -> 6927037.1 | C26: =MAX(0,(B26)*(1+Assumptions!$B$13)-C23) -> 6540450.1 | D26: =MAX(0,(C26)*(1+Assumptions!$B$13)-D23) -> 6106159.5 | E26: =MAX(0,(D26)*(1+Assumptions!$B$13)-E23) -> 5620773.9 | F26: =MAX(0,(E26)*(1+Assumptions!$B$13)-F23) -> 5080698.5 | G26: =MAX(0,(F26)*(1+Assumptions!$B$13)-G23) -> 4543434.9 | H26: =MAX(0,(G26)*(1+Assumptions!$B$13)-H23) -> 3948906.7 | I26: =MAX(0,(H26)*(1+Assumptions!$B$13)-I23) -> 3293177.8 | J26: =MAX(0,(I26)*(1+Assumptions!$B$13)-J23) -> 2572078.8 | ... U26: =MAX(0,(T26)*(1+Assumptions!$B$13)-U23) -> 0 | V26: — | W26: — | X26: — | Y26: — | Z26: —
A28: SCENARIO 3: AGGRESSIVE — $47.5M start, 4% growth, 5-yr appeals to 2.5% CAGR line
A29: Component | B29: 2026 | C29: 2027 | D29: 2028 | E29: 2029 | F29: 2030 | G29: 2031 | H29: 2032 | I29: 2033 | J29: 2034 | K29: 2035 | L29: 2036 | M29: 2037 | N29: 2038 | O29: 2039 | P29: 2040 | Q29: 2041 | R29: 2042 | S29: 2043 | T29: 2044 | U29: 2045 | V29: Total | W29: NPV 5% | X29: NPV 6% | Y29: NPV 7% | Z29: NPV 8%
A30: Taxable Market Value (TMV) | B30: =Scenario_Analysis_4Cases!$D$7*(1+Scenario_Analysis_4Cases!$F$5)^0 -> 47500000 | C30: =B30*(1+Scenario_Analysis_4Cases!$D$5) -> 49400000 | D30: =C30*(1+Scenario_Analysis_4Cases!$D$5) -> 51376000 | E30: =D30*(1+Scenario_Analysis_4Cases!$D$5) -> 53431040 | F30: =E30*(1+Scenario_Analysis_4Cases!$D$5) -> 55568282 | G30: =Scenario_Analysis_4Cases!$D$7*(1+Scenario_Analysis_4Cases!$F$5)^5 -> 53741890 | H30: =G30*(1+Scenario_Analysis_4Cases!$D$5) -> 55891566 | I30: =H30*(1+Scenario_Analysis_4Cases!$D$5) -> 58127228 | J30: =I30*(1+Scenario_Analysis_4Cases!$D$5) -> 60452317 | K30: =J30*(1+Scenario_Analysis_4Cases!$D$5) -> 62870410 | L30: =Scenario_Analysis_4Cases!$D$7*(1+Scenario_Analysis_4Cases!$F$5)^10 -> 60804016 | M30: =L30*(1+Scenario_Analysis_4Cases!$D$5) -> 63236176 | N30: =M30*(1+Scenario_Analysis_4Cases!$D$5) -> 65765624 | O30: =N30*(1+Scenario_Analysis_4Cases!$D$5) -> 68396248 | P30: =O30*(1+Scenario_Analysis_4Cases!$D$5) -> 71132098 | Q30: =Scenario_Analysis_4Cases!$D$7*(1+Scenario_Analysis_4Cases!$F$5)^15 -> 68794163 | R30: =Q30*(1+Scenario_Analysis_4Cases!$D$5) -> 71545929 | S30: =R30*(1+Scenario_Analysis_4Cases!$D$5) -> 74407767 | T30: =S30*(1+Scenario_Analysis_4Cases!$D$5) -> 77384077 | U30: =T30*(1+Scenario_Analysis_4Cases!$D$5) -> 80479440 | V30: — | W30: — | X30: — | Y30: — | Z30: —
A31: Property Tax Paid (out) | B31: =-B30*Assumptions!$B$4*Assumptions!$B$5 -> -759204.38 | C31: =-C30*Assumptions!$B$4*Assumptions!$B$5 -> -789572.55 | D31: =-D30*Assumptions!$B$4*Assumptions!$B$5 -> -821155.45 | E31: =-E30*Assumptions!$B$4*Assumptions!$B$5 -> -854001.67 | F31: =-F30*Assumptions!$B$4*Assumptions!$B$5 -> -888161.74 | G31: =-G30*Assumptions!$B$4*Assumptions!$B$5 -> -858970.07 | H31: =-H30*Assumptions!$B$4*Assumptions!$B$5 -> -893328.87 | I31: =-I30*Assumptions!$B$4*Assumptions!$B$5 -> -929062.02 | ... U31: =-U30*Assumptions!$B$4*Assumptions!$B$5 -> -1286323 | V31: =SUM(B31:U31) -> -19983926 | W31: =NPV(Scenario_Analysis_4Cases!$B$6,B31:U31) -> -11950028 | X31: =NPV(Scenario_Analysis_4Cases!$C$6,B31:U31) -> -10913151 | Y31: =NPV(Scenario_Analysis_4Cases!$D$6,B31:U31) -> -10003504 | Z31: =NPV(Scenario_Analysis_4Cases!$E$6,B31:U31) -> -9202712.9
A32: Net TIF Received (in) | B32: =MIN(MAX(0,B30*Assumptions!$B$4-Assumptions!$B$9)*Assumptions!$B$5*(1-Assumptions!$B$7),(Assumptions!$B$15)*(1+Assumptions!$B$13)) -> 640498.57 | C32: =MIN(MAX(0,C30*Assumptions!$B$4-Assumptions!$B$9)*Assumptions!$B$5*(1-Assumptions!$B$7),(B35)*(1+Assumptions!$B$13)) -> 667829.92 | D32: =MIN(MAX(0,D30*Assumptions!$B$4-Assumptions!$B$9)*Assumptions!$B$5*(1-Assumptions!$B$7),(C35)*(1+Assumptions!$B$13)) -> 696254.54 | E32: =MIN(MAX(0,E30*Assumptions!$B$4-Assumptions!$B$9)*Assumptions!$B$5*(1-Assumptions!$B$7),(D35)*(1+Assumptions!$B$13)) -> 725816.13 | F32: =MIN(MAX(0,F30*Assumptions!$B$4-Assumptions!$B$9)*Assumptions!$B$5*(1-Assumptions!$B$7),(E35)*(1+Assumptions!$B$13)) -> 756560.19 | G32: =MIN(MAX(0,G30*Assumptions!$B$4-Assumptions!$B$9)*Assumptions!$B$5*(1-Assumptions!$B$7),(F35)*(1+Assumptions!$B$13)) -> 730287.69 | H32: =MIN(MAX(0,H30*Assumptions!$B$4-Assumptions!$B$9)*Assumptions!$B$5*(1-Assumptions!$B$7),(G35)*(1+Assumptions!$B$13)) -> 761210.61 | I32: =MIN(MAX(0,I30*Assumptions!$B$4-Assumptions!$B$9)*Assumptions!$B$5*(1-Assumptions!$B$7),(H35)*(1+Assumptions!$B$13)) -> 793370.45 | J32: =MIN(MAX(0,J30*Assumptions!$B$4-Assumptions!$B$9)*Assumptions!$B$5*(1-Assumptions!$B$7),(I35)*(1+Assumptions!$B$13)) -> 826816.68 | ... U32: =MIN(MAX(0,U30*Assumptions!$B$4-Assumptions!$B$9)*Assumptions!$B$5*(1-Assumptions!$B$7),(T35)*(1+Assumptions!$B$13)) -> 0 | V32: =SUM(B32:U32) -> 9961032.2 | W32: =NPV(Scenario_Analysis_4Cases!$B$6,B32:U32) -> 7086367.7 | X32: =NPV(Scenario_Analysis_4Cases!$C$6,B32:U32) -> 6657864.4 | Y32: =NPV(Scenario_Analysis_4Cases!$D$6,B32:U32) -> 6266473.8 | Z32: =NPV(Scenario_Analysis_4Cases!$E$6,B32:U32) -> 5908350.2
A33: Attorney Fee Paid (out) | B33: =-Scenario_Analysis_4Cases!$B$5*MAX(0,(Scenario_Analysis_4Cases!$B$7*(1+Scenario_Analysis_4Cases!$D$5)^0-B30))*Assumptions!$B$4*Assumptions!$B$5 -> -29433.155 | C33: 0 | D33: 0 | E33: 0 | F33: 0 | G33: =-Scenario_Analysis_4Cases!$B$5*MAX(0,(Scenario_Analysis_4Cases!$B$7*(1+Scenario_Analysis_4Cases!$D$5)^5-G30))*Assumptions!$B$4*Assumptions!$B$5 -> -51989.469 | H33: 0 | I33: 0 | J33: 0 | K33: 0 | L33: =-Scenario_Analysis_4Cases!$B$5*MAX(0,(Scenario_Analysis_4Cases!$B$7*(1+Scenario_Analysis_4Cases!$D$5)^10-L30))*Assumptions!$B$4*Assumptions!$B$5 -> -81558.797 | M33: 0 | N33: 0 | O33: 0 | P33: 0 | Q33: =-Scenario_Analysis_4Cases!$B$5*MAX(0,(Scenario_Analysis_4Cases!$B$7*(1+Scenario_Analysis_4Cases!$D$5)^15-Q30))*Assumptions!$B$4*Assumptions!$B$5 -> -119939.92 | R33: 0 | S33: 0 | T33: 0 | U33: 0 | V33: =SUM(B33:U33) -> -282921.34 | W33: =NPV(Scenario_Analysis_4Cases!$B$6,B33:U33) -> -169458.52 | X33: =NPV(Scenario_Analysis_4Cases!$C$6,B33:U33) -> -154595.71 | Y33: =NPV(Scenario_Analysis_4Cases!$D$6,B33:U33) -> -141526.2 | Z33: =NPV(Scenario_Analysis_4Cases!$E$6,B33:U33) -> -130003.59
A34: Net Cash Flow (Tax + TIF + Fee) | B34: =B31+B32+B33 -> -148138.96 | C34: =C31+C32+C33 -> -121742.63 | D34: =D31+D32+D33 -> -124900.92 | E34: =E31+E32+E33 -> -128185.54 | F34: =F31+F32+F33 -> -131601.54 | G34: =G31+G32+G33 -> -180671.85 | H34: =H31+H32+H33 -> -132118.26 | I34: =I31+I32+I33 -> -135691.57 | ... U34: =U31+U32+U33 -> -1286323 | V34: =SUM(B34:U34) -> -10305815 | W34: =NPV(Scenario_Analysis_4Cases!$B$6,B34:U34) -> -5033118.5 | X34: =NPV(Scenario_Analysis_4Cases!$C$6,B34:U34) -> -4409882.4 | Y34: =NPV(Scenario_Analysis_4Cases!$D$6,B34:U34) -> -3878556 | Z34: =NPV(Scenario_Analysis_4Cases!$E$6,B34:U34) -> -3424366.3
A35: Note End Balance (info) | B35: =MAX(0,(Assumptions!$B$15)*(1+Assumptions!$B$13)-B32) -> 6962999.5 | C35: =MAX(0,(B35)*(1+Assumptions!$B$13)-C32) -> 6615467.5 | D35: =MAX(0,(C35)*(1+Assumptions!$B$13)-D32) -> 6223524.5 | E35: =MAX(0,(D35)*(1+Assumptions!$B$13)-E32) -> 5783990.5 | F35: =MAX(0,(E35)*(1+Assumptions!$B$13)-F32) -> 5293493.8 | G35: =MAX(0,(F35)*(1+Assumptions!$B$13)-G32) -> 4806706.9 | H35: =MAX(0,(G35)*(1+Assumptions!$B$13)-H32) -> 4266604.8 | I35: =MAX(0,(H35)*(1+Assumptions!$B$13)-I32) -> 3669498.1 | J35: =MAX(0,(I35)*(1+Assumptions!$B$13)-J32) -> 3011478.4 | ... U35: =MAX(0,(T35)*(1+Assumptions!$B$13)-U32) -> 0 | V35: — | W35: — | X35: — | Y35: — | Z35: —
A37: SCENARIO 4: MAA FLOOR — $43.835M start, 4% growth, 5-yr re-appeals BACK to MAA floor
A38: Component | B38: 2026 | C38: 2027 | D38: 2028 | E38: 2029 | F38: 2030 | G38: 2031 | H38: 2032 | I38: 2033 | J38: 2034 | K38: 2035 | L38: 2036 | M38: 2037 | N38: 2038 | O38: 2039 | P38: 2040 | Q38: 2041 | R38: 2042 | S38: 2043 | T38: 2044 | U38: 2045 | V38: Total | W38: NPV 5% | X38: NPV 6% | Y38: NPV 7% | Z38: NPV 8%
A39: Taxable Market Value (TMV) | B39: =Scenario_Analysis_4Cases!$E$7 -> 43835000 | C39: =B39*(1+Scenario_Analysis_4Cases!$D$5) -> 45588400 | D39: =C39*(1+Scenario_Analysis_4Cases!$D$5) -> 47411936 | E39: =D39*(1+Scenario_Analysis_4Cases!$D$5) -> 49308413 | F39: =E39*(1+Scenario_Analysis_4Cases!$D$5) -> 51280750 | G39: =Scenario_Analysis_4Cases!$E$7 -> 43835000 | H39: =G39*(1+Scenario_Analysis_4Cases!$D$5) -> 45588400 | I39: =H39*(1+Scenario_Analysis_4Cases!$D$5) -> 47411936 | J39: =I39*(1+Scenario_Analysis_4Cases!$D$5) -> 49308413 | K39: =J39*(1+Scenario_Analysis_4Cases!$D$5) -> 51280750 | L39: =Scenario_Analysis_4Cases!$E$7 -> 43835000 | M39: =L39*(1+Scenario_Analysis_4Cases!$D$5) -> 45588400 | N39: =M39*(1+Scenario_Analysis_4Cases!$D$5) -> 47411936 | O39: =N39*(1+Scenario_Analysis_4Cases!$D$5) -> 49308413 | P39: =O39*(1+Scenario_Analysis_4Cases!$D$5) -> 51280750 | Q39: =Scenario_Analysis_4Cases!$E$7 -> 43835000 | R39: =Q39*(1+Scenario_Analysis_4Cases!$D$5) -> 45588400 | S39: =R39*(1+Scenario_Analysis_4Cases!$D$5) -> 47411936 | T39: =S39*(1+Scenario_Analysis_4Cases!$D$5) -> 49308413 | U39: =T39*(1+Scenario_Analysis_4Cases!$D$5) -> 51280750 | V39: — | W39: — | X39: — | Y39: — | Z39: —
A40: Property Tax Paid (out) | B40: =-B39*Assumptions!$B$4*Assumptions!$B$5 -> -700625.76 | C40: =-C39*Assumptions!$B$4*Assumptions!$B$5 -> -728650.79 | D40: =-D39*Assumptions!$B$4*Assumptions!$B$5 -> -757796.83 | E40: =-E39*Assumptions!$B$4*Assumptions!$B$5 -> -788108.7 | F40: =-F39*Assumptions!$B$4*Assumptions!$B$5 -> -819633.05 | G40: =-G39*Assumptions!$B$4*Assumptions!$B$5 -> -700625.76 | H40: =-H39*Assumptions!$B$4*Assumptions!$B$5 -> -728650.79 | I40: =-I39*Assumptions!$B$4*Assumptions!$B$5 -> -757796.83 | ... U40: =-U39*Assumptions!$B$4*Assumptions!$B$5 -> -819633.05 | V40: =SUM(B40:U40) -> -15179261 | W40: =NPV(Scenario_Analysis_4Cases!$B$6,B40:U40) -> -9422243.7 | X40: =NPV(Scenario_Analysis_4Cases!$C$6,B40:U40) -> -8665573.7 | Y40: =NPV(Scenario_Analysis_4Cases!$D$6,B40:U40) -> -7997944.7 | Z40: =NPV(Scenario_Analysis_4Cases!$E$6,B40:U40) -> -7406818.2
A41: Net TIF Received (in) | B41: =MIN(MAX(0,B39*Assumptions!$B$4-Assumptions!$B$9)*Assumptions!$B$5*(1-Assumptions!$B$7),(Assumptions!$B$15)*(1+Assumptions!$B$13)) -> 587777.82 | C41: =MIN(MAX(0,C39*Assumptions!$B$4-Assumptions!$B$9)*Assumptions!$B$5*(1-Assumptions!$B$7),(B44)*(1+Assumptions!$B$13)) -> 613000.34 | D41: =MIN(MAX(0,D39*Assumptions!$B$4-Assumptions!$B$9)*Assumptions!$B$5*(1-Assumptions!$B$7),(C44)*(1+Assumptions!$B$13)) -> 639231.77 | E41: =MIN(MAX(0,E39*Assumptions!$B$4-Assumptions!$B$9)*Assumptions!$B$5*(1-Assumptions!$B$7),(D44)*(1+Assumptions!$B$13)) -> 666512.46 | F41: =MIN(MAX(0,F39*Assumptions!$B$4-Assumptions!$B$9)*Assumptions!$B$5*(1-Assumptions!$B$7),(E44)*(1+Assumptions!$B$13)) -> 694884.37 | G41: =MIN(MAX(0,G39*Assumptions!$B$4-Assumptions!$B$9)*Assumptions!$B$5*(1-Assumptions!$B$7),(F44)*(1+Assumptions!$B$13)) -> 587777.82 | H41: =MIN(MAX(0,H39*Assumptions!$B$4-Assumptions!$B$9)*Assumptions!$B$5*(1-Assumptions!$B$7),(G44)*(1+Assumptions!$B$13)) -> 613000.34 | I41: =MIN(MAX(0,I39*Assumptions!$B$4-Assumptions!$B$9)*Assumptions!$B$5*(1-Assumptions!$B$7),(H44)*(1+Assumptions!$B$13)) -> 639231.77 | J41: =MIN(MAX(0,J39*Assumptions!$B$4-Assumptions!$B$9)*Assumptions!$B$5*(1-Assumptions!$B$7),(I44)*(1+Assumptions!$B$13)) -> 666512.46 | ... U41: =MIN(MAX(0,U39*Assumptions!$B$4-Assumptions!$B$9)*Assumptions!$B$5*(1-Assumptions!$B$7),(T44)*(1+Assumptions!$B$13)) -> 0 | V41: =SUM(B41:U41) -> 10577016 | W41: =NPV(Scenario_Analysis_4Cases!$B$6,B41:U41) -> 7056080.6 | X41: =NPV(Scenario_Analysis_4Cases!$C$6,B41:U41) -> 6562696.6 | Y41: =NPV(Scenario_Analysis_4Cases!$D$6,B41:U41) -> 6119714.7 | Z41: =NPV(Scenario_Analysis_4Cases!$E$6,B41:U41) -> 5720954.3
A42: Attorney Fee Paid (out) | B42: =-Scenario_Analysis_4Cases!$B$5*MAX(0,(Scenario_Analysis_4Cases!$B$7*(1+Scenario_Analysis_4Cases!$D$5)^0-B39))*Assumptions!$B$4*Assumptions!$B$5 -> -44077.808 | C42: 0 | D42: 0 | E42: 0 | F42: 0 | G42: =-Scenario_Analysis_4Cases!$B$5*MAX(0,(Scenario_Analysis_4Cases!$B$7*(1+Scenario_Analysis_4Cases!$D$5)^5-G39))*Assumptions!$B$4*Assumptions!$B$5 -> -91575.544 | H42: 0 | I42: 0 | J42: 0 | K42: 0 | L42: =-Scenario_Analysis_4Cases!$B$5*MAX(0,(Scenario_Analysis_4Cases!$B$7*(1+Scenario_Analysis_4Cases!$D$5)^10-L39))*Assumptions!$B$4*Assumptions!$B$5 -> -149363.8 | M42: 0 | N42: 0 | O42: 0 | P42: 0 | Q42: =-Scenario_Analysis_4Cases!$B$5*MAX(0,(Scenario_Analysis_4Cases!$B$7*(1+Scenario_Analysis_4Cases!$D$5)^15-Q39))*Assumptions!$B$4*Assumptions!$B$5 -> -219672.06 | R42: 0 | S42: 0 | T42: 0 | U42: 0
A43: Net Cash Flow (Tax + TIF + Fee) | B43: =B40+B41+B42 -> -156925.75 | C43: =C40+C41+C42 -> -115650.45 | D43: =D40+D41+D42 -> -118565.05 | E43: =E40+E41+E42 -> -121596.24 | F43: =F40+F41+F42 -> -124748.67 | G43: =G40+G41+G42 -> -204423.49 | H43: =H40+H41+H42 -> -115650.45 | I43: =I40+I41+I42 -> -118565.05 | ... U43: =U40+U41+U42 -> -819633.05 | V43: =SUM(B43:U43) -> -5106934.1 | W43: =NPV(Scenario_Analysis_4Cases!$B$6,B43:U43) -> -2664441.2 | X43: =NPV(Scenario_Analysis_4Cases!$C$6,B43:U43) -> -2374173.1 | Y43: =NPV(Scenario_Analysis_4Cases!$D$6,B43:U43) -> -2125817.1 | Z43: =NPV(Scenario_Analysis_4Cases!$E$6,B43:U43) -> -1912564.5
A44: Note End Balance (info) | B44: =MAX(0,(Assumptions!$B$15)*(1+Assumptions!$B$13)-B41) -> 7015720.2 | C44: =MAX(0,(B44)*(1+Assumptions!$B$13)-C41) -> 6725443 | D44: =MAX(0,(C44)*(1+Assumptions!$B$13)-D41) -> 6395581.6 | E44: =MAX(0,(D44)*(1+Assumptions!$B$13)-E41) -> 6023265.9 | F44: =MAX(0,(E44)*(1+Assumptions!$B$13)-F41) -> 5605451.7 | G44: =MAX(0,(F44)*(1+Assumptions!$B$13)-G41) -> 5275524.7 | H44: =MAX(0,(G44)*(1+Assumptions!$B$13)-H41) -> 4905198.5 | I44: =MAX(0,(H44)*(1+Assumptions!$B$13)-I41) -> 4491605.9 | J44: =MAX(0,(I44)*(1+Assumptions!$B$13)-J41) -> 4031707.3 | ... U44: =MAX(0,(T44)*(1+Assumptions!$B$13)-U41) -> 0 | V44: — | W44: — | X44: — | Y44: — | Z44: —
A47: ★ HEADLINE — APPEAL BENEFIT vs. NO-APPEAL BASELINE (the answer — positive = appeal is better)
A48: Component | B48: 2026 | C48: 2027 | D48: 2028 | E48: 2029 | F48: 2030 | G48: 2031 | H48: 2032 | I48: 2033 | J48: 2034 | K48: 2035 | L48: 2036 | M48: 2037 | N48: 2038 | O48: 2039 | P48: 2040 | Q48: 2041 | R48: 2042 | S48: 2043 | T48: 2044 | U48: 2045 | V48: Total | W48: NPV 5% | X48: NPV 6% | Y48: NPV 7% | Z48: NPV 8%
A49: S2: Mid Appeal − Baseline | B49: =B25-B16 -> -11666.174 | C49: =C25-C16 -> 8088.5474 | D49: =D25-D16 -> 8412.0893 | E49: =E25-E16 -> 8748.5729 | F49: =F25-F16 -> 9098.5158 | G49: =G25-G16 -> -24412.339 | H49: =H25-H16 -> 16925.888 | I49: =I25-I16 -> 17602.924 | ... U49: =U25-U16 -> 493549.76 | V49: =SUM(B49:U49) -> 5170644.7 | W49: =NPV(Scenario_Analysis_4Cases!$B$6,B49:U49) -> 2540442.4 | X49: =NPV(Scenario_Analysis_4Cases!$C$6,B49:U49) -> 2218881.3 | Y49: =NPV(Scenario_Analysis_4Cases!$D$6,B49:U49) -> 1942139.3 | Z49: =NPV(Scenario_Analysis_4Cases!$E$6,B49:U49) -> 1703423.8
A50: S3: Aggressive − Baseline | B50: =B34-B16 -> -17659.893 | C50: =C34-C16 -> 12244.192 | D50: =D34-D16 -> 12733.96 | E50: =E34-E16 -> 13243.319 | F50: =F34-F16 -> 13773.051 | G50: =G34-G16 -> -31193.681 | H50: =H34-H16 -> 21627.619 | I50: =I34-I16 -> 22492.724 | ... U50: =U34-U16 -> 561250.97 | V50: =SUM(B50:U50) -> 6345730.6 | W50: =NPV(Scenario_Analysis_4Cases!$B$6,B50:U50) -> 3127907.2 | X50: =NPV(Scenario_Analysis_4Cases!$C$6,B50:U50) -> 2733175 | Y50: =NPV(Scenario_Analysis_4Cases!$D$6,B50:U50) -> 2393171.2 | Z50: =NPV(Scenario_Analysis_4Cases!$E$6,B50:U50) -> 2099656.9
A51: S4: MAA Floor − Baseline | B51: =B43-B16 -> -26446.685 | C51: =C43-C16 -> 18336.368 | D51: =D43-D16 -> 19069.823 | E51: =E43-E16 -> 19832.616 | F51: =F43-F16 -> 20625.92 | G51: =G43-G16 -> -54945.326 | H51: =H43-H16 -> 38095.426 | I51: =I43-I16 -> 39619.243 | ... U51: =U43-U16 -> 1027940.9 | V51: =SUM(B51:U51) -> 11544611 | W51: =NPV(Scenario_Analysis_4Cases!$B$6,B51:U51) -> 5496584.5 | X51: =NPV(Scenario_Analysis_4Cases!$C$6,B51:U51) -> 4768884.3 | Y51: =NPV(Scenario_Analysis_4Cases!$D$6,B51:U51) -> 4145910.2 | Z51: =NPV(Scenario_Analysis_4Cases!$E$6,B51:U51) -> 3611458.7
A52: KEY TAKEAWAYS: (1) The MAA Floor strategy delivers $11.5M nominal / $5.5M NPV@5% / $3.6M NPV@8% of value vs. no-appeal baseline. (2) Even Shaver's punitive 8% rate doesn't erase the benefit — every NPV column is strongly positive. (3) Attorney fees grow each appeal cycle (gap widens as baseline TMV grows): S4 total fees ~$505K = ~11x return on fees. (4) Note still pays off in all scenarios (latest 2042 under MAA Floor) before the 2045 last-increment date — zero risk of forgiven balance.

Sheet Note_Payoff_Breakeven
A1: TIF Note Payoff Breakeven Analysis
A2: What is the lowest 2026 TMV at which the TIF Note still fully pays off by the last TIF District increment (2045)? This identifies the floor beyond which the appeal would create an unpaid Note balance at maturity. Note that any unpaid balance is forgiven per Note §3 (limited revenue note) — so "not paid off" means foregone TIF, not a default.
A4: ASSUMPTIONS (linked to Assumptions tab)
A5: Note Starting Balance (2026) | B5: =Assumptions!$B$15 -> 7269118.6 | C5: Linked: starting balance entering 2026
A6: Note Interest Rate | B6: =Assumptions!$B$13 -> 0.046 | C6: Linked: 4.60%
A7: Original NTC (Base) | B7: =Assumptions!$B$9 -> 37179 | C7: Pre-development tax capacity ($37,179 per Ehlers reconciliation)
A8: Class Rate | B8: =Assumptions!$B$4 -> 0.0125 | C8: Linked: 1.25% for housing
A9: Tax Capacity Rate | B9: =Assumptions!$B$5 -> 1.27866 | C9: Linked: 1.28 (Ehlers uses 1.27866)
A10: Effective Dev Share (1 − Admin %) | B10: =1-Assumptions!$B$7 -> 0.9 | C10: Linked: 90% to developer
A11: TMV Annual Growth Rate | B11: 0 | C11: INPUT: 0% = worst case for payoff (your scenario)
A12: First Pay Year | B12: 2026 | C12: First year of analysis
A13: Last TIF Year (district decertification) | B13: 2045 | C13: 25-yr district, first increment 2020 → last 2045 per TIF Plan §2-7
A15: BREAKEVEN — Lowest 2026 TMV for Full Note Payoff
A16: Number of TIF years (LastYr − FirstYr + 1) | B16: =Note_Payoff_Breakeven!$B$13-Note_Payoff_Breakeven!$B$12+1 -> 20
A17: Required Annual TIF Payment (to retire Note) | B17: =PMT(Note_Payoff_Breakeven!$B$6,Note_Payoff_Breakeven!$B$16,-Note_Payoff_Breakeven!$B$5) -> 563674.52 | C17: Standard loan amortization formula at given rate/term
A18: Required Captured NTC | B18: =Note_Payoff_Breakeven!$B$17/Note_Payoff_Breakeven!$B$10/Note_Payoff_Breakeven!$B$9 -> 489813.58 | C18: Required PMT ÷ DevShare ÷ TaxCap
A19: BREAKEVEN 2026 TMV | B19: =(Note_Payoff_Breakeven!$B$18+Note_Payoff_Breakeven!$B$7)/Note_Payoff_Breakeven!$B$8 -> 42159406 | C19: (Captured NTC + Base NTC) ÷ Class Rate. ⚠ Valid for 0% growth assumption only.
A20: MAA Floor (contractual minimum TMV) | B20: =Assumptions!$B$18 -> 43835000
A21: Cushion (MAA above Breakeven) | B21: =Assumptions!$B$18-Note_Payoff_Breakeven!$B$19 -> 1675594 | C21: =(Assumptions!$B$18-Note_Payoff_Breakeven!$B$19)/Assumptions!$B$18 -> 0.038225025 | D21: ← % of MAA Floor
A23: SCENARIO TABLE — payoff year by 2026 TMV (at assumed growth rate)
A24: Scenario | B24: 2026 TMV | C24: Year-1 TIF to Dev | D24: Note Payoff Year | E24: End-2045 Bal
A25: Current 2025 baseline | B25: 54866000 | C25: =MAX(0,B25*Note_Payoff_Breakeven!$B$8-Note_Payoff_Breakeven!$B$7)*Note_Payoff_Breakeven!$B$9*Note_Payoff_Breakeven!$B$10 -> 746457.92 | D25: =IFERROR(INDEX($C$38:$V$38,MATCH(0,$C$39:$V$39,0)),"NOT PAID") -> 2039 | E25: =V39 -> 0
A26: County-set 2026 (no appeal) | B26: 52151000 | C26: =MAX(0,B26*Note_Payoff_Breakeven!$B$8-Note_Payoff_Breakeven!$B$7)*Note_Payoff_Breakeven!$B$9*Note_Payoff_Breakeven!$B$10 -> 707402.85 | D26: =IFERROR(INDEX($C$38:$V$38,MATCH(0,$C$40:$V$40,0)),"NOT PAID") -> 2040 | E26: =V40 -> 0
A27: Mid Appeal target | B27: 50000000 | C27: =MAX(0,B27*Note_Payoff_Breakeven!$B$8-Note_Payoff_Breakeven!$B$7)*Note_Payoff_Breakeven!$B$9*Note_Payoff_Breakeven!$B$10 -> 676460.88 | D27: =IFERROR(INDEX($C$38:$V$38,MATCH(0,$C$41:$V$41,0)),"NOT PAID") -> 2041 | E27: =V41 -> 0
A28: Aggressive Appeal | B28: 47500000 | C28: =MAX(0,B28*Note_Payoff_Breakeven!$B$8-Note_Payoff_Breakeven!$B$7)*Note_Payoff_Breakeven!$B$9*Note_Payoff_Breakeven!$B$10 -> 640498.57 | D28: =IFERROR(INDEX($C$38:$V$38,MATCH(0,$C$42:$V$42,0)),"NOT PAID") -> 2042 | E28: =V42 -> 0
A29: Deep Appeal | B29: 45000000 | C29: =MAX(0,B29*Note_Payoff_Breakeven!$B$8-Note_Payoff_Breakeven!$B$7)*Note_Payoff_Breakeven!$B$9*Note_Payoff_Breakeven!$B$10 -> 604536.25 | D29: =IFERROR(INDEX($C$38:$V$38,MATCH(0,$C$43:$V$43,0)),"NOT PAID") -> 2043 | E29: =V43 -> 0
A30: MAA Floor (contractual min) | B30: 43835000 | C30: =MAX(0,B30*Note_Payoff_Breakeven!$B$8-Note_Payoff_Breakeven!$B$7)*Note_Payoff_Breakeven!$B$9*Note_Payoff_Breakeven!$B$10 -> 587777.82 | D30: =IFERROR(INDEX($C$38:$V$38,MATCH(0,$C$44:$V$44,0)),"NOT PAID") -> 2044 | E30: =V44 -> 0
A31: 1M below MAA (hypothetical) | B31: 42835000 | C31: =MAX(0,B31*Note_Payoff_Breakeven!$B$8-Note_Payoff_Breakeven!$B$7)*Note_Payoff_Breakeven!$B$9*Note_Payoff_Breakeven!$B$10 -> 573392.89 | D31: =IFERROR(INDEX($C$38:$V$38,MATCH(0,$C$45:$V$45,0)),"NOT PAID") -> 2045 | E31: =V45 -> 0
A32: BREAKEVEN (calculated) | B32: =Note_Payoff_Breakeven!$B$19 -> 42159406 | C32: =MAX(0,B32*Note_Payoff_Breakeven!$B$8-Note_Payoff_Breakeven!$B$7)*Note_Payoff_Breakeven!$B$9*Note_Payoff_Breakeven!$B$10 -> 563674.52 | D32: =IFERROR(INDEX($C$38:$V$38,MATCH(0,$C$46:$V$46,0)),"NOT PAID") -> 2045 | E32: =V46 -> 0
A33: 500K below breakeven | B33: =Note_Payoff_Breakeven!$B$19-500000 -> 41659406 | C33: =MAX(0,B33*Note_Payoff_Breakeven!$B$8-Note_Payoff_Breakeven!$B$7)*Note_Payoff_Breakeven!$B$9*Note_Payoff_Breakeven!$B$10 -> 556482.06 | D33: =IFERROR(INDEX($C$38:$V$38,MATCH(0,$C$47:$V$47,0)),"NOT PAID") -> NOT PAID | E33: =V47 -> 228015.64
A34: 1M below breakeven | B34: =Note_Payoff_Breakeven!$B$19-1000000 -> 41159406 | C34: =MAX(0,B34*Note_Payoff_Breakeven!$B$8-Note_Payoff_Breakeven!$B$7)*Note_Payoff_Breakeven!$B$9*Note_Payoff_Breakeven!$B$10 -> 549289.6 | D34: =IFERROR(INDEX($C$38:$V$38,MATCH(0,$C$48:$V$48,0)),"NOT PAID") -> NOT PAID | E34: =V48 -> 456031.29
A37: DETAIL: Year-by-year balances (each row = one scenario, columns = 2026-2045)
A38: Scenario | B38: Annual TIF | C38: 2026 | D38: 2027 | E38: 2028 | F38: 2029 | G38: 2030 | H38: 2031 | I38: 2032 | J38: 2033 | K38: 2034 | L38: 2035 | M38: 2036 | N38: 2037 | O38: 2038 | P38: 2039 | Q38: 2040 | R38: 2041 | S38: 2042 | T38: 2043 | U38: 2044 | V38: 2045
A39: =A25 -> Current 2025 baseline | B39: =B25 -> 54866000 | C39: =MAX(0,Note_Payoff_Breakeven!$B$5+Note_Payoff_Breakeven!$B$5*Note_Payoff_Breakeven!$B$6-MAX(0,B39*POWER(1+Note_Payoff_Breakeven!$B$11,0)*Note_Payoff_Breakeven!$B$8-Note_Payoff_Breakeven!$B$7)*Note_Payoff_Breakeven!$B$9*Note_Payoff_Breakeven!$B$10) -> 6857040.1 | D39: =MAX(0,C39+C39*Note_Payoff_Breakeven!$B$6-MAX(0,B39*POWER(1+Note_Payoff_Breakeven!$B$11,1)*Note_Payoff_Breakeven!$B$8-Note_Payoff_Breakeven!$B$7)*Note_Payoff_Breakeven!$B$9*Note_Payoff_Breakeven!$B$10) -> 6426006 | E39: =MAX(0,D39+D39*Note_Payoff_Breakeven!$B$6-MAX(0,B39*POWER(1+Note_Payoff_Breakeven!$B$11,2)*Note_Payoff_Breakeven!$B$8-Note_Payoff_Breakeven!$B$7)*Note_Payoff_Breakeven!$B$9*Note_Payoff_Breakeven!$B$10) -> 5975144.4 | F39: =MAX(0,E39+E39*Note_Payoff_Breakeven!$B$6-MAX(0,B39*POWER(1+Note_Payoff_Breakeven!$B$11,3)*Note_Payoff_Breakeven!$B$8-Note_Payoff_Breakeven!$B$7)*Note_Payoff_Breakeven!$B$9*Note_Payoff_Breakeven!$B$10) -> 5503543.1 | G39: =MAX(0,F39+F39*Note_Payoff_Breakeven!$B$6-MAX(0,B39*POWER(1+Note_Payoff_Breakeven!$B$11,4)*Note_Payoff_Breakeven!$B$8-Note_Payoff_Breakeven!$B$7)*Note_Payoff_Breakeven!$B$9*Note_Payoff_Breakeven!$B$10) -> 5010248.1 | H39: =MAX(0,G39+G39*Note_Payoff_Breakeven!$B$6-MAX(0,B39*POWER(1+Note_Payoff_Breakeven!$B$11,5)*Note_Payoff_Breakeven!$B$8-Note_Payoff_Breakeven!$B$7)*Note_Payoff_Breakeven!$B$9*Note_Payoff_Breakeven!$B$10) -> 4494261.6 | I39: =MAX(0,H39+H39*Note_Payoff_Breakeven!$B$6-MAX(0,B39*POWER(1+Note_Payoff_Breakeven!$B$11,6)*Note_Payoff_Breakeven!$B$8-Note_Payoff_Breakeven!$B$7)*Note_Payoff_Breakeven!$B$9*Note_Payoff_Breakeven!$B$10) -> 3954539.7 | J39: =MAX(0,I39+I39*Note_Payoff_Breakeven!$B$6-MAX(0,B39*POWER(1+Note_Payoff_Breakeven!$B$11,7)*Note_Payoff_Breakeven!$B$8-Note_Payoff_Breakeven!$B$7)*Note_Payoff_Breakeven!$B$9*Note_Payoff_Breakeven!$B$10) -> 3389990.6 | K39: =MAX(0,J39+J39*Note_Payoff_Breakeven!$B$6-MAX(0,B39*POWER(1+Note_Payoff_Breakeven!$B$11,8)*Note_Payoff_Breakeven!$B$8-Note_Payoff_Breakeven!$B$7)*Note_Payoff_Breakeven!$B$9*Note_Payoff_Breakeven!$B$10) -> 2799472.3 | L39: =MAX(0,K39+K39*Note_Payoff_Breakeven!$B$6-MAX(0,B39*POWER(1+Note_Payoff_Breakeven!$B$11,9)*Note_Payoff_Breakeven!$B$8-Note_Payoff_Breakeven!$B$7)*Note_Payoff_Breakeven!$B$9*Note_Payoff_Breakeven!$B$10) -> 2181790.1 | M39: =MAX(0,L39+L39*Note_Payoff_Breakeven!$B$6-MAX(0,B39*POWER(1+Note_Payoff_Breakeven!$B$11,10)*Note_Payoff_Breakeven!$B$8-Note_Payoff_Breakeven!$B$7)*Note_Payoff_Breakeven!$B$9*Note_Payoff_Breakeven!$B$10) -> 1535694.5 | N39: =MAX(0,M39+M39*Note_Payoff_Breakeven!$B$6-MAX(0,B39*POWER(1+Note_Payoff_Breakeven!$B$11,11)*Note_Payoff_Breakeven!$B$8-Note_Payoff_Breakeven!$B$7)*Note_Payoff_Breakeven!$B$9*Note_Payoff_Breakeven!$B$10) -> 859878.53 | O39: =MAX(0,N39+N39*Note_Payoff_Breakeven!$B$6-MAX(0,B39*POWER(1+Note_Payoff_Breakeven!$B$11,12)*Note_Payoff_Breakeven!$B$8-Note_Payoff_Breakeven!$B$7)*Note_Payoff_Breakeven!$B$9*Note_Payoff_Breakeven!$B$10) -> 152975.02 | P39: =MAX(0,O39+O39*Note_Payoff_Breakeven!$B$6-MAX(0,B39*POWER(1+Note_Payoff_Breakeven!$B$11,13)*Note_Payoff_Breakeven!$B$8-Note_Payoff_Breakeven!$B$7)*Note_Payoff_Breakeven!$B$9*Note_Payoff_Breakeven!$B$10) -> 0 | Q39: =MAX(0,P39+P39*Note_Payoff_Breakeven!$B$6-MAX(0,B39*POWER(1+Note_Payoff_Breakeven!$B$11,14)*Note_Payoff_Breakeven!$B$8-Note_Payoff_Breakeven!$B$7)*Note_Payoff_Breakeven!$B$9*Note_Payoff_Breakeven!$B$10) -> 0 | R39: =MAX(0,Q39+Q39*Note_Payoff_Breakeven!$B$6-MAX(0,B39*POWER(1+Note_Payoff_Breakeven!$B$11,15)*Note_Payoff_Breakeven!$B$8-Note_Payoff_Breakeven!$B$7)*Note_Payoff_Breakeven!$B$9*Note_Payoff_Breakeven!$B$10) -> 0 | S39: =MAX(0,R39+R39*Note_Payoff_Breakeven!$B$6-MAX(0,B39*POWER(1+Note_Payoff_Breakeven!$B$11,16)*Note_Payoff_Breakeven!$B$8-Note_Payoff_Breakeven!$B$7)*Note_Payoff_Breakeven!$B$9*Note_Payoff_Breakeven!$B$10) -> 0 | T39: =MAX(0,S39+S39*Note_Payoff_Breakeven!$B$6-MAX(0,B39*POWER(1+Note_Payoff_Breakeven!$B$11,17)*Note_Payoff_Breakeven!$B$8-Note_Payoff_Breakeven!$B$7)*Note_Payoff_Breakeven!$B$9*Note_Payoff_Breakeven!$B$10) -> 0 | U39: =MAX(0,T39+T39*Note_Payoff_Breakeven!$B$6-MAX(0,B39*POWER(1+Note_Payoff_Breakeven!$B$11,18)*Note_Payoff_Breakeven!$B$8-Note_Payoff_Breakeven!$B$7)*Note_Payoff_Breakeven!$B$9*Note_Payoff_Breakeven!$B$10) -> 0 | V39: =MAX(0,U39+U39*Note_Payoff_Breakeven!$B$6-MAX(0,B39*POWER(1+Note_Payoff_Breakeven!$B$11,19)*Note_Payoff_Breakeven!$B$8-Note_Payoff_Breakeven!$B$7)*Note_Payoff_Breakeven!$B$9*Note_Payoff_Breakeven!$B$10) -> 0
A40: =A26 -> County-set 2026 (no appeal) | B40: =B26 -> 52151000 | C40: =MAX(0,Note_Payoff_Breakeven!$B$5+Note_Payoff_Breakeven!$B$5*Note_Payoff_Breakeven!$B$6-MAX(0,B40*POWER(1+Note_Payoff_Breakeven!$B$11,0)*Note_Payoff_Breakeven!$B$8-Note_Payoff_Breakeven!$B$7)*Note_Payoff_Breakeven!$B$9*Note_Payoff_Breakeven!$B$10) -> 6896095.2 | D40: =MAX(0,C40+C40*Note_Payoff_Breakeven!$B$6-MAX(0,B40*POWER(1+Note_Payoff_Breakeven!$B$11,1)*Note_Payoff_Breakeven!$B$8-Note_Payoff_Breakeven!$B$7)*Note_Payoff_Breakeven!$B$9*Note_Payoff_Breakeven!$B$10) -> 6505912.7 | E40: =MAX(0,D40+D40*Note_Payoff_Breakeven!$B$6-MAX(0,B40*POWER(1+Note_Payoff_Breakeven!$B$11,2)*Note_Payoff_Breakeven!$B$8-Note_Payoff_Breakeven!$B$7)*Note_Payoff_Breakeven!$B$9*Note_Payoff_Breakeven!$B$10) -> 6097781.8 | F40: =MAX(0,E40+E40*Note_Payoff_Breakeven!$B$6-MAX(0,B40*POWER(1+Note_Payoff_Breakeven!$B$11,3)*Note_Payoff_Breakeven!$B$8-Note_Payoff_Breakeven!$B$7)*Note_Payoff_Breakeven!$B$9*Note_Payoff_Breakeven!$B$10) -> 5670876.9 | G40: =MAX(0,F40+F40*Note_Payoff_Breakeven!$B$6-MAX(0,B40*POWER(1+Note_Payoff_Breakeven!$B$11,4)*Note_Payoff_Breakeven!$B$8-Note_Payoff_Breakeven!$B$7)*Note_Payoff_Breakeven!$B$9*Note_Payoff_Breakeven!$B$10) -> 5224334.4 | H40: =MAX(0,G40+G40*Note_Payoff_Breakeven!$B$6-MAX(0,B40*POWER(1+Note_Payoff_Breakeven!$B$11,5)*Note_Payoff_Breakeven!$B$8-Note_Payoff_Breakeven!$B$7)*Note_Payoff_Breakeven!$B$9*Note_Payoff_Breakeven!$B$10) -> 4757251 | I40: =MAX(0,H40+H40*Note_Payoff_Breakeven!$B$6-MAX(0,B40*POWER(1+Note_Payoff_Breakeven!$B$11,6)*Note_Payoff_Breakeven!$B$8-Note_Payoff_Breakeven!$B$7)*Note_Payoff_Breakeven!$B$9*Note_Payoff_Breakeven!$B$10) -> 4268681.6 | J40: =MAX(0,I40+I40*Note_Payoff_Breakeven!$B$6-MAX(0,B40*POWER(1+Note_Payoff_Breakeven!$B$11,7)*Note_Payoff_Breakeven!$B$8-Note_Payoff_Breakeven!$B$7)*Note_Payoff_Breakeven!$B$9*Note_Payoff_Breakeven!$B$10) -> 3757638.1 | K40: =MAX(0,J40+J40*Note_Payoff_Breakeven!$B$6-MAX(0,B40*POWER(1+Note_Payoff_Breakeven!$B$11,8)*Note_Payoff_Breakeven!$B$8-Note_Payoff_Breakeven!$B$7)*Note_Payoff_Breakeven!$B$9*Note_Payoff_Breakeven!$B$10) -> 3223086.6 | L40: =MAX(0,K40+K40*Note_Payoff_Breakeven!$B$6-MAX(0,B40*POWER(1+Note_Payoff_Breakeven!$B$11,9)*Note_Payoff_Breakeven!$B$8-Note_Payoff_Breakeven!$B$7)*Note_Payoff_Breakeven!$B$9*Note_Payoff_Breakeven!$B$10) -> 2663945.8 | M40: =MAX(0,L40+L40*Note_Payoff_Breakeven!$B$6-MAX(0,B40*POWER(1+Note_Payoff_Breakeven!$B$11,10)*Note_Payoff_Breakeven!$B$8-Note_Payoff_Breakeven!$B$7)*Note_Payoff_Breakeven!$B$9*Note_Payoff_Breakeven!$B$10) -> 2079084.4 | N40: =MAX(0,M40+M40*Note_Payoff_Breakeven!$B$6-MAX(0,B40*POWER(1+Note_Payoff_Breakeven!$B$11,11)*Note_Payoff_Breakeven!$B$8-Note_Payoff_Breakeven!$B$7)*Note_Payoff_Breakeven!$B$9*Note_Payoff_Breakeven!$B$10) -> 1467319.5 | O40: =MAX(0,N40+N40*Note_Payoff_Breakeven!$B$6-MAX(0,B40*POWER(1+Note_Payoff_Breakeven!$B$11,12)*Note_Payoff_Breakeven!$B$8-Note_Payoff_Breakeven!$B$7)*Note_Payoff_Breakeven!$B$9*Note_Payoff_Breakeven!$B$10) -> 827413.3 | P40: =MAX(0,O40+O40*Note_Payoff_Breakeven!$B$6-MAX(0,B40*POWER(1+Note_Payoff_Breakeven!$B$11,13)*Note_Payoff_Breakeven!$B$8-Note_Payoff_Breakeven!$B$7)*Note_Payoff_Breakeven!$B$9*Note_Payoff_Breakeven!$B$10) -> 158071.46 | Q40: =MAX(0,P40+P40*Note_Payoff_Breakeven!$B$6-MAX(0,B40*POWER(1+Note_Payoff_Breakeven!$B$11,14)*Note_Payoff_Breakeven!$B$8-Note_Payoff_Breakeven!$B$7)*Note_Payoff_Breakeven!$B$9*Note_Payoff_Breakeven!$B$10) -> 0 | R40: =MAX(0,Q40+Q40*Note_Payoff_Breakeven!$B$6-MAX(0,B40*POWER(1+Note_Payoff_Breakeven!$B$11,15)*Note_Payoff_Breakeven!$B$8-Note_Payoff_Breakeven!$B$7)*Note_Payoff_Breakeven!$B$9*Note_Payoff_Breakeven!$B$10) -> 0 | S40: =MAX(0,R40+R40*Note_Payoff_Breakeven!$B$6-MAX(0,B40*POWER(1+Note_Payoff_Breakeven!$B$11,16)*Note_Payoff_Breakeven!$B$8-Note_Payoff_Breakeven!$B$7)*Note_Payoff_Breakeven!$B$9*Note_Payoff_Breakeven!$B$10) -> 0 | T40: =MAX(0,S40+S40*Note_Payoff_Breakeven!$B$6-MAX(0,B40*POWER(1+Note_Payoff_Breakeven!$B$11,17)*Note_Payoff_Breakeven!$B$8-Note_Payoff_Breakeven!$B$7)*Note_Payoff_Breakeven!$B$9*Note_Payoff_Breakeven!$B$10) -> 0 | U40: =MAX(0,T40+T40*Note_Payoff_Breakeven!$B$6-MAX(0,B40*POWER(1+Note_Payoff_Breakeven!$B$11,18)*Note_Payoff_Breakeven!$B$8-Note_Payoff_Breakeven!$B$7)*Note_Payoff_Breakeven!$B$9*Note_Payoff_Breakeven!$B$10) -> 0 | V40: =MAX(0,U40+U40*Note_Payoff_Breakeven!$B$6-MAX(0,B40*POWER(1+Note_Payoff_Breakeven!$B$11,19)*Note_Payoff_Breakeven!$B$8-Note_Payoff_Breakeven!$B$7)*Note_Payoff_Breakeven!$B$9*Note_Payoff_Breakeven!$B$10) -> 0
A41: =A27 -> Mid Appeal target | B41: =B27 -> 50000000 | C41: =MAX(0,Note_Payoff_Breakeven!$B$5+Note_Payoff_Breakeven!$B$5*Note_Payoff_Breakeven!$B$6-MAX(0,B41*POWER(1+Note_Payoff_Breakeven!$B$11,0)*Note_Payoff_Breakeven!$B$8-Note_Payoff_Breakeven!$B$7)*Note_Payoff_Breakeven!$B$9*Note_Payoff_Breakeven!$B$10) -> 6927037.1 | D41: =MAX(0,C41+C41*Note_Payoff_Breakeven!$B$6-MAX(0,B41*POWER(1+Note_Payoff_Breakeven!$B$11,1)*Note_Payoff_Breakeven!$B$8-Note_Payoff_Breakeven!$B$7)*Note_Payoff_Breakeven!$B$9*Note_Payoff_Breakeven!$B$10) -> 6569220 | E41: =MAX(0,D41+D41*Note_Payoff_Breakeven!$B$6-MAX(0,B41*POWER(1+Note_Payoff_Breakeven!$B$11,2)*Note_Payoff_Breakeven!$B$8-Note_Payoff_Breakeven!$B$7)*Note_Payoff_Breakeven!$B$9*Note_Payoff_Breakeven!$B$10) -> 6194943.2 | F41: =MAX(0,E41+E41*Note_Payoff_Breakeven!$B$6-MAX(0,B41*POWER(1+Note_Payoff_Breakeven!$B$11,3)*Note_Payoff_Breakeven!$B$8-Note_Payoff_Breakeven!$B$7)*Note_Payoff_Breakeven!$B$9*Note_Payoff_Breakeven!$B$10) -> 5803449.7 | G41: =MAX(0,F41+F41*Note_Payoff_Breakeven!$B$6-MAX(0,B41*POWER(1+Note_Payoff_Breakeven!$B$11,4)*Note_Payoff_Breakeven!$B$8-Note_Payoff_Breakeven!$B$7)*Note_Payoff_Breakeven!$B$9*Note_Payoff_Breakeven!$B$10) -> 5393947.5 | H41: =MAX(0,G41+G41*Note_Payoff_Breakeven!$B$6-MAX(0,B41*POWER(1+Note_Payoff_Breakeven!$B$11,5)*Note_Payoff_Breakeven!$B$8-Note_Payoff_Breakeven!$B$7)*Note_Payoff_Breakeven!$B$9*Note_Payoff_Breakeven!$B$10) -> 4965608.2 | I41: =MAX(0,H41+H41*Note_Payoff_Breakeven!$B$6-MAX(0,B41*POWER(1+Note_Payoff_Breakeven!$B$11,6)*Note_Payoff_Breakeven!$B$8-Note_Payoff_Breakeven!$B$7)*Note_Payoff_Breakeven!$B$9*Note_Payoff_Breakeven!$B$10) -> 4517565.3 | J41: =MAX(0,I41+I41*Note_Payoff_Breakeven!$B$6-MAX(0,B41*POWER(1+Note_Payoff_Breakeven!$B$11,7)*Note_Payoff_Breakeven!$B$8-Note_Payoff_Breakeven!$B$7)*Note_Payoff_Breakeven!$B$9*Note_Payoff_Breakeven!$B$10) -> 4048912.5 | K41: =MAX(0,J41+J41*Note_Payoff_Breakeven!$B$6-MAX(0,B41*POWER(1+Note_Payoff_Breakeven!$B$11,8)*Note_Payoff_Breakeven!$B$8-Note_Payoff_Breakeven!$B$7)*Note_Payoff_Breakeven!$B$9*Note_Payoff_Breakeven!$B$10) -> 3558701.6 | L41: =MAX(0,K41+K41*Note_Payoff_Breakeven!$B$6-MAX(0,B41*POWER(1+Note_Payoff_Breakeven!$B$11,9)*Note_Payoff_Breakeven!$B$8-Note_Payoff_Breakeven!$B$7)*Note_Payoff_Breakeven!$B$9*Note_Payoff_Breakeven!$B$10) -> 3045940.9 | M41: =MAX(0,L41+L41*Note_Payoff_Breakeven!$B$6-MAX(0,B41*POWER(1+Note_Payoff_Breakeven!$B$11,10)*Note_Payoff_Breakeven!$B$8-Note_Payoff_Breakeven!$B$7)*Note_Payoff_Breakeven!$B$9*Note_Payoff_Breakeven!$B$10) -> 2509593.3 | N41: =MAX(0,M41+M41*Note_Payoff_Breakeven!$B$6-MAX(0,B41*POWER(1+Note_Payoff_Breakeven!$B$11,11)*Note_Payoff_Breakeven!$B$8-Note_Payoff_Breakeven!$B$7)*Note_Payoff_Breakeven!$B$9*Note_Payoff_Breakeven!$B$10) -> 1948573.8 | O41: =MAX(0,N41+N41*Note_Payoff_Breakeven!$B$6-MAX(0,B41*POWER(1+Note_Payoff_Breakeven!$B$11,12)*Note_Payoff_Breakeven!$B$8-Note_Payoff_Breakeven!$B$7)*Note_Payoff_Breakeven!$B$9*Note_Payoff_Breakeven!$B$10) -> 1361747.3 | P41: =MAX(0,O41+O41*Note_Payoff_Breakeven!$B$6-MAX(0,B41*POWER(1+Note_Payoff_Breakeven!$B$11,13)*Note_Payoff_Breakeven!$B$8-Note_Payoff_Breakeven!$B$7)*Note_Payoff_Breakeven!$B$9*Note_Payoff_Breakeven!$B$10) -> 747926.77 | Q41: =MAX(0,P41+P41*Note_Payoff_Breakeven!$B$6-MAX(0,B41*POWER(1+Note_Payoff_Breakeven!$B$11,14)*Note_Payoff_Breakeven!$B$8-Note_Payoff_Breakeven!$B$7)*Note_Payoff_Breakeven!$B$9*Note_Payoff_Breakeven!$B$10) -> 105870.52 | R41: =MAX(0,Q41+Q41*Note_Payoff_Breakeven!$B$6-MAX(0,B41*POWER(1+Note_Payoff_Breakeven!$B$11,15)*Note_Payoff_Breakeven!$B$8-Note_Payoff_Breakeven!$B$7)*Note_Payoff_Breakeven!$B$9*Note_Payoff_Breakeven!$B$10) -> 0 | S41: =MAX(0,R41+R41*Note_Payoff_Breakeven!$B$6-MAX(0,B41*POWER(1+Note_Payoff_Breakeven!$B$11,16)*Note_Payoff_Breakeven!$B$8-Note_Payoff_Breakeven!$B$7)*Note_Payoff_Breakeven!$B$9*Note_Payoff_Breakeven!$B$10) -> 0 | T41: =MAX(0,S41+S41*Note_Payoff_Breakeven!$B$6-MAX(0,B41*POWER(1+Note_Payoff_Breakeven!$B$11,17)*Note_Payoff_Breakeven!$B$8-Note_Payoff_Breakeven!$B$7)*Note_Payoff_Breakeven!$B$9*Note_Payoff_Breakeven!$B$10) -> 0 | U41: =MAX(0,T41+T41*Note_Payoff_Breakeven!$B$6-MAX(0,B41*POWER(1+Note_Payoff_Breakeven!$B$11,18)*Note_Payoff_Breakeven!$B$8-Note_Payoff_Breakeven!$B$7)*Note_Payoff_Breakeven!$B$9*Note_Payoff_Breakeven!$B$10) -> 0 | V41: =MAX(0,U41+U41*Note_Payoff_Breakeven!$B$6-MAX(0,B41*POWER(1+Note_Payoff_Breakeven!$B$11,19)*Note_Payoff_Breakeven!$B$8-Note_Payoff_Breakeven!$B$7)*Note_Payoff_Breakeven!$B$9*Note_Payoff_Breakeven!$B$10) -> 0
A42: =A28 -> Aggressive Appeal | B42: =B28 -> 47500000 | C42: =MAX(0,Note_Payoff_Breakeven!$B$5+Note_Payoff_Breakeven!$B$5*Note_Payoff_Breakeven!$B$6-MAX(0,B42*POWER(1+Note_Payoff_Breakeven!$B$11,0)*Note_Payoff_Breakeven!$B$8-Note_Payoff_Breakeven!$B$7)*Note_Payoff_Breakeven!$B$9*Note_Payoff_Breakeven!$B$10) -> 6962999.5 | D42: =MAX(0,C42+C42*Note_Payoff_Breakeven!$B$6-MAX(0,B42*POWER(1+Note_Payoff_Breakeven!$B$11,1)*Note_Payoff_Breakeven!$B$8-Note_Payoff_Breakeven!$B$7)*Note_Payoff_Breakeven!$B$9*Note_Payoff_Breakeven!$B$10) -> 6642798.9 | E42: =MAX(0,D42+D42*Note_Payoff_Breakeven!$B$6-MAX(0,B42*POWER(1+Note_Payoff_Breakeven!$B$11,2)*Note_Payoff_Breakeven!$B$8-Note_Payoff_Breakeven!$B$7)*Note_Payoff_Breakeven!$B$9*Note_Payoff_Breakeven!$B$10) -> 6307869 | F42: =MAX(0,E42+E42*Note_Payoff_Breakeven!$B$6-MAX(0,B42*POWER(1+Note_Payoff_Breakeven!$B$11,3)*Note_Payoff_Breakeven!$B$8-Note_Payoff_Breakeven!$B$7)*Note_Payoff_Breakeven!$B$9*Note_Payoff_Breakeven!$B$10) -> 5957532.5 | G42: =MAX(0,F42+F42*Note_Payoff_Breakeven!$B$6-MAX(0,B42*POWER(1+Note_Payoff_Breakeven!$B$11,4)*Note_Payoff_Breakeven!$B$8-Note_Payoff_Breakeven!$B$7)*Note_Payoff_Breakeven!$B$9*Note_Payoff_Breakeven!$B$10) -> 5591080.4 | H42: =MAX(0,G42+G42*Note_Payoff_Breakeven!$B$6-MAX(0,B42*POWER(1+Note_Payoff_Breakeven!$B$11,5)*Note_Payoff_Breakeven!$B$8-Note_Payoff_Breakeven!$B$7)*Note_Payoff_Breakeven!$B$9*Note_Payoff_Breakeven!$B$10) -> 5207771.5 | I42: =MAX(0,H42+H42*Note_Payoff_Breakeven!$B$6-MAX(0,B42*POWER(1+Note_Payoff_Breakeven!$B$11,6)*Note_Payoff_Breakeven!$B$8-Note_Payoff_Breakeven!$B$7)*Note_Payoff_Breakeven!$B$9*Note_Payoff_Breakeven!$B$10) -> 4806830.4 | J42: =MAX(0,I42+I42*Note_Payoff_Breakeven!$B$6-MAX(0,B42*POWER(1+Note_Payoff_Breakeven!$B$11,7)*Note_Payoff_Breakeven!$B$8-Note_Payoff_Breakeven!$B$7)*Note_Payoff_Breakeven!$B$9*Note_Payoff_Breakeven!$B$10) -> 4387446.1 | K42: =MAX(0,J42+J42*Note_Payoff_Breakeven!$B$6-MAX(0,B42*POWER(1+Note_Payoff_Breakeven!$B$11,8)*Note_Payoff_Breakeven!$B$8-Note_Payoff_Breakeven!$B$7)*Note_Payoff_Breakeven!$B$9*Note_Payoff_Breakeven!$B$10) -> 3948770 | L42: =MAX(0,K42+K42*Note_Payoff_Breakeven!$B$6-MAX(0,B42*POWER(1+Note_Payoff_Breakeven!$B$11,9)*Note_Payoff_Breakeven!$B$8-Note_Payoff_Breakeven!$B$7)*Note_Payoff_Breakeven!$B$9*Note_Payoff_Breakeven!$B$10) -> 3489914.9 | M42: =MAX(0,L42+L42*Note_Payoff_Breakeven!$B$6-MAX(0,B42*POWER(1+Note_Payoff_Breakeven!$B$11,10)*Note_Payoff_Breakeven!$B$8-Note_Payoff_Breakeven!$B$7)*Note_Payoff_Breakeven!$B$9*Note_Payoff_Breakeven!$B$10) -> 3009952.4 | N42: =MAX(0,M42+M42*Note_Payoff_Breakeven!$B$6-MAX(0,B42*POWER(1+Note_Payoff_Breakeven!$B$11,11)*Note_Payoff_Breakeven!$B$8-Note_Payoff_Breakeven!$B$7)*Note_Payoff_Breakeven!$B$9*Note_Payoff_Breakeven!$B$10) -> 2507911.6 | O42: =MAX(0,N42+N42*Note_Payoff_Breakeven!$B$6-MAX(0,B42*POWER(1+Note_Payoff_Breakeven!$B$11,12)*Note_Payoff_Breakeven!$B$8-Note_Payoff_Breakeven!$B$7)*Note_Payoff_Breakeven!$B$9*Note_Payoff_Breakeven!$B$10) -> 1982777 | P42: =MAX(0,O42+O42*Note_Payoff_Breakeven!$B$6-MAX(0,B42*POWER(1+Note_Payoff_Breakeven!$B$11,13)*Note_Payoff_Breakeven!$B$8-Note_Payoff_Breakeven!$B$7)*Note_Payoff_Breakeven!$B$9*Note_Payoff_Breakeven!$B$10) -> 1433486.2 | Q42: =MAX(0,P42+P42*Note_Payoff_Breakeven!$B$6-MAX(0,B42*POWER(1+Note_Payoff_Breakeven!$B$11,14)*Note_Payoff_Breakeven!$B$8-Note_Payoff_Breakeven!$B$7)*Note_Payoff_Breakeven!$B$9*Note_Payoff_Breakeven!$B$10) -> 858927.97 | R42: =MAX(0,Q42+Q42*Note_Payoff_Breakeven!$B$6-MAX(0,B42*POWER(1+Note_Payoff_Breakeven!$B$11,15)*Note_Payoff_Breakeven!$B$8-Note_Payoff_Breakeven!$B$7)*Note_Payoff_Breakeven!$B$9*Note_Payoff_Breakeven!$B$10) -> 257940.08 | S42: =MAX(0,R42+R42*Note_Payoff_Breakeven!$B$6-MAX(0,B42*POWER(1+Note_Payoff_Breakeven!$B$11,16)*Note_Payoff_Breakeven!$B$8-Note_Payoff_Breakeven!$B$7)*Note_Payoff_Breakeven!$B$9*Note_Payoff_Breakeven!$B$10) -> 0 | T42: =MAX(0,S42+S42*Note_Payoff_Breakeven!$B$6-MAX(0,B42*POWER(1+Note_Payoff_Breakeven!$B$11,17)*Note_Payoff_Breakeven!$B$8-Note_Payoff_Breakeven!$B$7)*Note_Payoff_Breakeven!$B$9*Note_Payoff_Breakeven!$B$10) -> 0 | U42: =MAX(0,T42+T42*Note_Payoff_Breakeven!$B$6-MAX(0,B42*POWER(1+Note_Payoff_Breakeven!$B$11,18)*Note_Payoff_Breakeven!$B$8-Note_Payoff_Breakeven!$B$7)*Note_Payoff_Breakeven!$B$9*Note_Payoff_Breakeven!$B$10) -> 0 | V42: =MAX(0,U42+U42*Note_Payoff_Breakeven!$B$6-MAX(0,B42*POWER(1+Note_Payoff_Breakeven!$B$11,19)*Note_Payoff_Breakeven!$B$8-Note_Payoff_Breakeven!$B$7)*Note_Payoff_Breakeven!$B$9*Note_Payoff_Breakeven!$B$10) -> 0
A43: =A29 -> Deep Appeal | B43: =B29 -> 45000000 | C43: =MAX(0,Note_Payoff_Breakeven!$B$5+Note_Payoff_Breakeven!$B$5*Note_Payoff_Breakeven!$B$6-MAX(0,B43*POWER(1+Note_Payoff_Breakeven!$B$11,0)*Note_Payoff_Breakeven!$B$8-Note_Payoff_Breakeven!$B$7)*Note_Payoff_Breakeven!$B$9*Note_Payoff_Breakeven!$B$10) -> 6998961.8 | D43: =MAX(0,C43+C43*Note_Payoff_Breakeven!$B$6-MAX(0,B43*POWER(1+Note_Payoff_Breakeven!$B$11,1)*Note_Payoff_Breakeven!$B$8-Note_Payoff_Breakeven!$B$7)*Note_Payoff_Breakeven!$B$9*Note_Payoff_Breakeven!$B$10) -> 6716377.8 | E43: =MAX(0,D43+D43*Note_Payoff_Breakeven!$B$6-MAX(0,B43*POWER(1+Note_Payoff_Breakeven!$B$11,2)*Note_Payoff_Breakeven!$B$8-Note_Payoff_Breakeven!$B$7)*Note_Payoff_Breakeven!$B$9*Note_Payoff_Breakeven!$B$10) -> 6420794.9 | F43: =MAX(0,E43+E43*Note_Payoff_Breakeven!$B$6-MAX(0,B43*POWER(1+Note_Payoff_Breakeven!$B$11,3)*Note_Payoff_Breakeven!$B$8-Note_Payoff_Breakeven!$B$7)*Note_Payoff_Breakeven!$B$9*Note_Payoff_Breakeven!$B$10) -> 6111615.2 | G43: =MAX(0,F43+F43*Note_Payoff_Breakeven!$B$6-MAX(0,B43*POWER(1+Note_Payoff_Breakeven!$B$11,4)*Note_Payoff_Breakeven!$B$8-Note_Payoff_Breakeven!$B$7)*Note_Payoff_Breakeven!$B$9*Note_Payoff_Breakeven!$B$10) -> 5788213.2 | H43: =MAX(0,G43+G43*Note_Payoff_Breakeven!$B$6-MAX(0,B43*POWER(1+Note_Payoff_Breakeven!$B$11,5)*Note_Payoff_Breakeven!$B$8-Note_Payoff_Breakeven!$B$7)*Note_Payoff_Breakeven!$B$9*Note_Payoff_Breakeven!$B$10) -> 5449934.8 | I43: =MAX(0,H43+H43*Note_Payoff_Breakeven!$B$6-MAX(0,B43*POWER(1+Note_Payoff_Breakeven!$B$11,6)*Note_Payoff_Breakeven!$B$8-Note_Payoff_Breakeven!$B$7)*Note_Payoff_Breakeven!$B$9*Note_Payoff_Breakeven!$B$10) -> 5096095.5 | J43: =MAX(0,I43+I43*Note_Payoff_Breakeven!$B$6-MAX(0,B43*POWER(1+Note_Payoff_Breakeven!$B$11,7)*Note_Payoff_Breakeven!$B$8-Note_Payoff_Breakeven!$B$7)*Note_Payoff_Breakeven!$B$9*Note_Payoff_Breakeven!$B$10) -> 4725979.7 | K43: =MAX(0,J43+J43*Note_Payoff_Breakeven!$B$6-MAX(0,B43*POWER(1+Note_Payoff_Breakeven!$B$11,8)*Note_Payoff_Breakeven!$B$8-Note_Payoff_Breakeven!$B$7)*Note_Payoff_Breakeven!$B$9*Note_Payoff_Breakeven!$B$10) -> 4338838.5 | L43: =MAX(0,K43+K43*Note_Payoff_Breakeven!$B$6-MAX(0,B43*POWER(1+Note_Payoff_Breakeven!$B$11,9)*Note_Payoff_Breakeven!$B$8-Note_Payoff_Breakeven!$B$7)*Note_Payoff_Breakeven!$B$9*Note_Payoff_Breakeven!$B$10) -> 3933888.8 | M43: =MAX(0,L43+L43*Note_Payoff_Breakeven!$B$6-MAX(0,B43*POWER(1+Note_Payoff_Breakeven!$B$11,10)*Note_Payoff_Breakeven!$B$8-Note_Payoff_Breakeven!$B$7)*Note_Payoff_Breakeven!$B$9*Note_Payoff_Breakeven!$B$10) -> 3510311.4 | N43: =MAX(0,M43+M43*Note_Payoff_Breakeven!$B$6-MAX(0,B43*POWER(1+Note_Payoff_Breakeven!$B$11,11)*Note_Payoff_Breakeven!$B$8-Note_Payoff_Breakeven!$B$7)*Note_Payoff_Breakeven!$B$9*Note_Payoff_Breakeven!$B$10) -> 3067249.5 | O43: =MAX(0,N43+N43*Note_Payoff_Breakeven!$B$6-MAX(0,B43*POWER(1+Note_Payoff_Breakeven!$B$11,12)*Note_Payoff_Breakeven!$B$8-Note_Payoff_Breakeven!$B$7)*Note_Payoff_Breakeven!$B$9*Note_Payoff_Breakeven!$B$10) -> 2603806.7 | P43: =MAX(0,O43+O43*Note_Payoff_Breakeven!$B$6-MAX(0,B43*POWER(1+Note_Payoff_Breakeven!$B$11,13)*Note_Payoff_Breakeven!$B$8-Note_Payoff_Breakeven!$B$7)*Note_Payoff_Breakeven!$B$9*Note_Payoff_Breakeven!$B$10) -> 2119045.6 | Q43: =MAX(0,P43+P43*Note_Payoff_Breakeven!$B$6-MAX(0,B43*POWER(1+Note_Payoff_Breakeven!$B$11,14)*Note_Payoff_Breakeven!$B$8-Note_Payoff_Breakeven!$B$7)*Note_Payoff_Breakeven!$B$9*Note_Payoff_Breakeven!$B$10) -> 1611985.4 | R43: =MAX(0,Q43+Q43*Note_Payoff_Breakeven!$B$6-MAX(0,B43*POWER(1+Note_Payoff_Breakeven!$B$11,15)*Note_Payoff_Breakeven!$B$8-Note_Payoff_Breakeven!$B$7)*Note_Payoff_Breakeven!$B$9*Note_Payoff_Breakeven!$B$10) -> 1081600.5 | S43: =MAX(0,R43+R43*Note_Payoff_Breakeven!$B$6-MAX(0,B43*POWER(1+Note_Payoff_Breakeven!$B$11,16)*Note_Payoff_Breakeven!$B$8-Note_Payoff_Breakeven!$B$7)*Note_Payoff_Breakeven!$B$9*Note_Payoff_Breakeven!$B$10) -> 526817.85 | T43: =MAX(0,S43+S43*Note_Payoff_Breakeven!$B$6-MAX(0,B43*POWER(1+Note_Payoff_Breakeven!$B$11,17)*Note_Payoff_Breakeven!$B$8-Note_Payoff_Breakeven!$B$7)*Note_Payoff_Breakeven!$B$9*Note_Payoff_Breakeven!$B$10) -> 0 | U43: =MAX(0,T43+T43*Note_Payoff_Breakeven!$B$6-MAX(0,B43*POWER(1+Note_Payoff_Breakeven!$B$11,18)*Note_Payoff_Breakeven!$B$8-Note_Payoff_Breakeven!$B$7)*Note_Payoff_Breakeven!$B$9*Note_Payoff_Breakeven!$B$10) -> 0 | V43: =MAX(0,U43+U43*Note_Payoff_Breakeven!$B$6-MAX(0,B43*POWER(1+Note_Payoff_Breakeven!$B$11,19)*Note_Payoff_Breakeven!$B$8-Note_Payoff_Breakeven!$B$7)*Note_Payoff_Breakeven!$B$9*Note_Payoff_Breakeven!$B$10) -> 0
A44: =A30 -> MAA Floor (contractual min) | B44: =B30 -> 43835000 | C44: =MAX(0,Note_Payoff_Breakeven!$B$5+Note_Payoff_Breakeven!$B$5*Note_Payoff_Breakeven!$B$6-MAX(0,B44*POWER(1+Note_Payoff_Breakeven!$B$11,0)*Note_Payoff_Breakeven!$B$8-Note_Payoff_Breakeven!$B$7)*Note_Payoff_Breakeven!$B$9*Note_Payoff_Breakeven!$B$10) -> 7015720.2 | D44: =MAX(0,C44+C44*Note_Payoff_Breakeven!$B$6-MAX(0,B44*POWER(1+Note_Payoff_Breakeven!$B$11,1)*Note_Payoff_Breakeven!$B$8-Note_Payoff_Breakeven!$B$7)*Note_Payoff_Breakeven!$B$9*Note_Payoff_Breakeven!$B$10) -> 6750665.5 | E44: =MAX(0,D44+D44*Note_Payoff_Breakeven!$B$6-MAX(0,B44*POWER(1+Note_Payoff_Breakeven!$B$11,2)*Note_Payoff_Breakeven!$B$8-Note_Payoff_Breakeven!$B$7)*Note_Payoff_Breakeven!$B$9*Note_Payoff_Breakeven!$B$10) -> 6473418.3 | F44: =MAX(0,E44+E44*Note_Payoff_Breakeven!$B$6-MAX(0,B44*POWER(1+Note_Payoff_Breakeven!$B$11,3)*Note_Payoff_Breakeven!$B$8-Note_Payoff_Breakeven!$B$7)*Note_Payoff_Breakeven!$B$9*Note_Payoff_Breakeven!$B$10) -> 6183417.7 | G44: =MAX(0,F44+F44*Note_Payoff_Breakeven!$B$6-MAX(0,B44*POWER(1+Note_Payoff_Breakeven!$B$11,4)*Note_Payoff_Breakeven!$B$8-Note_Payoff_Breakeven!$B$7)*Note_Payoff_Breakeven!$B$9*Note_Payoff_Breakeven!$B$10) -> 5880077.1 | H44: =MAX(0,G44+G44*Note_Payoff_Breakeven!$B$6-MAX(0,B44*POWER(1+Note_Payoff_Breakeven!$B$11,5)*Note_Payoff_Breakeven!$B$8-Note_Payoff_Breakeven!$B$7)*Note_Payoff_Breakeven!$B$9*Note_Payoff_Breakeven!$B$10) -> 5562782.9 | I44: =MAX(0,H44+H44*Note_Payoff_Breakeven!$B$6-MAX(0,B44*POWER(1+Note_Payoff_Breakeven!$B$11,6)*Note_Payoff_Breakeven!$B$8-Note_Payoff_Breakeven!$B$7)*Note_Payoff_Breakeven!$B$9*Note_Payoff_Breakeven!$B$10) -> 5230893.1 | J44: =MAX(0,I44+I44*Note_Payoff_Breakeven!$B$6-MAX(0,B44*POWER(1+Note_Payoff_Breakeven!$B$11,7)*Note_Payoff_Breakeven!$B$8-Note_Payoff_Breakeven!$B$7)*Note_Payoff_Breakeven!$B$9*Note_Payoff_Breakeven!$B$10) -> 4883736.3 | K44: =MAX(0,J44+J44*Note_Payoff_Breakeven!$B$6-MAX(0,B44*POWER(1+Note_Payoff_Breakeven!$B$11,8)*Note_Payoff_Breakeven!$B$8-Note_Payoff_Breakeven!$B$7)*Note_Payoff_Breakeven!$B$9*Note_Payoff_Breakeven!$B$10) -> 4520610.4 | L44: =MAX(0,K44+K44*Note_Payoff_Breakeven!$B$6-MAX(0,B44*POWER(1+Note_Payoff_Breakeven!$B$11,9)*Note_Payoff_Breakeven!$B$8-Note_Payoff_Breakeven!$B$7)*Note_Payoff_Breakeven!$B$9*Note_Payoff_Breakeven!$B$10) -> 4140780.6 | M44: =MAX(0,L44+L44*Note_Payoff_Breakeven!$B$6-MAX(0,B44*POWER(1+Note_Payoff_Breakeven!$B$11,10)*Note_Payoff_Breakeven!$B$8-Note_Payoff_Breakeven!$B$7)*Note_Payoff_Breakeven!$B$9*Note_Payoff_Breakeven!$B$10) -> 3743478.7 | N44: =MAX(0,M44+M44*Note_Payoff_Breakeven!$B$6-MAX(0,B44*POWER(1+Note_Payoff_Breakeven!$B$11,11)*Note_Payoff_Breakeven!$B$8-Note_Payoff_Breakeven!$B$7)*Note_Payoff_Breakeven!$B$9*Note_Payoff_Breakeven!$B$10) -> 3327900.9 | O44: =MAX(0,N44+N44*Note_Payoff_Breakeven!$B$6-MAX(0,B44*POWER(1+Note_Payoff_Breakeven!$B$11,12)*Note_Payoff_Breakeven!$B$8-Note_Payoff_Breakeven!$B$7)*Note_Payoff_Breakeven!$B$9*Note_Payoff_Breakeven!$B$10) -> 2893206.6 | P44: =MAX(0,O44+O44*Note_Payoff_Breakeven!$B$6-MAX(0,B44*POWER(1+Note_Payoff_Breakeven!$B$11,13)*Note_Payoff_Breakeven!$B$8-Note_Payoff_Breakeven!$B$7)*Note_Payoff_Breakeven!$B$9*Note_Payoff_Breakeven!$B$10) -> 2438516.3 | Q44: =MAX(0,P44+P44*Note_Payoff_Breakeven!$B$6-MAX(0,B44*POWER(1+Note_Payoff_Breakeven!$B$11,14)*Note_Payoff_Breakeven!$B$8-Note_Payoff_Breakeven!$B$7)*Note_Payoff_Breakeven!$B$9*Note_Payoff_Breakeven!$B$10) -> 1962910.2 | R44: =MAX(0,Q44+Q44*Note_Payoff_Breakeven!$B$6-MAX(0,B44*POWER(1+Note_Payoff_Breakeven!$B$11,15)*Note_Payoff_Breakeven!$B$8-Note_Payoff_Breakeven!$B$7)*Note_Payoff_Breakeven!$B$9*Note_Payoff_Breakeven!$B$10) -> 1465426.2 | S44: =MAX(0,R44+R44*Note_Payoff_Breakeven!$B$6-MAX(0,B44*POWER(1+Note_Payoff_Breakeven!$B$11,16)*Note_Payoff_Breakeven!$B$8-Note_Payoff_Breakeven!$B$7)*Note_Payoff_Breakeven!$B$9*Note_Payoff_Breakeven!$B$10) -> 945058.02 | T44: =MAX(0,S44+S44*Note_Payoff_Breakeven!$B$6-MAX(0,B44*POWER(1+Note_Payoff_Breakeven!$B$11,17)*Note_Payoff_Breakeven!$B$8-Note_Payoff_Breakeven!$B$7)*Note_Payoff_Breakeven!$B$9*Note_Payoff_Breakeven!$B$10) -> 400752.87 | U44: =MAX(0,T44+T44*Note_Payoff_Breakeven!$B$6-MAX(0,B44*POWER(1+Note_Payoff_Breakeven!$B$11,18)*Note_Payoff_Breakeven!$B$8-Note_Payoff_Breakeven!$B$7)*Note_Payoff_Breakeven!$B$9*Note_Payoff_Breakeven!$B$10) -> 0 | V44: =MAX(0,U44+U44*Note_Payoff_Breakeven!$B$6-MAX(0,B44*POWER(1+Note_Payoff_Breakeven!$B$11,19)*Note_Payoff_Breakeven!$B$8-Note_Payoff_Breakeven!$B$7)*Note_Payoff_Breakeven!$B$9*Note_Payoff_Breakeven!$B$10) -> 0
A45: =A31 -> 1M below MAA (hypothetical) | B45: =B31 -> 42835000 | C45: =MAX(0,Note_Payoff_Breakeven!$B$5+Note_Payoff_Breakeven!$B$5*Note_Payoff_Breakeven!$B$6-MAX(0,B45*POWER(1+Note_Payoff_Breakeven!$B$11,0)*Note_Payoff_Breakeven!$B$8-Note_Payoff_Breakeven!$B$7)*Note_Payoff_Breakeven!$B$9*Note_Payoff_Breakeven!$B$10) -> 7030105.1 | D45: =MAX(0,C45+C45*Note_Payoff_Breakeven!$B$6-MAX(0,B45*POWER(1+Note_Payoff_Breakeven!$B$11,1)*Note_Payoff_Breakeven!$B$8-Note_Payoff_Breakeven!$B$7)*Note_Payoff_Breakeven!$B$9*Note_Payoff_Breakeven!$B$10) -> 6780097.1 | E45: =MAX(0,D45+D45*Note_Payoff_Breakeven!$B$6-MAX(0,B45*POWER(1+Note_Payoff_Breakeven!$B$11,2)*Note_Payoff_Breakeven!$B$8-Note_Payoff_Breakeven!$B$7)*Note_Payoff_Breakeven!$B$9*Note_Payoff_Breakeven!$B$10) -> 6518588.6 | F45: =MAX(0,E45+E45*Note_Payoff_Breakeven!$B$6-MAX(0,B45*POWER(1+Note_Payoff_Breakeven!$B$11,3)*Note_Payoff_Breakeven!$B$8-Note_Payoff_Breakeven!$B$7)*Note_Payoff_Breakeven!$B$9*Note_Payoff_Breakeven!$B$10) -> 6245050.8 | G45: =MAX(0,F45+F45*Note_Payoff_Breakeven!$B$6-MAX(0,B45*POWER(1+Note_Payoff_Breakeven!$B$11,4)*Note_Payoff_Breakeven!$B$8-Note_Payoff_Breakeven!$B$7)*Note_Payoff_Breakeven!$B$9*Note_Payoff_Breakeven!$B$10) -> 5958930.3 | H45: =MAX(0,G45+G45*Note_Payoff_Breakeven!$B$6-MAX(0,B45*POWER(1+Note_Payoff_Breakeven!$B$11,5)*Note_Payoff_Breakeven!$B$8-Note_Payoff_Breakeven!$B$7)*Note_Payoff_Breakeven!$B$9*Note_Payoff_Breakeven!$B$10) -> 5659648.2 | I45: =MAX(0,H45+H45*Note_Payoff_Breakeven!$B$6-MAX(0,B45*POWER(1+Note_Payoff_Breakeven!$B$11,6)*Note_Payoff_Breakeven!$B$8-Note_Payoff_Breakeven!$B$7)*Note_Payoff_Breakeven!$B$9*Note_Payoff_Breakeven!$B$10) -> 5346599.1 | J45: =MAX(0,I45+I45*Note_Payoff_Breakeven!$B$6-MAX(0,B45*POWER(1+Note_Payoff_Breakeven!$B$11,7)*Note_Payoff_Breakeven!$B$8-Note_Payoff_Breakeven!$B$7)*Note_Payoff_Breakeven!$B$9*Note_Payoff_Breakeven!$B$10) -> 5019149.8 | K45: =MAX(0,J45+J45*Note_Payoff_Breakeven!$B$6-MAX(0,B45*POWER(1+Note_Payoff_Breakeven!$B$11,8)*Note_Payoff_Breakeven!$B$8-Note_Payoff_Breakeven!$B$7)*Note_Payoff_Breakeven!$B$9*Note_Payoff_Breakeven!$B$10) -> 4676637.8 | L45: =MAX(0,K45+K45*Note_Payoff_Breakeven!$B$6-MAX(0,B45*POWER(1+Note_Payoff_Breakeven!$B$11,9)*Note_Payoff_Breakeven!$B$8-Note_Payoff_Breakeven!$B$7)*Note_Payoff_Breakeven!$B$9*Note_Payoff_Breakeven!$B$10) -> 4318370.2 | M45: =MAX(0,L45+L45*Note_Payoff_Breakeven!$B$6-MAX(0,B45*POWER(1+Note_Payoff_Breakeven!$B$11,10)*Note_Payoff_Breakeven!$B$8-Note_Payoff_Breakeven!$B$7)*Note_Payoff_Breakeven!$B$9*Note_Payoff_Breakeven!$B$10) -> 3943622.4 | N45: =MAX(0,M45+M45*Note_Payoff_Breakeven!$B$6-MAX(0,B45*POWER(1+Note_Payoff_Breakeven!$B$11,11)*Note_Payoff_Breakeven!$B$8-Note_Payoff_Breakeven!$B$7)*Note_Payoff_Breakeven!$B$9*Note_Payoff_Breakeven!$B$10) -> 3551636.1 | O45: =MAX(0,N45+N45*Note_Payoff_Breakeven!$B$6-MAX(0,B45*POWER(1+Note_Payoff_Breakeven!$B$11,12)*Note_Payoff_Breakeven!$B$8-Note_Payoff_Breakeven!$B$7)*Note_Payoff_Breakeven!$B$9*Note_Payoff_Breakeven!$B$10) -> 3141618.5 | P45: =MAX(0,O45+O45*Note_Payoff_Breakeven!$B$6-MAX(0,B45*POWER(1+Note_Payoff_Breakeven!$B$11,13)*Note_Payoff_Breakeven!$B$8-Note_Payoff_Breakeven!$B$7)*Note_Payoff_Breakeven!$B$9*Note_Payoff_Breakeven!$B$10) -> 2712740 | Q45: =MAX(0,P45+P45*Note_Payoff_Breakeven!$B$6-MAX(0,B45*POWER(1+Note_Payoff_Breakeven!$B$11,14)*Note_Payoff_Breakeven!$B$8-Note_Payoff_Breakeven!$B$7)*Note_Payoff_Breakeven!$B$9*Note_Payoff_Breakeven!$B$10) -> 2264133.2 | R45: =MAX(0,Q45+Q45*Note_Payoff_Breakeven!$B$6-MAX(0,B45*POWER(1+Note_Payoff_Breakeven!$B$11,15)*Note_Payoff_Breakeven!$B$8-Note_Payoff_Breakeven!$B$7)*Note_Payoff_Breakeven!$B$9*Note_Payoff_Breakeven!$B$10) -> 1794890.4 | S45: =MAX(0,R45+R45*Note_Payoff_Breakeven!$B$6-MAX(0,B45*POWER(1+Note_Payoff_Breakeven!$B$11,16)*Note_Payoff_Breakeven!$B$8-Note_Payoff_Breakeven!$B$7)*Note_Payoff_Breakeven!$B$9*Note_Payoff_Breakeven!$B$10) -> 1304062.5 | T45: =MAX(0,S45+S45*Note_Payoff_Breakeven!$B$6-MAX(0,B45*POWER(1+Note_Payoff_Breakeven!$B$11,17)*Note_Payoff_Breakeven!$B$8-Note_Payoff_Breakeven!$B$7)*Note_Payoff_Breakeven!$B$9*Note_Payoff_Breakeven!$B$10) -> 790656.44 | U45: =MAX(0,T45+T45*Note_Payoff_Breakeven!$B$6-MAX(0,B45*POWER(1+Note_Payoff_Breakeven!$B$11,18)*Note_Payoff_Breakeven!$B$8-Note_Payoff_Breakeven!$B$7)*Note_Payoff_Breakeven!$B$9*Note_Payoff_Breakeven!$B$10) -> 253633.74 | V45: =MAX(0,U45+U45*Note_Payoff_Breakeven!$B$6-MAX(0,B45*POWER(1+Note_Payoff_Breakeven!$B$11,19)*Note_Payoff_Breakeven!$B$8-Note_Payoff_Breakeven!$B$7)*Note_Payoff_Breakeven!$B$9*Note_Payoff_Breakeven!$B$10) -> 0
A46: =A32 -> BREAKEVEN (calculated) | B46: =B32 -> 42159406 | C46: =MAX(0,Note_Payoff_Breakeven!$B$5+Note_Payoff_Breakeven!$B$5*Note_Payoff_Breakeven!$B$6-MAX(0,B46*POWER(1+Note_Payoff_Breakeven!$B$11,0)*Note_Payoff_Breakeven!$B$8-Note_Payoff_Breakeven!$B$7)*Note_Payoff_Breakeven!$B$9*Note_Payoff_Breakeven!$B$10) -> 7039823.5 | D46: =MAX(0,C46+C46*Note_Payoff_Breakeven!$B$6-MAX(0,B46*POWER(1+Note_Payoff_Breakeven!$B$11,1)*Note_Payoff_Breakeven!$B$8-Note_Payoff_Breakeven!$B$7)*Note_Payoff_Breakeven!$B$9*Note_Payoff_Breakeven!$B$10) -> 6799980.9 | E46: =MAX(0,D46+D46*Note_Payoff_Breakeven!$B$6-MAX(0,B46*POWER(1+Note_Payoff_Breakeven!$B$11,2)*Note_Payoff_Breakeven!$B$8-Note_Payoff_Breakeven!$B$7)*Note_Payoff_Breakeven!$B$9*Note_Payoff_Breakeven!$B$10) -> 6549105.5 | F46: =MAX(0,E46+E46*Note_Payoff_Breakeven!$B$6-MAX(0,B46*POWER(1+Note_Payoff_Breakeven!$B$11,3)*Note_Payoff_Breakeven!$B$8-Note_Payoff_Breakeven!$B$7)*Note_Payoff_Breakeven!$B$9*Note_Payoff_Breakeven!$B$10) -> 6286689.8 | G46: =MAX(0,F46+F46*Note_Payoff_Breakeven!$B$6-MAX(0,B46*POWER(1+Note_Payoff_Breakeven!$B$11,4)*Note_Payoff_Breakeven!$B$8-Note_Payoff_Breakeven!$B$7)*Note_Payoff_Breakeven!$B$9*Note_Payoff_Breakeven!$B$10) -> 6012203 | H46: =MAX(0,G46+G46*Note_Payoff_Breakeven!$B$6-MAX(0,B46*POWER(1+Note_Payoff_Breakeven!$B$11,5)*Note_Payoff_Breakeven!$B$8-Note_Payoff_Breakeven!$B$7)*Note_Payoff_Breakeven!$B$9*Note_Payoff_Breakeven!$B$10) -> 5725089.8 | I46: =MAX(0,H46+H46*Note_Payoff_Breakeven!$B$6-MAX(0,B46*POWER(1+Note_Payoff_Breakeven!$B$11,6)*Note_Payoff_Breakeven!$B$8-Note_Payoff_Breakeven!$B$7)*Note_Payoff_Breakeven!$B$9*Note_Payoff_Breakeven!$B$10) -> 5424769.4 | J46: =MAX(0,I46+I46*Note_Payoff_Breakeven!$B$6-MAX(0,B46*POWER(1+Note_Payoff_Breakeven!$B$11,7)*Note_Payoff_Breakeven!$B$8-Note_Payoff_Breakeven!$B$7)*Note_Payoff_Breakeven!$B$9*Note_Payoff_Breakeven!$B$10) -> 5110634.3 | K46: =MAX(0,J46+J46*Note_Payoff_Breakeven!$B$6-MAX(0,B46*POWER(1+Note_Payoff_Breakeven!$B$11,8)*Note_Payoff_Breakeven!$B$8-Note_Payoff_Breakeven!$B$7)*Note_Payoff_Breakeven!$B$9*Note_Payoff_Breakeven!$B$10) -> 4782048.9 | L46: =MAX(0,K46+K46*Note_Payoff_Breakeven!$B$6-MAX(0,B46*POWER(1+Note_Payoff_Breakeven!$B$11,9)*Note_Payoff_Breakeven!$B$8-Note_Payoff_Breakeven!$B$7)*Note_Payoff_Breakeven!$B$9*Note_Payoff_Breakeven!$B$10) -> 4438348.7 | M46: =MAX(0,L46+L46*Note_Payoff_Breakeven!$B$6-MAX(0,B46*POWER(1+Note_Payoff_Breakeven!$B$11,10)*Note_Payoff_Breakeven!$B$8-Note_Payoff_Breakeven!$B$7)*Note_Payoff_Breakeven!$B$9*Note_Payoff_Breakeven!$B$10) -> 4078838.2 | N46: =MAX(0,M46+M46*Note_Payoff_Breakeven!$B$6-MAX(0,B46*POWER(1+Note_Payoff_Breakeven!$B$11,11)*Note_Payoff_Breakeven!$B$8-Note_Payoff_Breakeven!$B$7)*Note_Payoff_Breakeven!$B$9*Note_Payoff_Breakeven!$B$10) -> 3702790.2 | O46: =MAX(0,N46+N46*Note_Payoff_Breakeven!$B$6-MAX(0,B46*POWER(1+Note_Payoff_Breakeven!$B$11,12)*Note_Payoff_Breakeven!$B$8-Note_Payoff_Breakeven!$B$7)*Note_Payoff_Breakeven!$B$9*Note_Payoff_Breakeven!$B$10) -> 3309444 | P46: =MAX(0,O46+O46*Note_Payoff_Breakeven!$B$6-MAX(0,B46*POWER(1+Note_Payoff_Breakeven!$B$11,13)*Note_Payoff_Breakeven!$B$8-Note_Payoff_Breakeven!$B$7)*Note_Payoff_Breakeven!$B$9*Note_Payoff_Breakeven!$B$10) -> 2898003.9 | Q46: =MAX(0,P46+P46*Note_Payoff_Breakeven!$B$6-MAX(0,B46*POWER(1+Note_Payoff_Breakeven!$B$11,14)*Note_Payoff_Breakeven!$B$8-Note_Payoff_Breakeven!$B$7)*Note_Payoff_Breakeven!$B$9*Note_Payoff_Breakeven!$B$10) -> 2467637.6 | R46: =MAX(0,Q46+Q46*Note_Payoff_Breakeven!$B$6-MAX(0,B46*POWER(1+Note_Payoff_Breakeven!$B$11,15)*Note_Payoff_Breakeven!$B$8-Note_Payoff_Breakeven!$B$7)*Note_Payoff_Breakeven!$B$9*Note_Payoff_Breakeven!$B$10) -> 2017474.4 | S46: =MAX(0,R46+R46*Note_Payoff_Breakeven!$B$6-MAX(0,B46*POWER(1+Note_Payoff_Breakeven!$B$11,16)*Note_Payoff_Breakeven!$B$8-Note_Payoff_Breakeven!$B$7)*Note_Payoff_Breakeven!$B$9*Note_Payoff_Breakeven!$B$10) -> 1546603.7 | T46: =MAX(0,S46+S46*Note_Payoff_Breakeven!$B$6-MAX(0,B46*POWER(1+Note_Payoff_Breakeven!$B$11,17)*Note_Payoff_Breakeven!$B$8-Note_Payoff_Breakeven!$B$7)*Note_Payoff_Breakeven!$B$9*Note_Payoff_Breakeven!$B$10) -> 1054072.9 | U46: =MAX(0,T46+T46*Note_Payoff_Breakeven!$B$6-MAX(0,B46*POWER(1+Note_Payoff_Breakeven!$B$11,18)*Note_Payoff_Breakeven!$B$8-Note_Payoff_Breakeven!$B$7)*Note_Payoff_Breakeven!$B$9*Note_Payoff_Breakeven!$B$10) -> 538885.78 | V46: =MAX(0,U46+U46*Note_Payoff_Breakeven!$B$6-MAX(0,B46*POWER(1+Note_Payoff_Breakeven!$B$11,19)*Note_Payoff_Breakeven!$B$8-Note_Payoff_Breakeven!$B$7)*Note_Payoff_Breakeven!$B$9*Note_Payoff_Breakeven!$B$10) -> 0
A47: =A33 -> 500K below breakeven | B47: =B33 -> 41659406 | C47: =MAX(0,Note_Payoff_Breakeven!$B$5+Note_Payoff_Breakeven!$B$5*Note_Payoff_Breakeven!$B$6-MAX(0,B47*POWER(1+Note_Payoff_Breakeven!$B$11,0)*Note_Payoff_Breakeven!$B$8-Note_Payoff_Breakeven!$B$7)*Note_Payoff_Breakeven!$B$9*Note_Payoff_Breakeven!$B$10) -> 7047016 | D47: =MAX(0,C47+C47*Note_Payoff_Breakeven!$B$6-MAX(0,B47*POWER(1+Note_Payoff_Breakeven!$B$11,1)*Note_Payoff_Breakeven!$B$8-Note_Payoff_Breakeven!$B$7)*Note_Payoff_Breakeven!$B$9*Note_Payoff_Breakeven!$B$10) -> 6814696.6 | E47: =MAX(0,D47+D47*Note_Payoff_Breakeven!$B$6-MAX(0,B47*POWER(1+Note_Payoff_Breakeven!$B$11,2)*Note_Payoff_Breakeven!$B$8-Note_Payoff_Breakeven!$B$7)*Note_Payoff_Breakeven!$B$9*Note_Payoff_Breakeven!$B$10) -> 6571690.6 | F47: =MAX(0,E47+E47*Note_Payoff_Breakeven!$B$6-MAX(0,B47*POWER(1+Note_Payoff_Breakeven!$B$11,3)*Note_Payoff_Breakeven!$B$8-Note_Payoff_Breakeven!$B$7)*Note_Payoff_Breakeven!$B$9*Note_Payoff_Breakeven!$B$10) -> 6317506.3 | G47: =MAX(0,F47+F47*Note_Payoff_Breakeven!$B$6-MAX(0,B47*POWER(1+Note_Payoff_Breakeven!$B$11,4)*Note_Payoff_Breakeven!$B$8-Note_Payoff_Breakeven!$B$7)*Note_Payoff_Breakeven!$B$9*Note_Payoff_Breakeven!$B$10) -> 6051629.6 | H47: =MAX(0,G47+G47*Note_Payoff_Breakeven!$B$6-MAX(0,B47*POWER(1+Note_Payoff_Breakeven!$B$11,5)*Note_Payoff_Breakeven!$B$8-Note_Payoff_Breakeven!$B$7)*Note_Payoff_Breakeven!$B$9*Note_Payoff_Breakeven!$B$10) -> 5773522.5 | I47: =MAX(0,H47+H47*Note_Payoff_Breakeven!$B$6-MAX(0,B47*POWER(1+Note_Payoff_Breakeven!$B$11,6)*Note_Payoff_Breakeven!$B$8-Note_Payoff_Breakeven!$B$7)*Note_Payoff_Breakeven!$B$9*Note_Payoff_Breakeven!$B$10) -> 5482622.4 | J47: =MAX(0,I47+I47*Note_Payoff_Breakeven!$B$6-MAX(0,B47*POWER(1+Note_Payoff_Breakeven!$B$11,7)*Note_Payoff_Breakeven!$B$8-Note_Payoff_Breakeven!$B$7)*Note_Payoff_Breakeven!$B$9*Note_Payoff_Breakeven!$B$10) -> 5178341 | K47: =MAX(0,J47+J47*Note_Payoff_Breakeven!$B$6-MAX(0,B47*POWER(1+Note_Payoff_Breakeven!$B$11,8)*Note_Payoff_Breakeven!$B$8-Note_Payoff_Breakeven!$B$7)*Note_Payoff_Breakeven!$B$9*Note_Payoff_Breakeven!$B$10) -> 4860062.6 | L47: =MAX(0,K47+K47*Note_Payoff_Breakeven!$B$6-MAX(0,B47*POWER(1+Note_Payoff_Breakeven!$B$11,9)*Note_Payoff_Breakeven!$B$8-Note_Payoff_Breakeven!$B$7)*Note_Payoff_Breakeven!$B$9*Note_Payoff_Breakeven!$B$10) -> 4527143.4 | M47: =MAX(0,L47+L47*Note_Payoff_Breakeven!$B$6-MAX(0,B47*POWER(1+Note_Payoff_Breakeven!$B$11,10)*Note_Payoff_Breakeven!$B$8-Note_Payoff_Breakeven!$B$7)*Note_Payoff_Breakeven!$B$9*Note_Payoff_Breakeven!$B$10) -> 4178910 | N47: =MAX(0,M47+M47*Note_Payoff_Breakeven!$B$6-MAX(0,B47*POWER(1+Note_Payoff_Breakeven!$B$11,11)*Note_Payoff_Breakeven!$B$8-Note_Payoff_Breakeven!$B$7)*Note_Payoff_Breakeven!$B$9*Note_Payoff_Breakeven!$B$10) -> 3814657.8 | O47: =MAX(0,N47+N47*Note_Payoff_Breakeven!$B$6-MAX(0,B47*POWER(1+Note_Payoff_Breakeven!$B$11,12)*Note_Payoff_Breakeven!$B$8-Note_Payoff_Breakeven!$B$7)*Note_Payoff_Breakeven!$B$9*Note_Payoff_Breakeven!$B$10) -> 3433650 | P47: =MAX(0,O47+O47*Note_Payoff_Breakeven!$B$6-MAX(0,B47*POWER(1+Note_Payoff_Breakeven!$B$11,13)*Note_Payoff_Breakeven!$B$8-Note_Payoff_Breakeven!$B$7)*Note_Payoff_Breakeven!$B$9*Note_Payoff_Breakeven!$B$10) -> 3035115.8 | Q47: =MAX(0,P47+P47*Note_Payoff_Breakeven!$B$6-MAX(0,B47*POWER(1+Note_Payoff_Breakeven!$B$11,14)*Note_Payoff_Breakeven!$B$8-Note_Payoff_Breakeven!$B$7)*Note_Payoff_Breakeven!$B$9*Note_Payoff_Breakeven!$B$10) -> 2618249.1 | R47: =MAX(0,Q47+Q47*Note_Payoff_Breakeven!$B$6-MAX(0,B47*POWER(1+Note_Payoff_Breakeven!$B$11,15)*Note_Payoff_Breakeven!$B$8-Note_Payoff_Breakeven!$B$7)*Note_Payoff_Breakeven!$B$9*Note_Payoff_Breakeven!$B$10) -> 2182206.5 | S47: =MAX(0,R47+R47*Note_Payoff_Breakeven!$B$6-MAX(0,B47*POWER(1+Note_Payoff_Breakeven!$B$11,16)*Note_Payoff_Breakeven!$B$8-Note_Payoff_Breakeven!$B$7)*Note_Payoff_Breakeven!$B$9*Note_Payoff_Breakeven!$B$10) -> 1726105.9 | T47: =MAX(0,S47+S47*Note_Payoff_Breakeven!$B$6-MAX(0,B47*POWER(1+Note_Payoff_Breakeven!$B$11,17)*Note_Payoff_Breakeven!$B$8-Note_Payoff_Breakeven!$B$7)*Note_Payoff_Breakeven!$B$9*Note_Payoff_Breakeven!$B$10) -> 1249024.7 | U47: =MAX(0,T47+T47*Note_Payoff_Breakeven!$B$6-MAX(0,B47*POWER(1+Note_Payoff_Breakeven!$B$11,18)*Note_Payoff_Breakeven!$B$8-Note_Payoff_Breakeven!$B$7)*Note_Payoff_Breakeven!$B$9*Note_Payoff_Breakeven!$B$10) -> 749997.81 | V47: =MAX(0,U47+U47*Note_Payoff_Breakeven!$B$6-MAX(0,B47*POWER(1+Note_Payoff_Breakeven!$B$11,19)*Note_Payoff_Breakeven!$B$8-Note_Payoff_Breakeven!$B$7)*Note_Payoff_Breakeven!$B$9*Note_Payoff_Breakeven!$B$10) -> 228015.64
A48: =A34 -> 1M below breakeven | B48: =B34 -> 41159406 | C48: =MAX(0,Note_Payoff_Breakeven!$B$5+Note_Payoff_Breakeven!$B$5*Note_Payoff_Breakeven!$B$6-MAX(0,B48*POWER(1+Note_Payoff_Breakeven!$B$11,0)*Note_Payoff_Breakeven!$B$8-Note_Payoff_Breakeven!$B$7)*Note_Payoff_Breakeven!$B$9*Note_Payoff_Breakeven!$B$10) -> 7054208.4 | D48: =MAX(0,C48+C48*Note_Payoff_Breakeven!$B$6-MAX(0,B48*POWER(1+Note_Payoff_Breakeven!$B$11,1)*Note_Payoff_Breakeven!$B$8-Note_Payoff_Breakeven!$B$7)*Note_Payoff_Breakeven!$B$9*Note_Payoff_Breakeven!$B$10) -> 6829412.4 | E48: =MAX(0,D48+D48*Note_Payoff_Breakeven!$B$6-MAX(0,B48*POWER(1+Note_Payoff_Breakeven!$B$11,2)*Note_Payoff_Breakeven!$B$8-Note_Payoff_Breakeven!$B$7)*Note_Payoff_Breakeven!$B$9*Note_Payoff_Breakeven!$B$10) -> 6594275.8 | F48: =MAX(0,E48+E48*Note_Payoff_Breakeven!$B$6-MAX(0,B48*POWER(1+Note_Payoff_Breakeven!$B$11,3)*Note_Payoff_Breakeven!$B$8-Note_Payoff_Breakeven!$B$7)*Note_Payoff_Breakeven!$B$9*Note_Payoff_Breakeven!$B$10) -> 6348322.9 | G48: =MAX(0,F48+F48*Note_Payoff_Breakeven!$B$6-MAX(0,B48*POWER(1+Note_Payoff_Breakeven!$B$11,4)*Note_Payoff_Breakeven!$B$8-Note_Payoff_Breakeven!$B$7)*Note_Payoff_Breakeven!$B$9*Note_Payoff_Breakeven!$B$10) -> 6091056.1 | H48: =MAX(0,G48+G48*Note_Payoff_Breakeven!$B$6-MAX(0,B48*POWER(1+Note_Payoff_Breakeven!$B$11,5)*Note_Payoff_Breakeven!$B$8-Note_Payoff_Breakeven!$B$7)*Note_Payoff_Breakeven!$B$9*Note_Payoff_Breakeven!$B$10) -> 5821955.1 | I48: =MAX(0,H48+H48*Note_Payoff_Breakeven!$B$6-MAX(0,B48*POWER(1+Note_Payoff_Breakeven!$B$11,6)*Note_Payoff_Breakeven!$B$8-Note_Payoff_Breakeven!$B$7)*Note_Payoff_Breakeven!$B$9*Note_Payoff_Breakeven!$B$10) -> 5540475.4 | J48: =MAX(0,I48+I48*Note_Payoff_Breakeven!$B$6-MAX(0,B48*POWER(1+Note_Payoff_Breakeven!$B$11,7)*Note_Payoff_Breakeven!$B$8-Note_Payoff_Breakeven!$B$7)*Note_Payoff_Breakeven!$B$9*Note_Payoff_Breakeven!$B$10) -> 5246047.7 | K48: =MAX(0,J48+J48*Note_Payoff_Breakeven!$B$6-MAX(0,B48*POWER(1+Note_Payoff_Breakeven!$B$11,8)*Note_Payoff_Breakeven!$B$8-Note_Payoff_Breakeven!$B$7)*Note_Payoff_Breakeven!$B$9*Note_Payoff_Breakeven!$B$10) -> 4938076.3 | L48: =MAX(0,K48+K48*Note_Payoff_Breakeven!$B$6-MAX(0,B48*POWER(1+Note_Payoff_Breakeven!$B$11,9)*Note_Payoff_Breakeven!$B$8-Note_Payoff_Breakeven!$B$7)*Note_Payoff_Breakeven!$B$9*Note_Payoff_Breakeven!$B$10) -> 4615938.2 | M48: =MAX(0,L48+L48*Note_Payoff_Breakeven!$B$6-MAX(0,B48*POWER(1+Note_Payoff_Breakeven!$B$11,10)*Note_Payoff_Breakeven!$B$8-Note_Payoff_Breakeven!$B$7)*Note_Payoff_Breakeven!$B$9*Note_Payoff_Breakeven!$B$10) -> 4278981.8 | N48: =MAX(0,M48+M48*Note_Payoff_Breakeven!$B$6-MAX(0,B48*POWER(1+Note_Payoff_Breakeven!$B$11,11)*Note_Payoff_Breakeven!$B$8-Note_Payoff_Breakeven!$B$7)*Note_Payoff_Breakeven!$B$9*Note_Payoff_Breakeven!$B$10) -> 3926525.4 | O48: =MAX(0,N48+N48*Note_Payoff_Breakeven!$B$6-MAX(0,B48*POWER(1+Note_Payoff_Breakeven!$B$11,12)*Note_Payoff_Breakeven!$B$8-Note_Payoff_Breakeven!$B$7)*Note_Payoff_Breakeven!$B$9*Note_Payoff_Breakeven!$B$10) -> 3557855.9 | P48: =MAX(0,O48+O48*Note_Payoff_Breakeven!$B$6-MAX(0,B48*POWER(1+Note_Payoff_Breakeven!$B$11,13)*Note_Payoff_Breakeven!$B$8-Note_Payoff_Breakeven!$B$7)*Note_Payoff_Breakeven!$B$9*Note_Payoff_Breakeven!$B$10) -> 3172227.7 | Q48: =MAX(0,P48+P48*Note_Payoff_Breakeven!$B$6-MAX(0,B48*POWER(1+Note_Payoff_Breakeven!$B$11,14)*Note_Payoff_Breakeven!$B$8-Note_Payoff_Breakeven!$B$7)*Note_Payoff_Breakeven!$B$9*Note_Payoff_Breakeven!$B$10) -> 2768860.6 | R48: =MAX(0,Q48+Q48*Note_Payoff_Breakeven!$B$6-MAX(0,B48*POWER(1+Note_Payoff_Breakeven!$B$11,15)*Note_Payoff_Breakeven!$B$8-Note_Payoff_Breakeven!$B$7)*Note_Payoff_Breakeven!$B$9*Note_Payoff_Breakeven!$B$10) -> 2346938.6 | S48: =MAX(0,R48+R48*Note_Payoff_Breakeven!$B$6-MAX(0,B48*POWER(1+Note_Payoff_Breakeven!$B$11,16)*Note_Payoff_Breakeven!$B$8-Note_Payoff_Breakeven!$B$7)*Note_Payoff_Breakeven!$B$9*Note_Payoff_Breakeven!$B$10) -> 1905608.1 | T48: =MAX(0,S48+S48*Note_Payoff_Breakeven!$B$6-MAX(0,B48*POWER(1+Note_Payoff_Breakeven!$B$11,17)*Note_Payoff_Breakeven!$B$8-Note_Payoff_Breakeven!$B$7)*Note_Payoff_Breakeven!$B$9*Note_Payoff_Breakeven!$B$10) -> 1443976.5 | U48: =MAX(0,T48+T48*Note_Payoff_Breakeven!$B$6-MAX(0,B48*POWER(1+Note_Payoff_Breakeven!$B$11,18)*Note_Payoff_Breakeven!$B$8-Note_Payoff_Breakeven!$B$7)*Note_Payoff_Breakeven!$B$9*Note_Payoff_Breakeven!$B$10) -> 961109.83 | V48: =MAX(0,U48+U48*Note_Payoff_Breakeven!$B$6-MAX(0,B48*POWER(1+Note_Payoff_Breakeven!$B$11,19)*Note_Payoff_Breakeven!$B$8-Note_Payoff_Breakeven!$B$7)*Note_Payoff_Breakeven!$B$9*Note_Payoff_Breakeven!$B$10) -> 456031.29
A51: KEY OBSERVATIONS
A52: 1. Breakeven 2026 TMV (at 0% growth) ≈ $42.16M — about $1.7M BELOW the MAA Floor of $43.835M.
A53: 2. Appealing to the MAA Floor leaves a cushion: the Note still pays off in 2044 with $0 remaining at the last increment (2045).
A54: 3. The MAA Floor is the BINDING CONSTRAINT — you cannot legally appeal below it. The Note payoff constraint is even more conservative.
A55: 4. Higher growth assumptions push breakeven DOWN (more room to appeal). Negative growth pushes breakeven UP.
A56: 5. Per Note §3: any balance unpaid at last TIF receipt is FORGIVEN (limited revenue note). There is no Note "default" possible — only foregone TIF.
A57: 6. To stress test: change "TMV Annual Growth Rate" (yellow cell) to negative values to see how rate compresses cushion.

Sheet Ehlers_Recon
A1: Ehlers Reconciliation
A2: Proves this model reproduces Ehlers' published numbers when fed the same inputs (Ehlers tested the full reduction from $54.866M down to the recorded MAA floor of $43.835M).
A4: Item | B4: Ehlers Published | C4: This Model | D4: Difference | E4: Source / Note
A5: TMV reduction from $54.866M to MAA Floor | B5: =Assumptions!$B$24 -> 11031000 | C5: =Assumptions!$B$19-Assumptions!$B$18 -> 11031000 | D5: =C5-B5 -> 0 | E5: $54,866,000 − $43,835,000
A6: NTC reduction (annual) | B6: =Assumptions!$B$25 -> 137888 | C6: =(Assumptions!$B$19-Assumptions!$B$18)*Assumptions!$B$4 -> 137887.5 | D6: =C6-B6 -> -0.5 | E6: 11,031,000 × 1.25% Class Rate
A7: Gross TIF reduction (annual, before admin) | B7: =Assumptions!$B$26 -> 176312 | C7: =(Assumptions!$B$19-Assumptions!$B$18)*Assumptions!$B$4*Assumptions!$B$5 -> 176311.23 | D7: =C7-B7 -> -0.76925 | E7: 137,888 NTC × 1.28 Tax Capacity Rate
A8: Net TIF reduction after Admin 10% (annual) | B8: =Assumptions!$B$27 -> 158681 | C8: =(Assumptions!$B$19-Assumptions!$B$18)*Assumptions!$B$4*Assumptions!$B$5*(1-Assumptions!$B$7) -> 158680.11 | D8: =C8-B8 -> -0.892325 | E8: Ehlers applies 10% admin haircut to gross; this model matches exactly
A9: Annual gross tax savings (full burden) | B9: — | C9: =(Assumptions!$B$19-Assumptions!$B$18)*Assumptions!$B$4*Assumptions!$B$5 -> 176311.23 | D9: — | E9: Same multiplier as TIF reduction — owner saves what TIF loses, pre-admin
A10: 18-year cumulative tax savings | B10: =Assumptions!$B$28 -> 2856258 | C10: =(Assumptions!$B$19-Assumptions!$B$18)*Assumptions!$B$4*Assumptions!$B$5*18 -> 3173602.2 | D10: =C10-B10 -> 317344.15 | E10: Ehlers states ~$2.856M, 18 years of $158,681
A13: ENGINE-DRIVEN COMPARISON (full 19-year horizon)
A14: Metric | B14: MAA Floor Engine Output | C14: Ehlers Published | D14: Difference | E14: Note
A15: TMV held at MAA Floor for 19 years — Total Property Tax | B15: =Engine_MAA_Floor!N25 -> 13311890 | C15: — | D15: — | E15: N/A — Ehlers states annual tax SAVINGS, not absolute property tax
A16: 19-yr Total Tax Savings vs. $54.866M baseline | B16: =Engine_Current!N25-Engine_MAA_Floor!N25 -> 3349913.4 | C16: =(Assumptions!$B$19-Assumptions!$B$18)*Assumptions!$B$4*Assumptions!$B$5*19 -> 3349913.4 | D16: =B16-C16 -> 0 | E16: Direct verification — 19 years × $176K annual
A17: 19-yr Total Net TIF Reduction vs. $54.866M baseline | B17: =Engine_Current!I25-Engine_MAA_Floor!I25 -> 3004068.3 | C17: — | D17: — | E17: Note: 19-yr horizon includes years where Note has been paid off in both scenarios, so TIF flow may differ from 19 × $158,681
A18: Net Economic Benefit vs. Current (NPV @ DiscRate) | B18: =(Engine_Current!N28-Engine_MAA_Floor!N28)-(Engine_Current!I28-Engine_MAA_Floor!I28) -> 219981.5 | C18: =Assumptions!$B$31 -> 1100000 | D18: =B18-C18 -> -880018.5 | E18: Ehlers ~$1.10M NPV @ 5%; this model uses DiscRate input (default 5%)

Sheet Sensitivity_Appeal
A1: Appeal Target Sensitivity
A2: The CORRECT sensitivity axis for this decision is the appeal target, not the market-growth rate (which the IDP/Shaver model flexes). This table sweeps the post-appeal TMV from $54.866M (no appeal) down to the $43.835M MAA floor, holding the post-appeal TMV flat for 19 years. Each row uses simple multiplier math against the Ehlers methodology; users can verify any row by setting Inputs_TMV to that value.
A4: Scenario | B4: Post-Appeal TMV (flat) | C4: Annual Tax Savings vs. $54.866M | D4: Annual Net TIF Reduction vs. $54.866M | E4: 19-yr Cumulative Tax Savings | F4: 19-yr Cumulative TIF Reduction | G4: 19-yr Net Nominal Benefit | H4: NPV Tax Savings @ DiscRate | I4: NPV Net Benefit @ DiscRate
A5: No Appeal | B5: 54866000 | C5: =(Assumptions!$B$19-B5)*Assumptions!$B$4*Assumptions!$B$5 -> 0 | D5: =(Assumptions!$B$19-B5)*Assumptions!$B$4*Assumptions!$B$5*(1-Assumptions!$B$8)*(1-Assumptions!$B$7)*Assumptions!$B$6 -> 0 | E5: =C5*19 -> 0 | F5: =D5*19 -> 0 | G5: =E5-F5 -> 0 | H5: =PV(Assumptions!$B$34,19,-C5) -> 0 | I5: =PV(Assumptions!$B$34,19,-(C5-D5)) -> 0
A6: Mild Appeal | B6: 54000000 | C6: =(Assumptions!$B$19-B6)*Assumptions!$B$4*Assumptions!$B$5 -> 13841.495 | D6: =(Assumptions!$B$19-B6)*Assumptions!$B$4*Assumptions!$B$5*(1-Assumptions!$B$8)*(1-Assumptions!$B$7)*Assumptions!$B$6 -> 12412.499 | E6: =C6*19 -> 262988.4 | F6: =D6*19 -> 235837.47 | G6: =E6-F6 -> 27150.922 | H6: =PV(Assumptions!$B$34,19,-C6) -> 167278.9 | I6: =PV(Assumptions!$B$34,19,-(C6-D6)) -> 17269.874
A7: Mid Appeal ($52.15M) | B7: 52150000 | C7: =(Assumptions!$B$19-B7)*Assumptions!$B$4*Assumptions!$B$5 -> 43410.507 | D7: =(Assumptions!$B$19-B7)*Assumptions!$B$4*Assumptions!$B$5*(1-Assumptions!$B$8)*(1-Assumptions!$B$7)*Assumptions!$B$6 -> 38928.806 | E7: =C7*19 -> 824799.63 | F7: =D7*19 -> 739647.32 | G7: =E7-F7 -> 85152.314 | H7: =PV(Assumptions!$B$34,19,-C7) -> 524629.91 | I7: =PV(Assumptions!$B$34,19,-(C7-D7)) -> 54162.791
A8: Pay 2026 Current (County) | B8: 52151000 | C8: =(Assumptions!$B$19-B8)*Assumptions!$B$4*Assumptions!$B$5 -> 43394.524 | D8: =(Assumptions!$B$19-B8)*Assumptions!$B$4*Assumptions!$B$5*(1-Assumptions!$B$8)*(1-Assumptions!$B$7)*Assumptions!$B$6 -> 38914.473 | E8: =C8*19 -> 824495.95 | F8: =D8*19 -> 739374.99 | G8: =E8-F8 -> 85120.962 | H8: =PV(Assumptions!$B$34,19,-C8) -> 524436.74 | I8: =PV(Assumptions!$B$34,19,-(C8-D8)) -> 54142.849
A9: Aggressive Appeal ($50M) | B9: 50000000 | C9: =(Assumptions!$B$19-B9)*Assumptions!$B$4*Assumptions!$B$5 -> 77774.495 | D9: =(Assumptions!$B$19-B9)*Assumptions!$B$4*Assumptions!$B$5*(1-Assumptions!$B$8)*(1-Assumptions!$B$7)*Assumptions!$B$6 -> 69745.056 | E9: =C9*19 -> 1477715.4 | F9: =D9*19 -> 1325156.1 | G9: =E9-F9 -> 152559.34 | H9: =PV(Assumptions!$B$34,19,-C9) -> 939929.72 | I9: =PV(Assumptions!$B$34,19,-(C9-D9)) -> 97038.344
A10: Deep Appeal ($48M) | B10: 48000000 | C10: =(Assumptions!$B$19-B10)*Assumptions!$B$4*Assumptions!$B$5 -> 109740.99 | D10: =(Assumptions!$B$19-B10)*Assumptions!$B$4*Assumptions!$B$5*(1-Assumptions!$B$8)*(1-Assumptions!$B$7)*Assumptions!$B$6 -> 98411.334 | E10: =C10*19 -> 2085078.9 | F10: =D10*19 -> 1869815.4 | G10: =E10-F10 -> 215263.55 | H10: =PV(Assumptions!$B$34,19,-C10) -> 1326255.1 | I10: =PV(Assumptions!$B$34,19,-(C10-D10)) -> 136922.58
A11: Deep Appeal ($46M) | B11: 46000000 | C11: =(Assumptions!$B$19-B11)*Assumptions!$B$4*Assumptions!$B$5 -> 141707.49 | D11: =(Assumptions!$B$19-B11)*Assumptions!$B$4*Assumptions!$B$5*(1-Assumptions!$B$8)*(1-Assumptions!$B$7)*Assumptions!$B$6 -> 127077.61 | E11: =C11*19 -> 2692442.4 | F11: =D11*19 -> 2414474.6 | G11: =E11-F11 -> 277967.75 | H11: =PV(Assumptions!$B$34,19,-C11) -> 1712580.5 | I11: =PV(Assumptions!$B$34,19,-(C11-D11)) -> 176806.81
A12: MAA Floor ($43.835M) | B12: 43835000 | C12: =(Assumptions!$B$19-B12)*Assumptions!$B$4*Assumptions!$B$5 -> 176311.23 | D12: =(Assumptions!$B$19-B12)*Assumptions!$B$4*Assumptions!$B$5*(1-Assumptions!$B$8)*(1-Assumptions!$B$7)*Assumptions!$B$6 -> 158108.86 | E12: =C12*19 -> 3349913.4 | F12: =D12*19 -> 3004068.3 | G12: =E12-F12 -> 345845.06 | H12: =PV(Assumptions!$B$34,19,-C12) -> 2130777.8 | I12: =PV(Assumptions!$B$34,19,-(C12-D12)) -> 219981.5
A14: KEY POINT
A15: • Every appeal scenario produces a POSITIVE net benefit to ownership over the full 19-year TIF life. The benefit GROWS as the appeal goes deeper.
A16: • The IDP/Shaver model varies market growth rate and stops at year 10. That axis has nothing to do with the appeal decision — the appeal target itself does.
A17: • Annual property tax SAVINGS ($176K at the MAA floor) flow to ownership 1:1, every year, on top of the TIF mechanism. The annual TIF reduction ($158,681 net) only represents the slowing of Note repayment — it is timing, not loss.
A18: • Once the TIF Note retires (every scenario retires the Note before 2046 maturity), the tax savings continue to flow to ownership while the TIF mechanism is gone. Year 10 truncation misses this entirely.

Sheet Notes_vs_IDP_Model
A1: Itemized Differences: This Model vs. IDP/Shaver April 2026 Model
A2: Source: Tom Shaver email 4/17/2026 ("Chamberlain — Analysis on Tax Appeal and CapEx Plan") and attached workbook "Chamberlain — Tax Appeal Analysis 2026 — Updated.xlsx". Severity scale: 🔴 Major (changes the conclusion) / 🟠 Moderate / 🟡 Minor.
A4: # | B4: Issue | C4: IDP/Shaver Treatment | D4: Correct Treatment (this model) | E4: Severity
A5: 1 | B5: Wrong horizon | C5: Truncates analysis at 10 years (2026–2035). TIF Note has NOT paid off by 2035 in any scenario per Shaver Amort_No_Appeal!E12 = $1.77M and Amort_Rolling_Appeal!E12 = $3.06M outstanding at end of year 10. | D5: Runs full 19-year TIF life (2026–2044) until the Note retires. The back-end years are where the tax savings exceed the TIF reduction by the largest margin — truncating discards exactly the period that justifies the appeal. | E5: 🔴 Major
A6: 2 | B6: Wrong starting TMV | C6: Inputs!B6 = "Starting Market Value (2026) = $54,866,000". This is the 1H-2025 TMV per the County roll, NOT the 2026 payable TMV. | D6: County has already set Pay 2026 TMV = $52,151,000 per the same MV History PDF Shaver attached. Starting at $54.866M assumes a reduction the County has already granted. | E6: 🔴 Major
A7: 3 | B7: Wrong appeal target | C7: Inputs!B8 = "Appeal Target Value = $52,150,000" — but Pay 2026 TMV is ALREADY $52,151,000 (Shaver MV History row "2026"). His model effectively appeals from a value the County already reduced FROM, TO a value the County already set IT AT. There is no appeal in the math. | D7: Real pending appeal target per KA Investment Overview pg 13: "$50.0M, consistent with broader reassessment trends." Ehlers stress-tested all the way to the $43.835M MAA floor. | E7: 🔴 Major
A8: 4 | B8: Ignores Ehlers entirely | C8: No mention of Ehlers in the email or workbook. Ehlers is the City's neutral TIF consultant and the source of the actual TIF mechanics used in the project. | D8: Ehlers' published 11/8/25 analysis: net annual TIF reduction = $158,681, 18-yr cumulative tax savings = $2,856,258, lifetime principal slowdown = $180,329, net nominal benefit = $2.68M, NPV @ 5% = ~$1.10M. This model reconciles to within rounding (see Ehlers_Recon tab). | E8: 🔴 Major
A9: 5 | B9: Mis-frames holdback as additive cost | C9: Sensitivity_Analysis A91–F97 treats "rolling holdback" as an economic cost ("19–29% of 10-yr net tax savings offset"). Even his own Year-by-Year tables already include the lag mechanic via the G column (G3:G12 = TIF at $43.835M floor during pending period). | D9: Holdback is a TIMING difference, not a loss. Held-back TIF settles after the appeal resolves. Treating timing as cost is double-counting (already embedded in his Amort_Rolling_Appeal sheet) and exaggerates the negative. | E9: 🟠 Moderate
A10: 6 | B10: Wrong discount rate | C10: Inputs!B14 = 8% discount rate. Applied to future TIF receipts. | D10: TIF Note carries 4.60% interest. KA Nov-25 analysis uses 5% per Ehlers. Discounting future TIF at 8% systematically understates NPV by ~3 pts/yr compounded vs. the asset's actual cost of capital for this cash stream. | E10: 🟠 Moderate
A11: 7 | B11: Wrong sensitivity axis | C11: Sensitivity_Analysis flexes Market Growth Rate. Conclusion: "Under the 5-Yr Historical CAGR (-1.08%) the appeal is slightly net-negative." | D11: Growth rate has minimal effect on the appeal decision because the appealed value (currently $52.15M, MAA floor $43.835M) is below market for at least 5+ years under any plausible growth scenario. The CORRECT sensitivity is over appeal target — every target produces positive net benefit (Sensitivity_Appeal tab). | E11: 🟠 Moderate
A12: 8 | B12: Cherry-picks growth period | C12: Argues for using 5-Yr CAGR (-1.08%) because "post-2021 has been declining 4 of 5 years." Discards the 10-Yr CAGR as "front-loaded." | D12: Both CAGRs are arbitrary. The relevant question is the appeal target, not the growth path. But for completeness: Class rate, tax capacity rate, and MAA floor are FIXED by statute / contract — growth uncertainty is asymmetric to the upside (more growth = bigger appeal opportunity later). | E12: 🟡 Minor
A13: 9 | B13: Ignores TIF Note payoff acceleration | C13: Treats earlier payoff at higher TMV as a "good thing" implicitly (Investor_Summary B6 vs B7, "Difference in Outstanding Balance: $1,287,217.41" framed neutrally). | D13: Per KA Nov-25 pg 14: lower TMV = MORE interest collected on TIF Note over life (TIF Note interest flows to ownership). $50M scenario produces $1.8M MORE interest collected than $54.86M scenario. Shaver omits this entirely. | E13: 🔴 Major
A14: 10 | B14: Misrepresents income restrictions | C14: Investor_Summary A19: "Income Restrictions are removed after TIF is complete" — implying later payoff is bad because affordability lingers. | D14: TIF still retires before contractual maturity (2/1/2046) in EVERY appeal scenario. Per KA Nov-25: aggressive $50M scenario retires Note 2/1/2044. Income restrictions end at TIF termination regardless of appeal. | E14: 🟡 Minor
A15: 11 | B15: Attorney fee structure — fundamental error | C15: Shaver Cash Savings tab applies 25% to EVERY year of tax savings across the 10-year horizon ($373,694 cumulative per Investor_Summary B12). This is wrong on its face: contingency fees are paid ONCE per successful petition, at settlement, equal to 25% of the FIRST YEAR's savings achieved. | D15: Per Attorney_Fees tab: 3 appeal events over 19 years (current + 2030 + 2036), 25% × first-year savings each. Total fee for Aggressive Scenario = ~$98K nominal vs. Shaver's implied $373K. Even with this corrected fee burden subtracted, every scenario remains net positive. Shaver overstates fees ~4-19x depending on appeal cadence. | E15: 🔴 Major
A16: 12 | B16: Misses portfolio precedent | C16: No discussion of recent appeals at the property. | D16: KA Nov-25 Historical TIF table: 2024 TIF Paid = $1,046,813 (vs. 2023 = $418,365). The 2024 figure includes retroactive corrections from prior-year appeals. Appeals at this property have already been productive. | E16: 🟡 Minor
... A19: 15 | B19: Year-6 formula off-by-one errors (formula bugs) | C19: Multiple formulas in Year 6 reference the prior year's values instead of Year 6's own values. Specifically: Increment_Comparison!E8 (TIF No Appeal Yr6) uses B7 instead of B8. Same off-by-one repeats in Sensitivity_Analysis rows H42, H49, H56, H63, H70, H77, H84 (Year-6 TIF Rev Reduction formulas across all 7 sensitivity scenarios). Also Increment_Comparison!C3:C12 (Appeal Value column) and G4:G12 (Pending @ Min) each have a one-row lag. | D19: This model uses indexed formulas that reference each row's own data, eliminating any year-to-year drift. Individual dollar impact per bug is small (~$3K-$25K cumulative across scenarios), but the pattern indicates the Shaver model was not audited — reduces confidence in the larger framing decisions. | E19: 🟡 Minor
